Workbook

Sheet Model_Ready_Startups
A1: startup_id | B1: startup_name | C1: hq_country | D1: hq_city | E1: foreign_hq_flag | F1: entity_type | G1: related_startup_id | H1: possible_duplicate_of | I1: founding_year | J1: founding_month | K1: founding_date_precision | L1: baseline_date | M1: months_since_inception | N1: age_years | O1: industry_raw | P1: sector_group | Q1: business_model_raw | R1: is_b2b | S1: is_b2c | T1: is_marketplace | U1: is_subscription_saas | V1: is_hardware_iot | W1: is_transaction_commission | X1: mvp_status_raw | Y1: product_stage | Z1: mvp_built | AA1: accelerator_participated | AB1: accelerator_programs_raw | AC1: prior_grant_flag | AD1: prior_grants_usd | AE1: grant_info_source | AF1: n_founders | AG1: n_male_founders | AH1: n_female_founders | AI1: female_founder_share | AJ1: has_female_founder | AK1: gender_diversity_blau | AL1: team_female_pct_est | AM1: edu_max_level | AN1: edu_max_label | AO1: any_stem_founder | AP1: stem_share | AQ1: serial_entrepreneur | AR1: industry_exp_max_years | AS1: industry_exp_mean_years | AT1: team_size_mid | AU1: team_size_band | AV1: team_size_source | AW1: team_size_note | AX1: survival_status | AY1: status_confidence | AZ1: status_note | BA1: acquired_flag | BB1: is_acquirer | BC1: event_closed | BD1: closure_year | BE1: closure_month | BF1: duration_months | BG1: follow_on_funding_received | BH1: follow_on_funding_usd | BI1: funding_amount_basis | BJ1: follow_on_year | BK1: any_external_funding | BL1: n_accepted_investment_rows | BM1: has_vc_pe | BN1: has_angel | BO1: has_accelerator_investor | BP1: has_corporate | BQ1: has_government | BR1: has_grant_dfi | BS1: evaluation_score_1to5 | BT1: revenue_growth_pct_mid | BU1: employee_growth_pct_mid | BV1: web_visits_mid | BW1: news_mentions_mid | BX1: social_growth_pct_mid | BY1: app_downloads_lb | BZ1: app_rating | CA1: traction_n_components | CB1: traction_composite | CC1: gdp_growth_at_founding | CD1: inflation_at_founding | CE1: gdp_growth_at_funding | CF1: inflation_at_funding | CG1: n_key_fields_missing | CH1: source_citation | CI1: date_collected
A2: BD-ST-001 | B2: bKash | C2: Bangladesh | D2: Dhaka | E2: 0 | F2: Independent startup | I2: 2010 | K2: year | L2: 46295 | M2: =IF(I2="","",(YEAR(L2)-I2)*12+MONTH(L2)-IF(J2="",1,J2)) -> 200 | N2: =IF(M2="","",ROUND(M2/12,2)) -> 16.67 | O2: Fintech / Payments | P2: Fintech | Q2: Mobile Financial Services (MFS) - B2C/B2B agent network | R2: 1 | S2: 1 | T2: 0 | U2: 0 | V2: 0 | W2: 0 | X2: Active (market-mature; unicorn) | Y2: 3 | Z2: 1 | AA2: 0 | AC2: 1 | AD2: 10000000 | AE2: master | AF2: =IF(SUMIF(Founders_Clean!$A$2:$A$159,A2,Founders_Clean!$C$2:$C$159)=0,"",SUMIF(Founders_Clean!$A$2:$A$159,A2,Founders_Clean!$C$2:$C$159)) -> 2 | AG2: =IF(AF2="","",SUMIF(Founders_Clean!$A$2:$A$159,A2,Founders_Clean!$D$2:$D$159)) -> 2 | AH2: =IF(AF2="","",SUMIF(Founders_Clean!$A$2:$A$159,A2,Founders_Clean!$E$2:$E$159)) -> 0 | AI2: =IF(AF2="","",IF((AG2+AH2)=0,"",AH2/(AG2+AH2))) -> 0 | AJ2: =IF(AI2="","",IF(AH2>0,1,0)) -> 0 | AK2: =IF(AI2="","",ROUND(1-(AI2^2+(1-AI2)^2),3)) -> 0 | AM2: 2 | AN2: Master's/MBA/professional | AO2: 1 | AP2: 0.5 | AQ2: 1 | AR2: 25 | AS2: 20 | AT2: 1750 | AU2: 501+ | AV2: LinkedIn (Public_Macro_Data) | AX2: Active | AY2: High | BA2: 0 | BB2: 0 | BC2: 0 | BF2: =IF(OR(I2="",BC2=""),"",IF(BC2=1,(BD2-I2)*12+IF(BE2="",7,BE2)-IF(J2="",1,J2),M2)) -> 200 | BG2: 1 | BH2: 250000000 | BI2: round | BJ2: 2021 | BK2: 1 | BL2: =COUNTIFS(Investments_Clean!$A$2:$A$150,A2,Investments_Clean!$F$2:$F$150,"Accepted") -> 2 | BM2: =IF(BL2=0,"",IF((COUNTIFS(Investments_Clean!$A$2:$A$150,A2,Investments_Clean!$D$2:$D$150,"VC/PE",Investments_Clean!$F$2:$F$150,"Accepted"))>0,1,0)) -> 1 | BN2: =IF(BL2=0,"",IF((COUNTIFS(Investments_Clean!$A$2:$A$150,A2,Investments_Clean!$D$2:$D$150,"Angel",Investments_Clean!$F$2:$F$150,"Accepted"))>0,1,0)) -> 0 | BO2: =IF(BL2=0,"",IF((COUNTIFS(Investments_Clean!$A$2:$A$150,A2,Investments_Clean!$D$2:$D$150,"Accelerator",Investments_Clean!$F$2:$F$150,"Accepted"))>0,1,0)) -> 0 | BP2: =IF(BL2=0,"",IF((COUNTIFS(Investments_Clean!$A$2:$A$150,A2,Investments_Clean!$D$2:$D$150,"Corporate",Investments_Clean!$F$2:$F$150,"Accepted"))>0,1,0)) -> 0 | BQ2: =IF(BL2=0,"",IF((COUNTIFS(Investments_Clean!$A$2:$A$150,A2,Investments_Clean!$D$2:$D$150,"Government",Investments_Clean!$F$2:$F$150,"Accepted"))>0,1,0)) -> 0 | BR2: =IF(BL2=0,"",IF((COUNTIFS(Investments_Clean!$A$2:$A$150,A2,Investments_Clean!$D$2:$D$150,"Grant/Philanthropic",Investments_Clean!$F$2:$F$150,"Accepted")+COUNTIFS(Investments_Clean!$A$2:$A$150,A2,Investments_Clean!$D$2:$D$150,"DFI/Impact",Investments_Clean!$F$2:$F$150,"Accepted"))>0,1,0)) -> 1 | CA2: 0 | CC2: =IF(I2="","",IFERROR(IF(INDEX(Macro_Lookup!$B$2:$B$31,MATCH(I2,Macro_Lookup!$A$2:$A$31,0))="","",INDEX(Macro_Lookup!$B$2:$B$31,MATCH(I2,Macro_Lookup!$A$2:$A$31,0))),"")) | CD2: =IF(I2="","",IFERROR(IF(INDEX(Macro_Lookup!$C$2:$C$31,MATCH(I2,Macro_Lookup!$A$2:$A$31,0))="","",INDEX(Macro_Lookup!$C$2:$C$31,MATCH(I2,Macro_Lookup!$A$2:$A$31,0))),"")) | CE2: =IF(BJ2="","",IFERROR(IF(INDEX(Macro_Lookup!$B$2:$B$31,MATCH(BJ2,Macro_Lookup!$A$2:$A$31,0))="","",INDEX(Macro_Lookup!$B$2:$B$31,MATCH(BJ2,Macro_Lookup!$A$2:$A$31,0))),"")) | CF2: =IF(BJ2="","",IFERROR(IF(INDEX(Macro_Lookup!$C$2:$C$31,MATCH(BJ2,Macro_Lookup!$A$2:$A$31,0))="","",INDEX(Macro_Lookup!$C$2:$C$31,MATCH(BJ2,Macro_Lookup!$A$2:$A$31,0))),"")) | CG2: 1 | CH2: Original 100 (BD-ST-001..100); see Version_Log v1 (2026-10-06) | CI2: 2026-10-06
A3: BD-ST-002 | B3: Nagad | C3: Bangladesh | D3: Dhaka | E3: 0 | F3: Independent startup | I3: 2019 | K3: year | L3: 46295 | M3: =IF(I3="","",(YEAR(L3)-I3)*12+MONTH(L3)-IF(J3="",1,J3)) -> 92 | N3: =IF(M3="","",ROUND(M3/12,2)) -> 7.67 | O3: Fintech / Payments | P3: Fintech | Q3: MFS (Public-Private Partnership w/ Bangladesh Post Office) | R3: 0 | S3: 0 | T3: 0 | U3: 0 | V3: 0 | W3: 0 | X3: Active | Y3: 3 | Z3: 1 | AF3: =IF(SUMIF(Founders_Clean!$A$2:$A$159,A3,Founders_Clean!$C$2:$C$159)=0,"",SUMIF(Founders_Clean!$A$2:$A$159,A3,Founders_Clean!$C$2:$C$159)) -> 1 | AG3: =IF(AF3="","",SUMIF(Founders_Clean!$A$2:$A$159,A3,Founders_Clean!$D$2:$D$159)) -> 1 | AH3: =IF(AF3="","",SUMIF(Founders_Clean!$A$2:$A$159,A3,Founders_Clean!$E$2:$E$159)) -> 0 | AI3: =IF(AF3="","",IF((AG3+AH3)=0,"",AH3/(AG3+AH3))) -> 0 | AJ3: =IF(AI3="","",IF(AH3>0,1,0)) -> 0 | AK3: =IF(AI3="","",ROUND(1-(AI3^2+(1-AI3)^2),3)) -> 0 | AM3: 2 | AN3: Master's/MBA/professional | AO3: 0 | AP3: 0 | AQ3: 1 | AR3: 11 | AS3: 11 | AT3: 1000 | AU3: 501+ | AV3: LinkedIn (Public_Macro_Data) | AX3: Active | AY3: High | BA3: 0 | BB3: 0 | BC3: 0 | BF3: =IF(OR(I3="",BC3=""),"",IF(BC3=1,(BD3-I3)*12+IF(BE3="",7,BE3)-IF(J3="",1,J3),M3)) -> 92 | BG3: 1 | BI3: unknown | BJ3: 2026 | BK3: 1 | BL3: =COUNTIFS(Investments_Clean!$A$2:$A$150,A3,Investments_Clean!$F$2:$F$150,"Accepted") -> 2 | BM3: =IF(BL3=0,"",IF((COUNTIFS(Investments_Clean!$A$2:$A$150,A3,Investments_Clean!$D$2:$D$150,"VC/PE",Investments_Clean!$F$2:$F$150,"Accepted"))>0,1,0)) -> 0 | BN3: =IF(BL3=0,"",IF((COUNTIFS(Investments_Clean!$A$2:$A$150,A3,Investments_Clean!$D$2:$D$150,"Angel",Investments_Clean!$F$2:$F$150,"Accepted"))>0,1,0)) -> 0 | BO3: =IF(BL3=0,"",IF((COUNTIFS(Investments_Clean!$A$2:$A$150,A3,Investments_Clean!$D$2:$D$150,"Accelerator",Investments_Clean!$F$2:$F$150,"Accepted"))>0,1,0)) -> 0 | BP3: =IF(BL3=0,"",IF((COUNTIFS(Investments_Clean!$A$2:$A$150,A3,Investments_Clean!$D$2:$D$150,"Corporate",Investments_Clean!$F$2:$F$150,"Accepted"))>0,1,0)) -> 1 | BQ3: =IF(BL3=0,"",IF((COUNTIFS(Investments_Clean!$A$2:$A$150,A3,Investments_Clean!$D$2:$D$150,"Government",Investments_Clean!$F$2:$F$150,"Accepted"))>0,1,0)) -> 1 | BR3: =IF(BL3=0,"",IF((COUNTIFS(Investments_Clean!$A$2:$A$150,A3,Investments_Clean!$D$2:$D$150,"Grant/Philanthropic",Investments_Clean!$F$2:$F$150,"Accepted")+COUNTIFS(Investments_Clean!$A$2:$A$150,A3,Investments_Clean!$D$2:$D$150,"DFI/Impact",Investments_Clean!$F$2:$F$150,"Accepted"))>0,1,0)) -> 0 | CA3: 0 | CC3: =IF(I3="","",IFERROR(IF(INDEX(Macro_Lookup!$B$2:$B$31,MATCH(I3,Macro_Lookup!$A$2:$A$31,0))="","",INDEX(Macro_Lookup!$B$2:$B$31,MATCH(I3,Macro_Lookup!$A$2:$A$31,0))),"")) | CD3: =IF(I3="","",IFERROR(IF(INDEX(Macro_Lookup!$C$2:$C$31,MATCH(I3,Macro_Lookup!$A$2:$A$31,0))="","",INDEX(Macro_Lookup!$C$2:$C$31,MATCH(I3,Macro_Lookup!$A$2:$A$31,0))),"")) | CE3: =IF(BJ3="","",IFERROR(IF(INDEX(Macro_Lookup!$B$2:$B$31,MATCH(BJ3,Macro_Lookup!$A$2:$A$31,0))="","",INDEX(Macro_Lookup!$B$2:$B$31,MATCH(BJ3,Macro_Lookup!$A$2:$A$31,0))),"")) | CF3: =IF(BJ3="","",IFERROR(IF(INDEX(Macro_Lookup!$C$2:$C$31,MATCH(BJ3,Macro_Lookup!$A$2:$A$31,0))="","",INDEX(Macro_Lookup!$C$2:$C$31,MATCH(BJ3,Macro_Lookup!$A$2:$A$31,0))),"")) | CG3: 3 | CH3: Original 100 (BD-ST-001..100); see Version_Log v1 (2026-10-06) | CI3: 2026-10-06
A4: BD-ST-003 | B4: Rocket (DBBL Mobile Banking) | C4: Bangladesh | D4: Dhaka | E4: 0 | F4: Corporate division/subsidiary | I4: 2011 | K4: year | L4: 46295 | M4: =IF(I4="","",(YEAR(L4)-I4)*12+MONTH(L4)-IF(J4="",1,J4)) -> 188 | N4: =IF(M4="","",ROUND(M4/12,2)) -> 15.67 | O4: Fintech / Payments | P4: Fintech | Q4: Bank-led MFS Payments (DBBL subsidiary) | R4: 0 | S4: 0 | T4: 0 | U4: 0 | V4: 0 | W4: 0 | X4: Active | Y4: 3 | Z4: 1 | AF4: =IF(SUMIF(Founders_Clean!$A$2:$A$159,A4,Founders_Clean!$C$2:$C$159)=0,"",SUMIF(Founders_Clean!$A$2:$A$159,A4,Founders_Clean!$C$2:$C$159)) -> 1 | AG4: =IF(AF4="","",SUMIF(Founders_Clean!$A$2:$A$159,A4,Founders_Clean!$D$2:$D$159)) -> 1 | AH4: =IF(AF4="","",SUMIF(Founders_Clean!$A$2:$A$159,A4,Founders_Clean!$E$2:$E$159)) -> 0 | AI4: =IF(AF4="","",IF((AG4+AH4)=0,"",AH4/(AG4+AH4))) -> 0 | AJ4: =IF(AI4="","",IF(AH4>0,1,0)) -> 0 | AK4: =IF(AI4="","",ROUND(1-(AI4^2+(1-AI4)^2),3)) -> 0 | AR4: 30 | AS4: 30 | AV4: excluded | AW4: Value is Dutch-Bangla Bank group headcount (projected), not Rocket team size | AX4: Active | AY4: High | BA4: 0 | BB4: 0 | BC4: 0 | BF4: =IF(OR(I4="",BC4=""),"",IF(BC4=1,(BD4-I4)*12+IF(BE4="",7,BE4)-IF(J4="",1,J4),M4)) -> 188 | BG4: 0 | BH4: 0 | BI4: none | BK4: 0 | BL4: =COUNTIFS(Investments_Clean!$A$2:$A$150,A4,Investments_Clean!$F$2:$F$150,"Accepted") -> 1 | BM4: =IF(BL4=0,"",IF((COUNTIFS(Investments_Clean!$A$2:$A$150,A4,Investments_Clean!$D$2:$D$150,"VC/PE",Investments_Clean!$F$2:$F$150,"Accepted"))>0,1,0)) -> 0 | BN4: =IF(BL4=0,"",IF((COUNTIFS(Investments_Clean!$A$2:$A$150,A4,Investments_Clean!$D$2:$D$150,"Angel",Investments_Clean!$F$2:$F$150,"Accepted"))>0,1,0)) -> 0 | BO4: =IF(BL4=0,"",IF((COUNTIFS(Investments_Clean!$A$2:$A$150,A4,Investments_Clean!$D$2:$D$150,"Accelerator",Investments_Clean!$F$2:$F$150,"Accepted"))>0,1,0)) -> 0 | BP4: =IF(BL4=0,"",IF((COUNTIFS(Investments_Clean!$A$2:$A$150,A4,Investments_Clean!$D$2:$D$150,"Corporate",Investments_Clean!$F$2:$F$150,"Accepted"))>0,1,0)) -> 0 | BQ4: =IF(BL4=0,"",IF((COUNTIFS(Investments_Clean!$A$2:$A$150,A4,Investments_Clean!$D$2:$D$150,"Government",Investments_Clean!$F$2:$F$150,"Accepted"))>0,1,0)) -> 0 | BR4: =IF(BL4=0,"",IF((COUNTIFS(Investments_Clean!$A$2:$A$150,A4,Investments_Clean!$D$2:$D$150,"Grant/Philanthropic",Investments_Clean!$F$2:$F$150,"Accepted")+COUNTIFS(Investments_Clean!$A$2:$A$150,A4,Investments_Clean!$D$2:$D$150,"DFI/Impact",Investments_Clean!$F$2:$F$150,"Accepted"))>0,1,0)) -> 0 | CA4: 0 | CC4: =IF(I4="","",IFERROR(IF(INDEX(Macro_Lookup!$B$2:$B$31,MATCH(I4,Macro_Lookup!$A$2:$A$31,0))="","",INDEX(Macro_Lookup!$B$2:$B$31,MATCH(I4,Macro_Lookup!$A$2:$A$31,0))),"")) | CD4: =IF(I4="","",IFERROR(IF(INDEX(Macro_Lookup!$C$2:$C$31,MATCH(I4,Macro_Lookup!$A$2:$A$31,0))="","",INDEX(Macro_Lookup!$C$2:$C$31,MATCH(I4,Macro_Lookup!$A$2:$A$31,0))),"")) | CE4: =IF(BJ4="","",IFERROR(IF(INDEX(Macro_Lookup!$B$2:$B$31,MATCH(BJ4,Macro_Lookup!$A$2:$A$31,0))="","",INDEX(Macro_Lookup!$B$2:$B$31,MATCH(BJ4,Macro_Lookup!$A$2:$A$31,0))),"")) | CF4: =IF(BJ4="","",IFERROR(IF(INDEX(Macro_Lookup!$C$2:$C$31,MATCH(BJ4,Macro_Lookup!$A$2:$A$31,0))="","",INDEX(Macro_Lookup!$C$2:$C$31,MATCH(BJ4,Macro_Lookup!$A$2:$A$31,0))),"")) | CG4: 7 | CH4: Original 100 (BD-ST-001..100); see Version_Log v1 (2026-10-06) | CI4: 2026-10-06
A5: BD-ST-004 | B5: SureCash | C5: Bangladesh | D5: Dhaka | E5: 0 | F5: Independent startup | I5: 2010 | K5: year | L5: 46295 | M5: =IF(I5="","",(YEAR(L5)-I5)*12+MONTH(L5)-IF(J5="",1,J5)) -> 200 | N5: =IF(M5="","",ROUND(M5/12,2)) -> 16.67 | O5: Fintech / Payments | P5: Fintech | Q5: Payment Network Rails / Interoperability Infrastructure | R5: 0 | S5: 0 | T5: 0 | U5: 0 | V5: 0 | W5: 0 | X5: Active | Y5: 3 | Z5: 1 | AA5: 0 | AF5: =IF(SUMIF(Founders_Clean!$A$2:$A$159,A5,Founders_Clean!$C$2:$C$159)=0,"",SUMIF(Founders_Clean!$A$2:$A$159,A5,Founders_Clean!$C$2:$C$159)) -> 1 | AG5: =IF(AF5="","",SUMIF(Founders_Clean!$A$2:$A$159,A5,Founders_Clean!$D$2:$D$159)) -> 1 | AH5: =IF(AF5="","",SUMIF(Founders_Clean!$A$2:$A$159,A5,Founders_Clean!$E$2:$E$159)) -> 0 | AI5: =IF(AF5="","",IF((AG5+AH5)=0,"",AH5/(AG5+AH5))) -> 0 | AJ5: =IF(AI5="","",IF(AH5>0,1,0)) -> 0 | AK5: =IF(AI5="","",ROUND(1-(AI5^2+(1-AI5)^2),3)) -> 0 | AM5: 3 | AN5: PhD | AO5: 1 | AP5: 1 | AQ5: 1 | AR5: 23 | AS5: 23 | AT5: 260 | AU5: 201-500 | AV5: Founders_Team | AX5: Active | AY5: High | BA5: 0 | BB5: 0 | BC5: 0 | BF5: =IF(OR(I5="",BC5=""),"",IF(BC5=1,(BD5-I5)*12+IF(BE5="",7,BE5)-IF(J5="",1,J5),M5)) -> 200 | BG5: 1 | BH5: 7000000 | BI5: round | BJ5: 2015 | BK5: 1 | BL5: =COUNTIFS(Investments_Clean!$A$2:$A$150,A5,Investments_Clean!$F$2:$F$150,"Accepted") -> 1 | BM5: =IF(BL5=0,"",IF((COUNTIFS(Investments_Clean!$A$2:$A$150,A5,Investments_Clean!$D$2:$D$150,"VC/PE",Investments_Clean!$F$2:$F$150,"Accepted"))>0,1,0)) -> 1 | BN5: =IF(BL5=0,"",IF((COUNTIFS(Investments_Clean!$A$2:$A$150,A5,Investments_Clean!$D$2:$D$150,"Angel",Investments_Clean!$F$2:$F$150,"Accepted"))>0,1,0)) -> 0 | BO5: =IF(BL5=0,"",IF((COUNTIFS(Investments_Clean!$A$2:$A$150,A5,Investments_Clean!$D$2:$D$150,"Accelerator",Investments_Clean!$F$2:$F$150,"Accepted"))>0,1,0)) -> 0 | BP5: =IF(BL5=0,"",IF((COUNTIFS(Investments_Clean!$A$2:$A$150,A5,Investments_Clean!$D$2:$D$150,"Corporate",Investments_Clean!$F$2:$F$150,"Accepted"))>0,1,0)) -> 0 | BQ5: =IF(BL5=0,"",IF((COUNTIFS(Investments_Clean!$A$2:$A$150,A5,Investments_Clean!$D$2:$D$150,"Government",Investments_Clean!$F$2:$F$150,"Accepted"))>0,1,0)) -> 0 | BR5: =IF(BL5=0,"",IF((COUNTIFS(Investments_Clean!$A$2:$A$150,A5,Investments_Clean!$D$2:$D$150,"Grant/Philanthropic",Investments_Clean!$F$2:$F$150,"Accepted")+COUNTIFS(Investments_Clean!$A$2:$A$150,A5,Investments_Clean!$D$2:$D$150,"DFI/Impact",Investments_Clean!$F$2:$F$150,"Accepted"))>0,1,0)) -> 0 | CA5: 0 | CC5: =IF(I5="","",IFERROR(IF(INDEX(Macro_Lookup!$B$2:$B$31,MATCH(I5,Macro_Lookup!$A$2:$A$31,0))="","",INDEX(Macro_Lookup!$B$2:$B$31,MATCH(I5,Macro_Lookup!$A$2:$A$31,0))),"")) | CD5: =IF(I5="","",IFERROR(IF(INDEX(Macro_Lookup!$C$2:$C$31,MATCH(I5,Macro_Lookup!$A$2:$A$31,0))="","",INDEX(Macro_Lookup!$C$2:$C$31,MATCH(I5,Macro_Lookup!$A$2:$A$31,0))),"")) | CE5: =IF(BJ5="","",IFERROR(IF(INDEX(Macro_Lookup!$B$2:$B$31,MATCH(BJ5,Macro_Lookup!$A$2:$A$31,0))="","",INDEX(Macro_Lookup!$B$2:$B$31,MATCH(BJ5,Macro_Lookup!$A$2:$A$31,0))),"")) | CF5: =IF(BJ5="","",IFERROR(IF(INDEX(Macro_Lookup!$C$2:$C$31,MATCH(BJ5,Macro_Lookup!$A$2:$A$31,0))="","",INDEX(Macro_Lookup!$C$2:$C$31,MATCH(BJ5,Macro_Lookup!$A$2:$A$31,0))),"")) | CG5: 2 | CH5: Original 100 (BD-ST-001..100); see Version_Log v1 (2026-10-06) | CI5: 2026-10-06
A6: BD-ST-005 | B6: Upay | C6: Bangladesh | D6: Dhaka | E6: 0 | F6: Corporate division/subsidiary | G6: BD-ST-008 | I6: 2021 | K6: year | L6: 46295 | M6: =IF(I6="","",(YEAR(L6)-I6)*12+MONTH(L6)-IF(J6="",1,J6)) -> 68 | N6: =IF(M6="","",ROUND(M6/12,2)) -> 5.67 | O6: Fintech / Payments | P6: Fintech | Q6: MFS (blockchain-based ledger; UCB subsidiary) | R6: 0 | S6: 0 | T6: 0 | U6: 0 | V6: 0 | W6: 0 | X6: Active | Y6: 3 | Z6: 1 | AF6: =IF(SUMIF(Founders_Clean!$A$2:$A$159,A6,Founders_Clean!$C$2:$C$159)=0,"",SUMIF(Founders_Clean!$A$2:$A$159,A6,Founders_Clean!$C$2:$C$159)) -> 1 | AG6: =IF(AF6="","",SUMIF(Founders_Clean!$A$2:$A$159,A6,Founders_Clean!$D$2:$D$159)) -> 1 | AH6: =IF(AF6="","",SUMIF(Founders_Clean!$A$2:$A$159,A6,Founders_Clean!$E$2:$E$159)) -> 0 | AI6: =IF(AF6="","",IF((AG6+AH6)=0,"",AH6/(AG6+AH6))) -> 0 | AJ6: =IF(AI6="","",IF(AH6>0,1,0)) -> 0 | AK6: =IF(AI6="","",ROUND(1-(AI6^2+(1-AI6)^2),3)) -> 0 | AM6: 2 | AN6: Master's/MBA/professional | AO6: 0 | AP6: 0 | AQ6: 0 | AR6: 20 | AS6: 20 | AT6: 350 | AU6: 201-500 | AV6: LinkedIn (Public_Macro_Data) | AX6: Active | AY6: High | BA6: 0 | BB6: 0 | BC6: 0 | BF6: =IF(OR(I6="",BC6=""),"",IF(BC6=1,(BD6-I6)*12+IF(BE6="",7,BE6)-IF(J6="",1,J6),M6)) -> 68 | BG6: 0 | BH6: 0 | BI6: none | BJ6: 2021 | BK6: 0 | BL6: =COUNTIFS(Investments_Clean!$A$2:$A$150,A6,Investments_Clean!$F$2:$F$150,"Accepted") -> 1 | BM6: =IF(BL6=0,"",IF((COUNTIFS(Investments_Clean!$A$2:$A$150,A6,Investments_Clean!$D$2:$D$150,"VC/PE",Investments_Clean!$F$2:$F$150,"Accepted"))>0,1,0)) -> 0 | BN6: =IF(BL6=0,"",IF((COUNTIFS(Investments_Clean!$A$2:$A$150,A6,Investments_Clean!$D$2:$D$150,"Angel",Investments_Clean!$F$2:$F$150,"Accepted"))>0,1,0)) -> 0 | BO6: =IF(BL6=0,"",IF((COUNTIFS(Investments_Clean!$A$2:$A$150,A6,Investments_Clean!$D$2:$D$150,"Accelerator",Investments_Clean!$F$2:$F$150,"Accepted"))>0,1,0)) -> 0 | BP6: =IF(BL6=0,"",IF((COUNTIFS(Investments_Clean!$A$2:$A$150,A6,Investments_Clean!$D$2:$D$150,"Corporate",Investments_Clean!$F$2:$F$150,"Accepted"))>0,1,0)) -> 0 | BQ6: =IF(BL6=0,"",IF((COUNTIFS(Investments_Clean!$A$2:$A$150,A6,Investments_Clean!$D$2:$D$150,"Government",Investments_Clean!$F$2:$F$150,"Accepted"))>0,1,0)) -> 0 | BR6: =IF(BL6=0,"",IF((COUNTIFS(Investments_Clean!$A$2:$A$150,A6,Investments_Clean!$D$2:$D$150,"Grant/Philanthropic",Investments_Clean!$F$2:$F$150,"Accepted")+COUNTIFS(Investments_Clean!$A$2:$A$150,A6,Investments_Clean!$D$2:$D$150,"DFI/Impact",Investments_Clean!$F$2:$F$150,"Accepted"))>0,1,0)) -> 0 | CA6: 0 | CC6: =IF(I6="","",IFERROR(IF(INDEX(Macro_Lookup!$B$2:$B$31,MATCH(I6,Macro_Lookup!$A$2:$A$31,0))="","",INDEX(Macro_Lookup!$B$2:$B$31,MATCH(I6,Macro_Lookup!$A$2:$A$31,0))),"")) | CD6: =IF(I6="","",IFERROR(IF(INDEX(Macro_Lookup!$C$2:$C$31,MATCH(I6,Macro_Lookup!$A$2:$A$31,0))="","",INDEX(Macro_Lookup!$C$2:$C$31,MATCH(I6,Macro_Lookup!$A$2:$A$31,0))),"")) | CE6: =IF(BJ6="","",IFERROR(IF(INDEX(Macro_Lookup!$B$2:$B$31,MATCH(BJ6,Macro_Lookup!$A$2:$A$31,0))="","",INDEX(Macro_Lookup!$B$2:$B$31,MATCH(BJ6,Macro_Lookup!$A$2:$A$31,0))),"")) | CF6: =IF(BJ6="","",IFERROR(IF(INDEX(Macro_Lookup!$C$2:$C$31,MATCH(BJ6,Macro_Lookup!$A$2:$A$31,0))="","",INDEX(Macro_Lookup!$C$2:$C$31,MATCH(BJ6,Macro_Lookup!$A$2:$A$31,0))),"")) | CG6: 3 | CH6: Original 100 (BD-ST-001..100); see Version_Log v1 (2026-10-06) | CI6: 2026-10-06
A7: BD-ST-006 | B7: Dmoney | C7: Bangladesh | D7: Dhaka | E7: 0 | F7: Independent startup | I7: 2016 | K7: year | L7: 46295 | M7: =IF(I7="","",(YEAR(L7)-I7)*12+MONTH(L7)-IF(J7="",1,J7)) -> 128 | N7: =IF(M7="","",ROUND(M7/12,2)) -> 10.67 | O7: Fintech / Payments | P7: Fintech | Q7: Digital Wallet | R7: 0 | S7: 0 | T7: 0 | U7: 0 | V7: 0 | W7: 0 | X7: Active | Y7: 3 | Z7: 1 | AF7: =IF(SUMIF(Founders_Clean!$A$2:$A$159,A7,Founders_Clean!$C$2:$C$159)=0,"",SUMIF(Founders_Clean!$A$2:$A$159,A7,Founders_Clean!$C$2:$C$159)) -> 2 | AG7: =IF(AF7="","",SUMIF(Founders_Clean!$A$2:$A$159,A7,Founders_Clean!$D$2:$D$159)) -> 1 | AH7: =IF(AF7="","",SUMIF(Founders_Clean!$A$2:$A$159,A7,Founders_Clean!$E$2:$E$159)) -> 1 | AI7: =IF(AF7="","",IF((AG7+AH7)=0,"",AH7/(AG7+AH7))) -> 0.5 | AJ7: =IF(AI7="","",IF(AH7>0,1,0)) -> 1 | AK7: =IF(AI7="","",ROUND(1-(AI7^2+(1-AI7)^2),3)) -> 0.5 | AM7: 2 | AN7: Master's/MBA/professional | AO7: 1 | AP7: 1 | AQ7: 1 | AR7: 25 | AS7: 22.5 | AT7: 150 | AU7: 51-200 | AV7: LinkedIn (Public_Macro_Data) | AX7: Active | AY7: High | BA7: 0 | BB7: 0 | BC7: 0 | BF7: =IF(OR(I7="",BC7=""),"",IF(BC7=1,(BD7-I7)*12+IF(BE7="",7,BE7)-IF(J7="",1,J7),M7)) -> 128 | BG7: 1 | BH7: 5000000 | BI7: round | BJ7: 2019 | BK7: 1 | BL7: =COUNTIFS(Investments_Clean!$A$2:$A$150,A7,Investments_Clean!$F$2:$F$150,"Accepted") -> 1 | BM7: =IF(BL7=0,"",IF((COUNTIFS(Investments_Clean!$A$2:$A$150,A7,Investments_Clean!$D$2:$D$150,"VC/PE",Investments_Clean!$F$2:$F$150,"Accepted"))>0,1,0)) -> 0 | BN7: =IF(BL7=0,"",IF((COUNTIFS(Investments_Clean!$A$2:$A$150,A7,Investments_Clean!$D$2:$D$150,"Angel",Investments_Clean!$F$2:$F$150,"Accepted"))>0,1,0)) -> 0 | BO7: =IF(BL7=0,"",IF((COUNTIFS(Investments_Clean!$A$2:$A$150,A7,Investments_Clean!$D$2:$D$150,"Accelerator",Investments_Clean!$F$2:$F$150,"Accepted"))>0,1,0)) -> 0 | BP7: =IF(BL7=0,"",IF((COUNTIFS(Investments_Clean!$A$2:$A$150,A7,Investments_Clean!$D$2:$D$150,"Corporate",Investments_Clean!$F$2:$F$150,"Accepted"))>0,1,0)) -> 1 | BQ7: =IF(BL7=0,"",IF((COUNTIFS(Investments_Clean!$A$2:$A$150,A7,Investments_Clean!$D$2:$D$150,"Government",Investments_Clean!$F$2:$F$150,"Accepted"))>0,1,0)) -> 0 | BR7: =IF(BL7=0,"",IF((COUNTIFS(Investments_Clean!$A$2:$A$150,A7,Investments_Clean!$D$2:$D$150,"Grant/Philanthropic",Investments_Clean!$F$2:$F$150,"Accepted")+COUNTIFS(Investments_Clean!$A$2:$A$150,A7,Investments_Clean!$D$2:$D$150,"DFI/Impact",Investments_Clean!$F$2:$F$150,"Accepted"))>0,1,0)) -> 0 | CA7: 0 | CC7: =IF(I7="","",IFERROR(IF(INDEX(Macro_Lookup!$B$2:$B$31,MATCH(I7,Macro_Lookup!$A$2:$A$31,0))="","",INDEX(Macro_Lookup!$B$2:$B$31,MATCH(I7,Macro_Lookup!$A$2:$A$31,0))),"")) | CD7: =IF(I7="","",IFERROR(IF(INDEX(Macro_Lookup!$C$2:$C$31,MATCH(I7,Macro_Lookup!$A$2:$A$31,0))="","",INDEX(Macro_Lookup!$C$2:$C$31,MATCH(I7,Macro_Lookup!$A$2:$A$31,0))),"")) | CE7: =IF(BJ7="","",IFERROR(IF(INDEX(Macro_Lookup!$B$2:$B$31,MATCH(BJ7,Macro_Lookup!$A$2:$A$31,0))="","",INDEX(Macro_Lookup!$B$2:$B$31,MATCH(BJ7,Macro_Lookup!$A$2:$A$31,0))),"")) | CF7: =IF(BJ7="","",IFERROR(IF(INDEX(Macro_Lookup!$C$2:$C$31,MATCH(BJ7,Macro_Lookup!$A$2:$A$31,0))="","",INDEX(Macro_Lookup!$C$2:$C$31,MATCH(BJ7,Macro_Lookup!$A$2:$A$31,0))),"")) | CG7: 3 | CH7: Original 100 (BD-ST-001..100); see Version_Log v1 (2026-10-06) | CI7: 2026-10-06
A8: BD-ST-007 | B8: PayWell | C8: Bangladesh | D8: Dhaka | E8: 0 | F8: Independent startup | I8: 2012 | J8: 11 | K8: month | L8: 46295 | M8: =IF(I8="","",(YEAR(L8)-I8)*12+MONTH(L8)-IF(J8="",1,J8)) -> 166 | N8: =IF(M8="","",ROUND(M8/12,2)) -> 13.83 | O8: Fintech / Payments | P8: Fintech | Q8: B2C/B2B utility, telecom & financial transaction retail aggregator (POS/agent network) | R8: 1 | S8: 1 | T8: 1 | U8: 0 | V8: 0 | W8: 1 | X8: Acquired (by ShopUp, Bangladeshi B2B commerce platform) | Y8: 3 | Z8: 1 | AC8: 0 | AD8: 0 | AE8: master | AF8: =IF(SUMIF(Founders_Clean!$A$2:$A$159,A8,Founders_Clean!$C$2:$C$159)=0,"",SUMIF(Founders_Clean!$A$2:$A$159,A8,Founders_Clean!$C$2:$C$159)) -> 2 | AG8: =IF(AF8="","",SUMIF(Founders_Clean!$A$2:$A$159,A8,Founders_Clean!$D$2:$D$159)) -> 1 | AH8: =IF(AF8="","",SUMIF(Founders_Clean!$A$2:$A$159,A8,Founders_Clean!$E$2:$E$159)) -> 0 | AI8: =IF(AF8="","",IF((AG8+AH8)=0,"",AH8/(AG8+AH8))) -> 0 | AJ8: =IF(AI8="","",IF(AH8>0,1,0)) -> 0 | AK8: =IF(AI8="","",ROUND(1-(AI8^2+(1-AI8)^2),3)) -> 0 | AM8: 0 | AN8: Below bachelor | AO8: 0 | AP8: 0 | AQ8: 1 | AR8: 15 | AS8: 15 | AT8: 200 | AU8: 51-200 | AV8: Founders_Team | AW8: Parent-company scale (CloudWell), not PayWell alone | AX8: Acquired | AY8: High | BA8: 1 | BB8: 0 | BC8: 0 | BF8: =IF(OR(I8="",BC8=""),"",IF(BC8=1,(BD8-I8)*12+IF(BE8="",7,BE8)-IF(J8="",1,J8),M8)) -> 166 | BL8: =COUNTIFS(Investments_Clean!$A$2:$A$150,A8,Investments_Clean!$F$2:$F$150,"Accepted") -> 0 | BM8: =IF(BL8=0,"",IF((COUNTIFS(Investments_Clean!$A$2:$A$150,A8,Investments_Clean!$D$2:$D$150,"VC/PE",Investments_Clean!$F$2:$F$150,"Accepted"))>0,1,0)) | BN8: =IF(BL8=0,"",IF((COUNTIFS(Investments_Clean!$A$2:$A$150,A8,Investments_Clean!$D$2:$D$150,"Angel",Investments_Clean!$F$2:$F$150,"Accepted"))>0,1,0)) | BO8: =IF(BL8=0,"",IF((COUNTIFS(Investments_Clean!$A$2:$A$150,A8,Investments_Clean!$D$2:$D$150,"Accelerator",Investments_Clean!$F$2:$F$150,"Accepted"))>0,1,0)) | BP8: =IF(BL8=0,"",IF((COUNTIFS(Investments_Clean!$A$2:$A$150,A8,Investments_Clean!$D$2:$D$150,"Corporate",Investments_Clean!$F$2:$F$150,"Accepted"))>0,1,0)) | BQ8: =IF(BL8=0,"",IF((COUNTIFS(Investments_Clean!$A$2:$A$150,A8,Investments_Clean!$D$2:$D$150,"Government",Investments_Clean!$F$2:$F$150,"Accepted"))>0,1,0)) | BR8: =IF(BL8=0,"",IF((COUNTIFS(Investments_Clean!$A$2:$A$150,A8,Investments_Clean!$D$2:$D$150,"Grant/Philanthropic",Investments_Clean!$F$2:$F$150,"Accepted")+COUNTIFS(Investments_Clean!$A$2:$A$150,A8,Investments_Clean!$D$2:$D$150,"DFI/Impact",Investments_Clean!$F$2:$F$150,"Accepted"))>0,1,0)) | CA8: 0 | CC8: =IF(I8="","",IFERROR(IF(INDEX(Macro_Lookup!$B$2:$B$31,MATCH(I8,Macro_Lookup!$A$2:$A$31,0))="","",INDEX(Macro_Lookup!$B$2:$B$31,MATCH(I8,Macro_Lookup!$A$2:$A$31,0))),"")) | CD8: =IF(I8="","",IFERROR(IF(INDEX(Macro_Lookup!$C$2:$C$31,MATCH(I8,Macro_Lookup!$A$2:$A$31,0))="","",INDEX(Macro_Lookup!$C$2:$C$31,MATCH(I8,Macro_Lookup!$A$2:$A$31,0))),"")) | CE8: =IF(BJ8="","",IFERROR(IF(INDEX(Macro_Lookup!$B$2:$B$31,MATCH(BJ8,Macro_Lookup!$A$2:$A$31,0))="","",INDEX(Macro_Lookup!$B$2:$B$31,MATCH(BJ8,Macro_Lookup!$A$2:$A$31,0))),"")) | CF8: =IF(BJ8="","",IFERROR(IF(INDEX(Macro_Lookup!$C$2:$C$31,MATCH(BJ8,Macro_Lookup!$A$2:$A$31,0))="","",INDEX(Macro_Lookup!$C$2:$C$31,MATCH(BJ8,Macro_Lookup!$A$2:$A$31,0))),"")) | CG8: 2 | CH8: Original 100 (BD-ST-001..100); see Version_Log v1 (2026-10-06) | CI8: 2026-10-06
A9: BD-ST-008 | B9: Ucash | C9: Bangladesh | D9: Dhaka | E9: 0 | F9: Corporate division/subsidiary | G9: BD-ST-005 | I9: 2013 | K9: year | L9: 46295 | M9: =IF(I9="","",(YEAR(L9)-I9)*12+MONTH(L9)-IF(J9="",1,J9)) -> 164 | N9: =IF(M9="","",ROUND(M9/12,2)) -> 13.67 | O9: Fintech / Payments | P9: Fintech | Q9: MFS Payments | R9: 0 | S9: 0 | T9: 0 | U9: 0 | V9: 0 | W9: 0 | X9: Closed (migrated users to Upay, 2021) | Y9: 3 | Z9: 1 | AA9: 0 | AF9: =IF(SUMIF(Founders_Clean!$A$2:$A$159,A9,Founders_Clean!$C$2:$C$159)=0,"",SUMIF(Founders_Clean!$A$2:$A$159,A9,Founders_Clean!$C$2:$C$159)) -> 1 | AG9: =IF(AF9="","",SUMIF(Founders_Clean!$A$2:$A$159,A9,Founders_Clean!$D$2:$D$159)) -> 0 | AH9: =IF(AF9="","",SUMIF(Founders_Clean!$A$2:$A$159,A9,Founders_Clean!$E$2:$E$159)) -> 0 | AI9: =IF(AF9="","",IF((AG9+AH9)=0,"",AH9/(AG9+AH9))) | AJ9: =IF(AI9="","",IF(AH9>0,1,0)) | AK9: =IF(AI9="","",ROUND(1-(AI9^2+(1-AI9)^2),3)) | AT9: 150 | AU9: 51-200 | AV9: LinkedIn (Public_Macro_Data) | AX9: Closed | AY9: High | AZ9: Closed 2021; users migrated to Upay (BD-ST-005) | BA9: 0 | BB9: 0 | BC9: 1 | BD9: 2021 | BF9: =IF(OR(I9="",BC9=""),"",IF(BC9=1,(BD9-I9)*12+IF(BE9="",7,BE9)-IF(J9="",1,J9),M9)) -> 102 | BG9: 0 | BH9: 0 | BI9: none | BK9: 0 | BL9: =COUNTIFS(Investments_Clean!$A$2:$A$150,A9,Investments_Clean!$F$2:$F$150,"Accepted") -> 1 | BM9: =IF(BL9=0,"",IF((COUNTIFS(Investments_Clean!$A$2:$A$150,A9,Investments_Clean!$D$2:$D$150,"VC/PE",Investments_Clean!$F$2:$F$150,"Accepted"))>0,1,0)) -> 0 | BN9: =IF(BL9=0,"",IF((COUNTIFS(Investments_Clean!$A$2:$A$150,A9,Investments_Clean!$D$2:$D$150,"Angel",Investments_Clean!$F$2:$F$150,"Accepted"))>0,1,0)) -> 0 | BO9: =IF(BL9=0,"",IF((COUNTIFS(Investments_Clean!$A$2:$A$150,A9,Investments_Clean!$D$2:$D$150,"Accelerator",Investments_Clean!$F$2:$F$150,"Accepted"))>0,1,0)) -> 0 | BP9: =IF(BL9=0,"",IF((COUNTIFS(Investments_Clean!$A$2:$A$150,A9,Investments_Clean!$D$2:$D$150,"Corporate",Investments_Clean!$F$2:$F$150,"Accepted"))>0,1,0)) -> 0 | BQ9: =IF(BL9=0,"",IF((COUNTIFS(Investments_Clean!$A$2:$A$150,A9,Investments_Clean!$D$2:$D$150,"Government",Investments_Clean!$F$2:$F$150,"Accepted"))>0,1,0)) -> 0 | BR9: =IF(BL9=0,"",IF((COUNTIFS(Investments_Clean!$A$2:$A$150,A9,Investments_Clean!$D$2:$D$150,"Grant/Philanthropic",Investments_Clean!$F$2:$F$150,"Accepted")+COUNTIFS(Investments_Clean!$A$2:$A$150,A9,Investments_Clean!$D$2:$D$150,"DFI/Impact",Investments_Clean!$F$2:$F$150,"Accepted"))>0,1,0)) -> 0 | CA9: 0 | CC9: =IF(I9="","",IFERROR(IF(INDEX(Macro_Lookup!$B$2:$B$31,MATCH(I9,Macro_Lookup!$A$2:$A$31,0))="","",INDEX(Macro_Lookup!$B$2:$B$31,MATCH(I9,Macro_Lookup!$A$2:$A$31,0))),"")) | CD9: =IF(I9="","",IFERROR(IF(INDEX(Macro_Lookup!$C$2:$C$31,MATCH(I9,Macro_Lookup!$A$2:$A$31,0))="","",INDEX(Macro_Lookup!$C$2:$C$31,MATCH(I9,Macro_Lookup!$A$2:$A$31,0))),"")) | CE9: =IF(BJ9="","",IFERROR(IF(INDEX(Macro_Lookup!$B$2:$B$31,MATCH(BJ9,Macro_Lookup!$A$2:$A$31,0))="","",INDEX(Macro_Lookup!$B$2:$B$31,MATCH(BJ9,Macro_Lookup!$A$2:$A$31,0))),"")) | CF9: =IF(BJ9="","",IFERROR(IF(INDEX(Macro_Lookup!$C$2:$C$31,MATCH(BJ9,Macro_Lookup!$A$2:$A$31,0))="","",INDEX(Macro_Lookup!$C$2:$C$31,MATCH(BJ9,Macro_Lookup!$A$2:$A$31,0))),"")) | CG9: 6 | CH9: Original 100 (BD-ST-001..100); see Version_Log v1 (2026-10-06) | CI9: 2026-10-06
A10: BD-ST-009 | B10: AamarPay | C10: Bangladesh | D10: Dhaka | E10: 0 | F10: Independent startup | I10: 2015 | K10: year | L10: 46295 | M10: =IF(I10="","",(YEAR(L10)-I10)*12+MONTH(L10)-IF(J10="",1,J10)) -> 140 | N10: =IF(M10="","",ROUND(M10/12,2)) -> 11.67 | O10: Fintech / Payments | P10: Fintech | Q10: Payment Gateway (PSO) | R10: 0 | S10: 0 | T10: 0 | U10: 0 | V10: 0 | W10: 0 | X10: Active | Y10: 3 | Z10: 1 | AF10: =IF(SUMIF(Founders_Clean!$A$2:$A$159,A10,Founders_Clean!$C$2:$C$159)=0,"",SUMIF(Founders_Clean!$A$2:$A$159,A10,Founders_Clean!$C$2:$C$159)) -> 1 | AG10: =IF(AF10="","",SUMIF(Founders_Clean!$A$2:$A$159,A10,Founders_Clean!$D$2:$D$159)) -> 1 | AH10: =IF(AF10="","",SUMIF(Founders_Clean!$A$2:$A$159,A10,Founders_Clean!$E$2:$E$159)) -> 0 | AI10: =IF(AF10="","",IF((AG10+AH10)=0,"",AH10/(AG10+AH10))) -> 0 | AJ10: =IF(AI10="","",IF(AH10>0,1,0)) -> 0 | AK10: =IF(AI10="","",ROUND(1-(AI10^2+(1-AI10)^2),3)) -> 0 | AM10: 1 | AN10: Bachelor's | AO10: 1 | AP10: 1 | AQ10: 1 | AR10: 10 | AS10: 10 | AT10: 100 | AU10: 51-200 | AV10: LinkedIn (Public_Macro_Data) | AX10: Active | AY10: High | AZ10: Acquired by Simpaisa March 2026; still operating | BA10: 1 | BB10: 0 | BC10: 0 | BF10: =IF(OR(I10="",BC10=""),"",IF(BC10=1,(BD10-I10)*12+IF(BE10="",7,BE10)-IF(J10="",1,J10),M10)) -> 140 | BG10: 1 | BH10: 1100000 | BI10: cumulative | BJ10: 2026 | BK10: 1 | BL10: =COUNTIFS(Investments_Clean!$A$2:$A$150,A10,Investments_Clean!$F$2:$F$150,"Accepted") -> 2 | BM10: =IF(BL10=0,"",IF((COUNTIFS(Investments_Clean!$A$2:$A$150,A10,Investments_Clean!$D$2:$D$150,"VC/PE",Investments_Clean!$F$2:$F$150,"Accepted"))>0,1,0)) -> 0 | BN10: =IF(BL10=0,"",IF((COUNTIFS(Investments_Clean!$A$2:$A$150,A10,Investments_Clean!$D$2:$D$150,"Angel",Investments_Clean!$F$2:$F$150,"Accepted"))>0,1,0)) -> 1 | BO10: =IF(BL10=0,"",IF((COUNTIFS(Investments_Clean!$A$2:$A$150,A10,Investments_Clean!$D$2:$D$150,"Accelerator",Investments_Clean!$F$2:$F$150,"Accepted"))>0,1,0)) -> 0 | BP10: =IF(BL10=0,"",IF((COUNTIFS(Investments_Clean!$A$2:$A$150,A10,Investments_Clean!$D$2:$D$150,"Corporate",Investments_Clean!$F$2:$F$150,"Accepted"))>0,1,0)) -> 1 | BQ10: =IF(BL10=0,"",IF((COUNTIFS(Investments_Clean!$A$2:$A$150,A10,Investments_Clean!$D$2:$D$150,"Government",Investments_Clean!$F$2:$F$150,"Accepted"))>0,1,0)) -> 0 | BR10: =IF(BL10=0,"",IF((COUNTIFS(Investments_Clean!$A$2:$A$150,A10,Investments_Clean!$D$2:$D$150,"Grant/Philanthropic",Investments_Clean!$F$2:$F$150,"Accepted")+COUNTIFS(Investments_Clean!$A$2:$A$150,A10,Investments_Clean!$D$2:$D$150,"DFI/Impact",Investments_Clean!$F$2:$F$150,"Accepted"))>0,1,0)) -> 0 | CA10: 0 | CC10: =IF(I10="","",IFERROR(IF(INDEX(Macro_Lookup!$B$2:$B$31,MATCH(I10,Macro_Lookup!$A$2:$A$31,0))="","",INDEX(Macro_Lookup!$B$2:$B$31,MATCH(I10,Macro_Lookup!$A$2:$A$31,0))),"")) | CD10: =IF(I10="","",IFERROR(IF(INDEX(Macro_Lookup!$C$2:$C$31,MATCH(I10,Macro_Lookup!$A$2:$A$31,0))="","",INDEX(Macro_Lookup!$C$2:$C$31,MATCH(I10,Macro_Lookup!$A$2:$A$31,0))),"")) | CE10: =IF(BJ10="","",IFERROR(IF(INDEX(Macro_Lookup!$B$2:$B$31,MATCH(BJ10,Macro_Lookup!$A$2:$A$31,0))="","",INDEX(Macro_Lookup!$B$2:$B$31,MATCH(BJ10,Macro_Lookup!$A$2:$A$31,0))),"")) | CF10: =IF(BJ10="","",IFERROR(IF(INDEX(Macro_Lookup!$C$2:$C$31,MATCH(BJ10,Macro_Lookup!$A$2:$A$31,0))="","",INDEX(Macro_Lookup!$C$2:$C$31,MATCH(BJ10,Macro_Lookup!$A$2:$A$31,0))),"")) | CG10: 3 | CH10: Original 100 (BD-ST-001..100); see Version_Log v1 (2026-10-06) | CI10: 2026-10-06
A11: BD-ST-010 | B11: SSLCOMMERZ | C11: Bangladesh | D11: Dhaka | E11: 0 | F11: Independent startup | I11: 2010 | K11: year | L11: 46295 | M11: =IF(I11="","",(YEAR(L11)-I11)*12+MONTH(L11)-IF(J11="",1,J11)) -> 200 | N11: =IF(M11="","",ROUND(M11/12,2)) -> 16.67 | O11: Fintech / Payments | P11: Fintech | Q11: Payment Gateway (PSO) | R11: 0 | S11: 0 | T11: 0 | U11: 0 | V11: 0 | W11: 0 | X11: Active | Y11: 3 | Z11: 1 | AF11: =IF(SUMIF(Founders_Clean!$A$2:$A$159,A11,Founders_Clean!$C$2:$C$159)=0,"",SUMIF(Founders_Clean!$A$2:$A$159,A11,Founders_Clean!$C$2:$C$159)) -> 1 | AG11: =IF(AF11="","",SUMIF(Founders_Clean!$A$2:$A$159,A11,Founders_Clean!$D$2:$D$159)) -> 1 | AH11: =IF(AF11="","",SUMIF(Founders_Clean!$A$2:$A$159,A11,Founders_Clean!$E$2:$E$159)) -> 0 | AI11: =IF(AF11="","",IF((AG11+AH11)=0,"",AH11/(AG11+AH11))) -> 0 | AJ11: =IF(AI11="","",IF(AH11>0,1,0)) -> 0 | AK11: =IF(AI11="","",ROUND(1-(AI11^2+(1-AI11)^2),3)) -> 0 | AM11: 2 | AN11: Master's/MBA/professional | AO11: 1 | AP11: 1 | AQ11: 1 | AR11: 25 | AS11: 25 | AT11: 275 | AU11: 201-500 | AV11: LinkedIn (Public_Macro_Data) | AX11: Active | AY11: High | BA11: 0 | BB11: 0 | BC11: 0 | BF11: =IF(OR(I11="",BC11=""),"",IF(BC11=1,(BD11-I11)*12+IF(BE11="",7,BE11)-IF(J11="",1,J11),M11)) -> 200 | BG11: 0 | BH11: 0 | BI11: none | BK11: 0 | BL11: =COUNTIFS(Investments_Clean!$A$2:$A$150,A11,Investments_Clean!$F$2:$F$150,"Accepted") -> 0 | BM11: =IF(BL11=0,"",IF((COUNTIFS(Investments_Clean!$A$2:$A$150,A11,Investments_Clean!$D$2:$D$150,"VC/PE",Investments_Clean!$F$2:$F$150,"Accepted"))>0,1,0)) | BN11: =IF(BL11=0,"",IF((COUNTIFS(Investments_Clean!$A$2:$A$150,A11,Investments_Clean!$D$2:$D$150,"Angel",Investments_Clean!$F$2:$F$150,"Accepted"))>0,1,0)) | BO11: =IF(BL11=0,"",IF((COUNTIFS(Investments_Clean!$A$2:$A$150,A11,Investments_Clean!$D$2:$D$150,"Accelerator",Investments_Clean!$F$2:$F$150,"Accepted"))>0,1,0)) | BP11: =IF(BL11=0,"",IF((COUNTIFS(Investments_Clean!$A$2:$A$150,A11,Investments_Clean!$D$2:$D$150,"Corporate",Investments_Clean!$F$2:$F$150,"Accepted"))>0,1,0)) | BQ11: =IF(BL11=0,"",IF((COUNTIFS(Investments_Clean!$A$2:$A$150,A11,Investments_Clean!$D$2:$D$150,"Government",Investments_Clean!$F$2:$F$150,"Accepted"))>0,1,0)) | BR11: =IF(BL11=0,"",IF((COUNTIFS(Investments_Clean!$A$2:$A$150,A11,Investments_Clean!$D$2:$D$150,"Grant/Philanthropic",Investments_Clean!$F$2:$F$150,"Accepted")+COUNTIFS(Investments_Clean!$A$2:$A$150,A11,Investments_Clean!$D$2:$D$150,"DFI/Impact",Investments_Clean!$F$2:$F$150,"Accepted"))>0,1,0)) | CA11: 0 | CC11: =IF(I11="","",IFERROR(IF(INDEX(Macro_Lookup!$B$2:$B$31,MATCH(I11,Macro_Lookup!$A$2:$A$31,0))="","",INDEX(Macro_Lookup!$B$2:$B$31,MATCH(I11,Macro_Lookup!$A$2:$A$31,0))),"")) | CD11: =IF(I11="","",IFERROR(IF(INDEX(Macro_Lookup!$C$2:$C$31,MATCH(I11,Macro_Lookup!$A$2:$A$31,0))="","",INDEX(Macro_Lookup!$C$2:$C$31,MATCH(I11,Macro_Lookup!$A$2:$A$31,0))),"")) | CE11: =IF(BJ11="","",IFERROR(IF(INDEX(Macro_Lookup!$B$2:$B$31,MATCH(BJ11,Macro_Lookup!$A$2:$A$31,0))="","",INDEX(Macro_Lookup!$B$2:$B$31,MATCH(BJ11,Macro_Lookup!$A$2:$A$31,0))),"")) | CF11: =IF(BJ11="","",IFERROR(IF(INDEX(Macro_Lookup!$C$2:$C$31,MATCH(BJ11,Macro_Lookup!$A$2:$A$31,0))="","",INDEX(Macro_Lookup!$C$2:$C$31,MATCH(BJ11,Macro_Lookup!$A$2:$A$31,0))),"")) | CG11: 3 | CH11: Original 100 (BD-ST-001..100); see Version_Log v1 (2026-10-06) | CI11: 2026-10-06
A12: BD-ST-011 | B12: Muthopay | C12: Bangladesh | D12: Dhaka | E12: 0 | F12: Independent startup | K12: unknown | L12: 46295 | M12: =IF(I12="","",(YEAR(L12)-I12)*12+MONTH(L12)-IF(J12="",1,J12)) | N12: =IF(M12="","",ROUND(M12/12,2)) | O12: Fintech / Payments | P12: Fintech | Q12: Payment Gateway (Bluetooth / low-bandwidth transactions) | R12: 0 | S12: 0 | T12: 0 | U12: 0 | V12: 0 | W12: 1 | X12: Active | Y12: 3 | Z12: 1 | AA12: 0 | AF12: =IF(SUMIF(Founders_Clean!$A$2:$A$159,A12,Founders_Clean!$C$2:$C$159)=0,"",SUMIF(Founders_Clean!$A$2:$A$159,A12,Founders_Clean!$C$2:$C$159)) -> 1 | AG12: =IF(AF12="","",SUMIF(Founders_Clean!$A$2:$A$159,A12,Founders_Clean!$D$2:$D$159)) -> 1 | AH12: =IF(AF12="","",SUMIF(Founders_Clean!$A$2:$A$159,A12,Founders_Clean!$E$2:$E$159)) -> 0 | AI12: =IF(AF12="","",IF((AG12+AH12)=0,"",AH12/(AG12+AH12))) -> 0 | AJ12: =IF(AI12="","",IF(AH12>0,1,0)) -> 0 | AK12: =IF(AI12="","",ROUND(1-(AI12^2+(1-AI12)^2),3)) -> 0 | AQ12: 1 | AR12: 17 | AS12: 17 | AT12: 5.5 | AU12: 1-10 | AV12: Founders_Team | AX12: Active | AY12: High | BA12: 0 | BB12: 0 | BC12: 0 | BF12: =IF(OR(I12="",BC12=""),"",IF(BC12=1,(BD12-I12)*12+IF(BE12="",7,BE12)-IF(J12="",1,J12),M12)) | BG12: 1 | BH12: 37100 | BI12: round | BJ12: 2020 | BK12: 1 | BL12: =COUNTIFS(Investments_Clean!$A$2:$A$150,A12,Investments_Clean!$F$2:$F$150,"Accepted") -> 1 | BM12: =IF(BL12=0,"",IF((COUNTIFS(Investments_Clean!$A$2:$A$150,A12,Investments_Clean!$D$2:$D$150,"VC/PE",Investments_Clean!$F$2:$F$150,"Accepted"))>0,1,0)) -> 0 | BN12: =IF(BL12=0,"",IF((COUNTIFS(Investments_Clean!$A$2:$A$150,A12,Investments_Clean!$D$2:$D$150,"Angel",Investments_Clean!$F$2:$F$150,"Accepted"))>0,1,0)) -> 0 | BO12: =IF(BL12=0,"",IF((COUNTIFS(Investments_Clean!$A$2:$A$150,A12,Investments_Clean!$D$2:$D$150,"Accelerator",Investments_Clean!$F$2:$F$150,"Accepted"))>0,1,0)) -> 1 | BP12: =IF(BL12=0,"",IF((COUNTIFS(Investments_Clean!$A$2:$A$150,A12,Investments_Clean!$D$2:$D$150,"Corporate",Investments_Clean!$F$2:$F$150,"Accepted"))>0,1,0)) -> 0 | BQ12: =IF(BL12=0,"",IF((COUNTIFS(Investments_Clean!$A$2:$A$150,A12,Investments_Clean!$D$2:$D$150,"Government",Investments_Clean!$F$2:$F$150,"Accepted"))>0,1,0)) -> 0 | BR12: =IF(BL12=0,"",IF((COUNTIFS(Investments_Clean!$A$2:$A$150,A12,Investments_Clean!$D$2:$D$150,"Grant/Philanthropic",Investments_Clean!$F$2:$F$150,"Accepted")+COUNTIFS(Investments_Clean!$A$2:$A$150,A12,Investments_Clean!$D$2:$D$150,"DFI/Impact",Investments_Clean!$F$2:$F$150,"Accepted"))>0,1,0)) -> 0 | CA12: 0 | CC12: =IF(I12="","",IFERROR(IF(INDEX(Macro_Lookup!$B$2:$B$31,MATCH(I12,Macro_Lookup!$A$2:$A$31,0))="","",INDEX(Macro_Lookup!$B$2:$B$31,MATCH(I12,Macro_Lookup!$A$2:$A$31,0))),"")) | CD12: =IF(I12="","",IFERROR(IF(INDEX(Macro_Lookup!$C$2:$C$31,MATCH(I12,Macro_Lookup!$A$2:$A$31,0))="","",INDEX(Macro_Lookup!$C$2:$C$31,MATCH(I12,Macro_Lookup!$A$2:$A$31,0))),"")) | CE12: =IF(BJ12="","",IFERROR(IF(INDEX(Macro_Lookup!$B$2:$B$31,MATCH(BJ12,Macro_Lookup!$A$2:$A$31,0))="","",INDEX(Macro_Lookup!$B$2:$B$31,MATCH(BJ12,Macro_Lookup!$A$2:$A$31,0))),"")) | CF12: =IF(BJ12="","",IFERROR(IF(INDEX(Macro_Lookup!$C$2:$C$31,MATCH(BJ12,Macro_Lookup!$A$2:$A$31,0))="","",INDEX(Macro_Lookup!$C$2:$C$31,MATCH(BJ12,Macro_Lookup!$A$2:$A$31,0))),"")) | CG12: 4 | CH12: Original 100 (BD-ST-001..100); see Version_Log v1 (2026-10-06) | CI12: 2026-10-06
A13: BD-ST-012 | B13: Tredx | C13: Bangladesh | D13: Dhaka | E13: 0 | F13: Independent startup | I13: 2022 | J13: 8 | K13: month | L13: 46295 | M13: =IF(I13="","",(YEAR(L13)-I13)*12+MONTH(L13)-IF(J13="",1,J13)) -> 49 | N13: =IF(M13="","",ROUND(M13/12,2)) -> 4.08 | O13: Fintech / Digital Lending | P13: Fintech | Q13: Digital supply chain finance / online invoice factoring marketplace | R13: 0 | S13: 0 | T13: 1 | U13: 0 | V13: 0 | W13: 0 | X13: Active (live production platform; integrated w/ Midland Bank PLC) | Y13: 3 | Z13: 1 | AA13: 0 | AC13: 0 | AD13: 0 | AE13: master | AF13: =IF(SUMIF(Founders_Clean!$A$2:$A$159,A13,Founders_Clean!$C$2:$C$159)=0,"",SUMIF(Founders_Clean!$A$2:$A$159,A13,Founders_Clean!$C$2:$C$159)) -> 3 | AG13: =IF(AF13="","",SUMIF(Founders_Clean!$A$2:$A$159,A13,Founders_Clean!$D$2:$D$159)) -> 3 | AH13: =IF(AF13="","",SUMIF(Founders_Clean!$A$2:$A$159,A13,Founders_Clean!$E$2:$E$159)) -> 0 | AI13: =IF(AF13="","",IF((AG13+AH13)=0,"",AH13/(AG13+AH13))) -> 0 | AJ13: =IF(AI13="","",IF(AH13>0,1,0)) -> 0 | AK13: =IF(AI13="","",ROUND(1-(AI13^2+(1-AI13)^2),3)) -> 0 | AM13: 3 | AN13: PhD | AO13: 0 | AP13: 0 | AQ13: 1 | AR13: 20 | AS13: 20 | AT13: 30.5 | AU13: 11-50 | AV13: Founders_Team | AX13: Active | AY13: High | BA13: 0 | BB13: 0 | BC13: 0 | BF13: =IF(OR(I13="",BC13=""),"",IF(BC13=1,(BD13-I13)*12+IF(BE13="",7,BE13)-IF(J13="",1,J13),M13)) -> 49 | BL13: =COUNTIFS(Investments_Clean!$A$2:$A$150,A13,Investments_Clean!$F$2:$F$150,"Accepted") -> 0 | BM13: =IF(BL13=0,"",IF((COUNTIFS(Investments_Clean!$A$2:$A$150,A13,Investments_Clean!$D$2:$D$150,"VC/PE",Investments_Clean!$F$2:$F$150,"Accepted"))>0,1,0)) | BN13: =IF(BL13=0,"",IF((COUNTIFS(Investments_Clean!$A$2:$A$150,A13,Investments_Clean!$D$2:$D$150,"Angel",Investments_Clean!$F$2:$F$150,"Accepted"))>0,1,0)) | BO13: =IF(BL13=0,"",IF((COUNTIFS(Investments_Clean!$A$2:$A$150,A13,Investments_Clean!$D$2:$D$150,"Accelerator",Investments_Clean!$F$2:$F$150,"Accepted"))>0,1,0)) | BP13: =IF(BL13=0,"",IF((COUNTIFS(Investments_Clean!$A$2:$A$150,A13,Investments_Clean!$D$2:$D$150,"Corporate",Investments_Clean!$F$2:$F$150,"Accepted"))>0,1,0)) | BQ13: =IF(BL13=0,"",IF((COUNTIFS(Investments_Clean!$A$2:$A$150,A13,Investments_Clean!$D$2:$D$150,"Government",Investments_Clean!$F$2:$F$150,"Accepted"))>0,1,0)) | BR13: =IF(BL13=0,"",IF((COUNTIFS(Investments_Clean!$A$2:$A$150,A13,Investments_Clean!$D$2:$D$150,"Grant/Philanthropic",Investments_Clean!$F$2:$F$150,"Accepted")+COUNTIFS(Investments_Clean!$A$2:$A$150,A13,Investments_Clean!$D$2:$D$150,"DFI/Impact",Investments_Clean!$F$2:$F$150,"Accepted"))>0,1,0)) | CA13: 0 | CC13: =IF(I13="","",IFERROR(IF(INDEX(Macro_Lookup!$B$2:$B$31,MATCH(I13,Macro_Lookup!$A$2:$A$31,0))="","",INDEX(Macro_Lookup!$B$2:$B$31,MATCH(I13,Macro_Lookup!$A$2:$A$31,0))),"")) | CD13: =IF(I13="","",IFERROR(IF(INDEX(Macro_Lookup!$C$2:$C$31,MATCH(I13,Macro_Lookup!$A$2:$A$31,0))="","",INDEX(Macro_Lookup!$C$2:$C$31,MATCH(I13,Macro_Lookup!$A$2:$A$31,0))),"")) | CE13: =IF(BJ13="","",IFERROR(IF(INDEX(Macro_Lookup!$B$2:$B$31,MATCH(BJ13,Macro_Lookup!$A$2:$A$31,0))="","",INDEX(Macro_Lookup!$B$2:$B$31,MATCH(BJ13,Macro_Lookup!$A$2:$A$31,0))),"")) | CF13: =IF(BJ13="","",IFERROR(IF(INDEX(Macro_Lookup!$C$2:$C$31,MATCH(BJ13,Macro_Lookup!$A$2:$A$31,0))="","",INDEX(Macro_Lookup!$C$2:$C$31,MATCH(BJ13,Macro_Lookup!$A$2:$A$31,0))),"")) | CG13: 1 | CH13: Original 100 (BD-ST-001..100); see Version_Log v1 (2026-10-06) | CI13: 2026-10-06
A14: BD-ST-013 | B14: Chaldal | C14: Bangladesh | D14: Dhaka | E14: 0 | F14: Independent startup | I14: 2013 | J14: 9 | K14: month | L14: 46295 | M14: =IF(I14="","",(YEAR(L14)-I14)*12+MONTH(L14)-IF(J14="",1,J14)) -> 156 | N14: =IF(M14="","",ROUND(M14/12,2)) -> 13 | O14: E-commerce / Grocery | P14: E-commerce | Q14: Micro-warehouse ('nano-warehouse') grocery retail | R14: 0 | S14: 0 | T14: 0 | U14: 0 | V14: 0 | W14: 0 | X14: Active | Y14: 3 | Z14: 1 | AA14: 1 | AB14: Y Combinator | AF14: =IF(SUMIF(Founders_Clean!$A$2:$A$159,A14,Founders_Clean!$C$2:$C$159)=0,"",SUMIF(Founders_Clean!$A$2:$A$159,A14,Founders_Clean!$C$2:$C$159)) -> 3 | AG14: =IF(AF14="","",SUMIF(Founders_Clean!$A$2:$A$159,A14,Founders_Clean!$D$2:$D$159)) -> 3 | AH14: =IF(AF14="","",SUMIF(Founders_Clean!$A$2:$A$159,A14,Founders_Clean!$E$2:$E$159)) -> 0 | AI14: =IF(AF14="","",IF((AG14+AH14)=0,"",AH14/(AG14+AH14))) -> 0 | AJ14: =IF(AI14="","",IF(AH14>0,1,0)) -> 0 | AK14: =IF(AI14="","",ROUND(1-(AI14^2+(1-AI14)^2),3)) -> 0 | AM14: 2 | AN14: Master's/MBA/professional | AO14: 1 | AP14: 0.33333333 | AQ14: 1 | AR14: 10 | AS14: 10 | AT14: 1549.5 | AU14: 501+ | AV14: Founders_Team | AX14: Active | AY14: High | BA14: 0 | BB14: 0 | BC14: 0 | BF14: =IF(OR(I14="",BC14=""),"",IF(BC14=1,(BD14-I14)*12+IF(BE14="",7,BE14)-IF(J14="",1,J14),M14)) -> 156 | BG14: 1 | BH14: 30000000 | BI14: cumulative | BJ14: 2024 | BK14: 1 | BL14: =COUNTIFS(Investments_Clean!$A$2:$A$150,A14,Investments_Clean!$F$2:$F$150,"Accepted") -> 2 | BM14: =IF(BL14=0,"",IF((COUNTIFS(Investments_Clean!$A$2:$A$150,A14,Investments_Clean!$D$2:$D$150,"VC/PE",Investments_Clean!$F$2:$F$150,"Accepted"))>0,1,0)) -> 1 | BN14: =IF(BL14=0,"",IF((COUNTIFS(Investments_Clean!$A$2:$A$150,A14,Investments_Clean!$D$2:$D$150,"Angel",Investments_Clean!$F$2:$F$150,"Accepted"))>0,1,0)) -> 0 | BO14: =IF(BL14=0,"",IF((COUNTIFS(Investments_Clean!$A$2:$A$150,A14,Investments_Clean!$D$2:$D$150,"Accelerator",Investments_Clean!$F$2:$F$150,"Accepted"))>0,1,0)) -> 0 | BP14: =IF(BL14=0,"",IF((COUNTIFS(Investments_Clean!$A$2:$A$150,A14,Investments_Clean!$D$2:$D$150,"Corporate",Investments_Clean!$F$2:$F$150,"Accepted"))>0,1,0)) -> 0 | BQ14: =IF(BL14=0,"",IF((COUNTIFS(Investments_Clean!$A$2:$A$150,A14,Investments_Clean!$D$2:$D$150,"Government",Investments_Clean!$F$2:$F$150,"Accepted"))>0,1,0)) -> 0 | BR14: =IF(BL14=0,"",IF((COUNTIFS(Investments_Clean!$A$2:$A$150,A14,Investments_Clean!$D$2:$D$150,"Grant/Philanthropic",Investments_Clean!$F$2:$F$150,"Accepted")+COUNTIFS(Investments_Clean!$A$2:$A$150,A14,Investments_Clean!$D$2:$D$150,"DFI/Impact",Investments_Clean!$F$2:$F$150,"Accepted"))>0,1,0)) -> 0 | CA14: 0 | CC14: =IF(I14="","",IFERROR(IF(INDEX(Macro_Lookup!$B$2:$B$31,MATCH(I14,Macro_Lookup!$A$2:$A$31,0))="","",INDEX(Macro_Lookup!$B$2:$B$31,MATCH(I14,Macro_Lookup!$A$2:$A$31,0))),"")) | CD14: =IF(I14="","",IFERROR(IF(INDEX(Macro_Lookup!$C$2:$C$31,MATCH(I14,Macro_Lookup!$A$2:$A$31,0))="","",INDEX(Macro_Lookup!$C$2:$C$31,MATCH(I14,Macro_Lookup!$A$2:$A$31,0))),"")) | CE14: =IF(BJ14="","",IFERROR(IF(INDEX(Macro_Lookup!$B$2:$B$31,MATCH(BJ14,Macro_Lookup!$A$2:$A$31,0))="","",INDEX(Macro_Lookup!$B$2:$B$31,MATCH(BJ14,Macro_Lookup!$A$2:$A$31,0))),"")) | CF14: =IF(BJ14="","",IFERROR(IF(INDEX(Macro_Lookup!$C$2:$C$31,MATCH(BJ14,Macro_Lookup!$A$2:$A$31,0))="","",INDEX(Macro_Lookup!$C$2:$C$31,MATCH(BJ14,Macro_Lookup!$A$2:$A$31,0))),"")) | CG14: 2 | CH14: Original 100 (BD-ST-001..100); see Version_Log v1 (2026-10-06) | CI14: 2026-10-06
A15: BD-ST-014 | B15: Daraz Bangladesh | C15: Bangladesh | D15: Dhaka | E15: 0 | F15: Independent startup (acquired by corporate) | I15: 2012 | K15: year | L15: 46295 | M15: =IF(I15="","",(YEAR(L15)-I15)*12+MONTH(L15)-IF(J15="",1,J15)) -> 176 | N15: =IF(M15="","",ROUND(M15/12,2)) -> 14.67 | O15: E-commerce / Marketplace | P15: E-commerce | Q15: Horizontal Marketplace | R15: 0 | S15: 0 | T15: 1 | U15: 0 | V15: 0 | W15: 0 | X15: Active | Y15: 3 | Z15: 1 | AA15: 0 | AF15: =IF(SUMIF(Founders_Clean!$A$2:$A$159,A15,Founders_Clean!$C$2:$C$159)=0,"",SUMIF(Founders_Clean!$A$2:$A$159,A15,Founders_Clean!$C$2:$C$159)) -> 2 | AG15: =IF(AF15="","",SUMIF(Founders_Clean!$A$2:$A$159,A15,Founders_Clean!$D$2:$D$159)) -> 0 | AH15: =IF(AF15="","",SUMIF(Founders_Clean!$A$2:$A$159,A15,Founders_Clean!$E$2:$E$159)) -> 0 | AI15: =IF(AF15="","",IF((AG15+AH15)=0,"",AH15/(AG15+AH15))) | AJ15: =IF(AI15="","",IF(AH15>0,1,0)) | AK15: =IF(AI15="","",ROUND(1-(AI15^2+(1-AI15)^2),3)) | AT15: 1000 | AU15: 501+ | AV15: LinkedIn (Public_Macro_Data) | AX15: Active | AY15: High | BA15: 1 | BB15: 0 | BC15: 0 | BF15: =IF(OR(I15="",BC15=""),"",IF(BC15=1,(BD15-I15)*12+IF(BE15="",7,BE15)-IF(J15="",1,J15),M15)) -> 176 | BK15: 1 | BL15: =COUNTIFS(Investments_Clean!$A$2:$A$150,A15,Investments_Clean!$F$2:$F$150,"Accepted") -> 1 | BM15: =IF(BL15=0,"",IF((COUNTIFS(Investments_Clean!$A$2:$A$150,A15,Investments_Clean!$D$2:$D$150,"VC/PE",Investments_Clean!$F$2:$F$150,"Accepted"))>0,1,0)) -> 0 | BN15: =IF(BL15=0,"",IF((COUNTIFS(Investments_Clean!$A$2:$A$150,A15,Investments_Clean!$D$2:$D$150,"Angel",Investments_Clean!$F$2:$F$150,"Accepted"))>0,1,0)) -> 0 | BO15: =IF(BL15=0,"",IF((COUNTIFS(Investments_Clean!$A$2:$A$150,A15,Investments_Clean!$D$2:$D$150,"Accelerator",Investments_Clean!$F$2:$F$150,"Accepted"))>0,1,0)) -> 0 | BP15: =IF(BL15=0,"",IF((COUNTIFS(Investments_Clean!$A$2:$A$150,A15,Investments_Clean!$D$2:$D$150,"Corporate",Investments_Clean!$F$2:$F$150,"Accepted"))>0,1,0)) -> 1 | BQ15: =IF(BL15=0,"",IF((COUNTIFS(Investments_Clean!$A$2:$A$150,A15,Investments_Clean!$D$2:$D$150,"Government",Investments_Clean!$F$2:$F$150,"Accepted"))>0,1,0)) -> 0 | BR15: =IF(BL15=0,"",IF((COUNTIFS(Investments_Clean!$A$2:$A$150,A15,Investments_Clean!$D$2:$D$150,"Grant/Philanthropic",Investments_Clean!$F$2:$F$150,"Accepted")+COUNTIFS(Investments_Clean!$A$2:$A$150,A15,Investments_Clean!$D$2:$D$150,"DFI/Impact",Investments_Clean!$F$2:$F$150,"Accepted"))>0,1,0)) -> 0 | CA15: 0 | CC15: =IF(I15="","",IFERROR(IF(INDEX(Macro_Lookup!$B$2:$B$31,MATCH(I15,Macro_Lookup!$A$2:$A$31,0))="","",INDEX(Macro_Lookup!$B$2:$B$31,MATCH(I15,Macro_Lookup!$A$2:$A$31,0))),"")) | CD15: =IF(I15="","",IFERROR(IF(INDEX(Macro_Lookup!$C$2:$C$31,MATCH(I15,Macro_Lookup!$A$2:$A$31,0))="","",INDEX(Macro_Lookup!$C$2:$C$31,MATCH(I15,Macro_Lookup!$A$2:$A$31,0))),"")) | CE15: =IF(BJ15="","",IFERROR(IF(INDEX(Macro_Lookup!$B$2:$B$31,MATCH(BJ15,Macro_Lookup!$A$2:$A$31,0))="","",INDEX(Macro_Lookup!$B$2:$B$31,MATCH(BJ15,Macro_Lookup!$A$2:$A$31,0))),"")) | CF15: =IF(BJ15="","",IFERROR(IF(INDEX(Macro_Lookup!$C$2:$C$31,MATCH(BJ15,Macro_Lookup!$A$2:$A$31,0))="","",INDEX(Macro_Lookup!$C$2:$C$31,MATCH(BJ15,Macro_Lookup!$A$2:$A$31,0))),"")) | CG15: 6 | CH15: Original 100 (BD-ST-001..100); see Version_Log v1 (2026-10-06) | CI15: 2026-10-06
A16: BD-ST-015 | B16: AjkerDeal | C16: Bangladesh | D16: Dhaka | E16: 0 | F16: Independent startup | I16: 2011 | K16: year | L16: 46295 | M16: =IF(I16="","",(YEAR(L16)-I16)*12+MONTH(L16)-IF(J16="",1,J16)) -> 188 | N16: =IF(M16="","",ROUND(M16/12,2)) -> 15.67 | O16: E-commerce / Marketplace | P16: E-commerce | Q16: B2C Marketplace | R16: 0 | S16: 1 | T16: 1 | U16: 0 | V16: 0 | W16: 0 | X16: Active | Y16: 3 | Z16: 1 | AF16: =IF(SUMIF(Founders_Clean!$A$2:$A$159,A16,Founders_Clean!$C$2:$C$159)=0,"",SUMIF(Founders_Clean!$A$2:$A$159,A16,Founders_Clean!$C$2:$C$159)) -> 1 | AG16: =IF(AF16="","",SUMIF(Founders_Clean!$A$2:$A$159,A16,Founders_Clean!$D$2:$D$159)) -> 1 | AH16: =IF(AF16="","",SUMIF(Founders_Clean!$A$2:$A$159,A16,Founders_Clean!$E$2:$E$159)) -> 0 | AI16: =IF(AF16="","",IF((AG16+AH16)=0,"",AH16/(AG16+AH16))) -> 0 | AJ16: =IF(AI16="","",IF(AH16>0,1,0)) -> 0 | AK16: =IF(AI16="","",ROUND(1-(AI16^2+(1-AI16)^2),3)) -> 0 | AM16: 2 | AN16: Master's/MBA/professional | AO16: 0 | AP16: 0 | AQ16: 1 | AR16: 25 | AS16: 25 | AT16: 75 | AU16: 51-200 | AV16: LinkedIn (Public_Macro_Data) | AX16: Active | AY16: High | BA16: 0 | BB16: 0 | BC16: 0 | BF16: =IF(OR(I16="",BC16=""),"",IF(BC16=1,(BD16-I16)*12+IF(BE16="",7,BE16)-IF(J16="",1,J16),M16)) -> 188 | BL16: =COUNTIFS(Investments_Clean!$A$2:$A$150,A16,Investments_Clean!$F$2:$F$150,"Accepted") -> 0 | BM16: =IF(BL16=0,"",IF((COUNTIFS(Investments_Clean!$A$2:$A$150,A16,Investments_Clean!$D$2:$D$150,"VC/PE",Investments_Clean!$F$2:$F$150,"Accepted"))>0,1,0)) | BN16: =IF(BL16=0,"",IF((COUNTIFS(Investments_Clean!$A$2:$A$150,A16,Investments_Clean!$D$2:$D$150,"Angel",Investments_Clean!$F$2:$F$150,"Accepted"))>0,1,0)) | BO16: =IF(BL16=0,"",IF((COUNTIFS(Investments_Clean!$A$2:$A$150,A16,Investments_Clean!$D$2:$D$150,"Accelerator",Investments_Clean!$F$2:$F$150,"Accepted"))>0,1,0)) | BP16: =IF(BL16=0,"",IF((COUNTIFS(Investments_Clean!$A$2:$A$150,A16,Investments_Clean!$D$2:$D$150,"Corporate",Investments_Clean!$F$2:$F$150,"Accepted"))>0,1,0)) | BQ16: =IF(BL16=0,"",IF((COUNTIFS(Investments_Clean!$A$2:$A$150,A16,Investments_Clean!$D$2:$D$150,"Government",Investments_Clean!$F$2:$F$150,"Accepted"))>0,1,0)) | BR16: =IF(BL16=0,"",IF((COUNTIFS(Investments_Clean!$A$2:$A$150,A16,Investments_Clean!$D$2:$D$150,"Grant/Philanthropic",Investments_Clean!$F$2:$F$150,"Accepted")+COUNTIFS(Investments_Clean!$A$2:$A$150,A16,Investments_Clean!$D$2:$D$150,"DFI/Impact",Investments_Clean!$F$2:$F$150,"Accepted"))>0,1,0)) | CA16: 0 | CC16: =IF(I16="","",IFERROR(IF(INDEX(Macro_Lookup!$B$2:$B$31,MATCH(I16,Macro_Lookup!$A$2:$A$31,0))="","",INDEX(Macro_Lookup!$B$2:$B$31,MATCH(I16,Macro_Lookup!$A$2:$A$31,0))),"")) | CD16: =IF(I16="","",IFERROR(IF(INDEX(Macro_Lookup!$C$2:$C$31,MATCH(I16,Macro_Lookup!$A$2:$A$31,0))="","",INDEX(Macro_Lookup!$C$2:$C$31,MATCH(I16,Macro_Lookup!$A$2:$A$31,0))),"")) | CE16: =IF(BJ16="","",IFERROR(IF(INDEX(Macro_Lookup!$B$2:$B$31,MATCH(BJ16,Macro_Lookup!$A$2:$A$31,0))="","",INDEX(Macro_Lookup!$B$2:$B$31,MATCH(BJ16,Macro_Lookup!$A$2:$A$31,0))),"")) | CF16: =IF(BJ16="","",IFERROR(IF(INDEX(Macro_Lookup!$C$2:$C$31,MATCH(BJ16,Macro_Lookup!$A$2:$A$31,0))="","",INDEX(Macro_Lookup!$C$2:$C$31,MATCH(BJ16,Macro_Lookup!$A$2:$A$31,0))),"")) | CG16: 3 | CH16: Original 100 (BD-ST-001..100); see Version_Log v1 (2026-10-06) | CI16: 2026-10-06
A17: BD-ST-016 | B17: Rokomari.com | C17: Bangladesh | D17: Dhaka | E17: 0 | F17: Independent startup | I17: 2012 | K17: year | L17: 46295 | M17: =IF(I17="","",(YEAR(L17)-I17)*12+MONTH(L17)-IF(J17="",1,J17)) -> 176 | N17: =IF(M17="","",ROUND(M17/12,2)) -> 14.67 | O17: E-commerce / Books | P17: E-commerce | Q17: Online Bookstore | R17: 0 | S17: 0 | T17: 0 | U17: 0 | V17: 0 | W17: 0 | X17: Active | Y17: 3 | Z17: 1 | AA17: 0 | AF17: =IF(SUMIF(Founders_Clean!$A$2:$A$159,A17,Founders_Clean!$C$2:$C$159)=0,"",SUMIF(Founders_Clean!$A$2:$A$159,A17,Founders_Clean!$C$2:$C$159)) -> 5 | AG17: =IF(AF17="","",SUMIF(Founders_Clean!$A$2:$A$159,A17,Founders_Clean!$D$2:$D$159)) -> 5 | AH17: =IF(AF17="","",SUMIF(Founders_Clean!$A$2:$A$159,A17,Founders_Clean!$E$2:$E$159)) -> 0 | AI17: =IF(AF17="","",IF((AG17+AH17)=0,"",AH17/(AG17+AH17))) -> 0 | AJ17: =IF(AI17="","",IF(AH17>0,1,0)) -> 0 | AK17: =IF(AI17="","",ROUND(1-(AI17^2+(1-AI17)^2),3)) -> 0 | AM17: 2 | AN17: Master's/MBA/professional | AO17: 1 | AP17: 1 | AQ17: 1 | AR17: 10 | AS17: 10 | AT17: 150 | AU17: 51-200 | AV17: Founders_Team | AX17: Active | AY17: High | BA17: 0 | BB17: 0 | BC17: 0 | BF17: =IF(OR(I17="",BC17=""),"",IF(BC17=1,(BD17-I17)*12+IF(BE17="",7,BE17)-IF(J17="",1,J17),M17)) -> 176 | BG17: 0 | BH17: 0 | BI17: none | BK17: 0 | BL17: =COUNTIFS(Investments_Clean!$A$2:$A$150,A17,Investments_Clean!$F$2:$F$150,"Accepted") -> 0 | BM17: =IF(BL17=0,"",IF((COUNTIFS(Investments_Clean!$A$2:$A$150,A17,Investments_Clean!$D$2:$D$150,"VC/PE",Investments_Clean!$F$2:$F$150,"Accepted"))>0,1,0)) | BN17: =IF(BL17=0,"",IF((COUNTIFS(Investments_Clean!$A$2:$A$150,A17,Investments_Clean!$D$2:$D$150,"Angel",Investments_Clean!$F$2:$F$150,"Accepted"))>0,1,0)) | BO17: =IF(BL17=0,"",IF((COUNTIFS(Investments_Clean!$A$2:$A$150,A17,Investments_Clean!$D$2:$D$150,"Accelerator",Investments_Clean!$F$2:$F$150,"Accepted"))>0,1,0)) | BP17: =IF(BL17=0,"",IF((COUNTIFS(Investments_Clean!$A$2:$A$150,A17,Investments_Clean!$D$2:$D$150,"Corporate",Investments_Clean!$F$2:$F$150,"Accepted"))>0,1,0)) | BQ17: =IF(BL17=0,"",IF((COUNTIFS(Investments_Clean!$A$2:$A$150,A17,Investments_Clean!$D$2:$D$150,"Government",Investments_Clean!$F$2:$F$150,"Accepted"))>0,1,0)) | BR17: =IF(BL17=0,"",IF((COUNTIFS(Investments_Clean!$A$2:$A$150,A17,Investments_Clean!$D$2:$D$150,"Grant/Philanthropic",Investments_Clean!$F$2:$F$150,"Accepted")+COUNTIFS(Investments_Clean!$A$2:$A$150,A17,Investments_Clean!$D$2:$D$150,"DFI/Impact",Investments_Clean!$F$2:$F$150,"Accepted"))>0,1,0)) | CA17: 0 | CC17: =IF(I17="","",IFERROR(IF(INDEX(Macro_Lookup!$B$2:$B$31,MATCH(I17,Macro_Lookup!$A$2:$A$31,0))="","",INDEX(Macro_Lookup!$B$2:$B$31,MATCH(I17,Macro_Lookup!$A$2:$A$31,0))),"")) | CD17: =IF(I17="","",IFERROR(IF(INDEX(Macro_Lookup!$C$2:$C$31,MATCH(I17,Macro_Lookup!$A$2:$A$31,0))="","",INDEX(Macro_Lookup!$C$2:$C$31,MATCH(I17,Macro_Lookup!$A$2:$A$31,0))),"")) | CE17: =IF(BJ17="","",IFERROR(IF(INDEX(Macro_Lookup!$B$2:$B$31,MATCH(BJ17,Macro_Lookup!$A$2:$A$31,0))="","",INDEX(Macro_Lookup!$B$2:$B$31,MATCH(BJ17,Macro_Lookup!$A$2:$A$31,0))),"")) | CF17: =IF(BJ17="","",IFERROR(IF(INDEX(Macro_Lookup!$C$2:$C$31,MATCH(BJ17,Macro_Lookup!$A$2:$A$31,0))="","",INDEX(Macro_Lookup!$C$2:$C$31,MATCH(BJ17,Macro_Lookup!$A$2:$A$31,0))),"")) | CG17: 2 | CH17: Original 100 (BD-ST-001..100); see Version_Log v1 (2026-10-06) | CI17: 2026-10-06
A18: BD-ST-017 | B18: Bikroy.com | C18: Bangladesh | D18: Dhaka | E18: 0 | F18: Independent startup | I18: 2012 | K18: year | L18: 46295 | M18: =IF(I18="","",(YEAR(L18)-I18)*12+MONTH(L18)-IF(J18="",1,J18)) -> 176 | N18: =IF(M18="","",ROUND(M18/12,2)) -> 14.67 | O18: E-commerce / Classifieds | P18: E-commerce | Q18: Online Classifieds | R18: 0 | S18: 0 | T18: 0 | U18: 0 | V18: 0 | W18: 0 | X18: Acquired | Y18: 3 | Z18: 1 | AA18: 0 | AF18: =IF(SUMIF(Founders_Clean!$A$2:$A$159,A18,Founders_Clean!$C$2:$C$159)=0,"",SUMIF(Founders_Clean!$A$2:$A$159,A18,Founders_Clean!$C$2:$C$159)) -> 1 | AG18: =IF(AF18="","",SUMIF(Founders_Clean!$A$2:$A$159,A18,Founders_Clean!$D$2:$D$159)) -> 0 | AH18: =IF(AF18="","",SUMIF(Founders_Clean!$A$2:$A$159,A18,Founders_Clean!$E$2:$E$159)) -> 1 | AI18: =IF(AF18="","",IF((AG18+AH18)=0,"",AH18/(AG18+AH18))) -> 1 | AJ18: =IF(AI18="","",IF(AH18>0,1,0)) -> 1 | AK18: =IF(AI18="","",ROUND(1-(AI18^2+(1-AI18)^2),3)) -> 0 | AM18: 1 | AN18: Bachelor's | AO18: 0 | AP18: 0 | AQ18: 0 | AR18: 13 | AS18: 13 | AT18: 427 | AU18: 201-500 | AV18: Founders_Team | AX18: Acquired | AY18: High | AZ18: Acquired by Jiji.com May 2026 | BA18: 1 | BB18: 0 | BC18: 0 | BF18: =IF(OR(I18="",BC18=""),"",IF(BC18=1,(BD18-I18)*12+IF(BE18="",7,BE18)-IF(J18="",1,J18),M18)) -> 176 | BG18: 1 | BH18: 1300000 | BI18: round | BJ18: 2021 | BK18: 1 | BL18: =COUNTIFS(Investments_Clean!$A$2:$A$150,A18,Investments_Clean!$F$2:$F$150,"Accepted") -> 0 | BM18: =IF(BL18=0,"",IF((COUNTIFS(Investments_Clean!$A$2:$A$150,A18,Investments_Clean!$D$2:$D$150,"VC/PE",Investments_Clean!$F$2:$F$150,"Accepted"))>0,1,0)) | BN18: =IF(BL18=0,"",IF((COUNTIFS(Investments_Clean!$A$2:$A$150,A18,Investments_Clean!$D$2:$D$150,"Angel",Investments_Clean!$F$2:$F$150,"Accepted"))>0,1,0)) | BO18: =IF(BL18=0,"",IF((COUNTIFS(Investments_Clean!$A$2:$A$150,A18,Investments_Clean!$D$2:$D$150,"Accelerator",Investments_Clean!$F$2:$F$150,"Accepted"))>0,1,0)) | BP18: =IF(BL18=0,"",IF((COUNTIFS(Investments_Clean!$A$2:$A$150,A18,Investments_Clean!$D$2:$D$150,"Corporate",Investments_Clean!$F$2:$F$150,"Accepted"))>0,1,0)) | BQ18: =IF(BL18=0,"",IF((COUNTIFS(Investments_Clean!$A$2:$A$150,A18,Investments_Clean!$D$2:$D$150,"Government",Investments_Clean!$F$2:$F$150,"Accepted"))>0,1,0)) | BR18: =IF(BL18=0,"",IF((COUNTIFS(Investments_Clean!$A$2:$A$150,A18,Investments_Clean!$D$2:$D$150,"Grant/Philanthropic",Investments_Clean!$F$2:$F$150,"Accepted")+COUNTIFS(Investments_Clean!$A$2:$A$150,A18,Investments_Clean!$D$2:$D$150,"DFI/Impact",Investments_Clean!$F$2:$F$150,"Accepted"))>0,1,0)) | CA18: 0 | CC18: =IF(I18="","",IFERROR(IF(INDEX(Macro_Lookup!$B$2:$B$31,MATCH(I18,Macro_Lookup!$A$2:$A$31,0))="","",INDEX(Macro_Lookup!$B$2:$B$31,MATCH(I18,Macro_Lookup!$A$2:$A$31,0))),"")) | CD18: =IF(I18="","",IFERROR(IF(INDEX(Macro_Lookup!$C$2:$C$31,MATCH(I18,Macro_Lookup!$A$2:$A$31,0))="","",INDEX(Macro_Lookup!$C$2:$C$31,MATCH(I18,Macro_Lookup!$A$2:$A$31,0))),"")) | CE18: =IF(BJ18="","",IFERROR(IF(INDEX(Macro_Lookup!$B$2:$B$31,MATCH(BJ18,Macro_Lookup!$A$2:$A$31,0))="","",INDEX(Macro_Lookup!$B$2:$B$31,MATCH(BJ18,Macro_Lookup!$A$2:$A$31,0))),"")) | CF18: =IF(BJ18="","",IFERROR(IF(INDEX(Macro_Lookup!$C$2:$C$31,MATCH(BJ18,Macro_Lookup!$A$2:$A$31,0))="","",INDEX(Macro_Lookup!$C$2:$C$31,MATCH(BJ18,Macro_Lookup!$A$2:$A$31,0))),"")) | CG18: 2 | CH18: Original 100 (BD-ST-001..100); see Version_Log v1 (2026-10-06) | CI18: 2026-10-06
A19: BD-ST-018 | B19: Pickaboo | C19: Bangladesh | D19: Dhaka | E19: 0 | F19: Independent startup | I19: 2016 | K19: year | L19: 46295 | M19: =IF(I19="","",(YEAR(L19)-I19)*12+MONTH(L19)-IF(J19="",1,J19)) -> 128 | N19: =IF(M19="","",ROUND(M19/12,2)) -> 10.67 | O19: E-commerce / Electronics | P19: E-commerce | Q19: Omnichannel Retail | R19: 0 | S19: 0 | T19: 0 | U19: 0 | V19: 0 | W19: 0 | X19: Active | Y19: 3 | Z19: 1 | AA19: 0 | AF19: =IF(SUMIF(Founders_Clean!$A$2:$A$159,A19,Founders_Clean!$C$2:$C$159)=0,"",SUMIF(Founders_Clean!$A$2:$A$159,A19,Founders_Clean!$C$2:$C$159)) -> 1 | AG19: =IF(AF19="","",SUMIF(Founders_Clean!$A$2:$A$159,A19,Founders_Clean!$D$2:$D$159)) -> 1 | AH19: =IF(AF19="","",SUMIF(Founders_Clean!$A$2:$A$159,A19,Founders_Clean!$E$2:$E$159)) -> 0 | AI19: =IF(AF19="","",IF((AG19+AH19)=0,"",AH19/(AG19+AH19))) -> 0 | AJ19: =IF(AI19="","",IF(AH19>0,1,0)) -> 0 | AK19: =IF(AI19="","",ROUND(1-(AI19^2+(1-AI19)^2),3)) -> 0 | AT19: 150 | AU19: 51-200 | AV19: LinkedIn (Public_Macro_Data) | AX19: Active | AY19: High | BA19: 0 | BB19: 0 | BC19: 0 | BF19: =IF(OR(I19="",BC19=""),"",IF(BC19=1,(BD19-I19)*12+IF(BE19="",7,BE19)-IF(J19="",1,J19),M19)) -> 128 | BG19: 1 | BH19: 1500000 | BI19: round | BJ19: 2023 | BK19: 1 | BL19: =COUNTIFS(Investments_Clean!$A$2:$A$150,A19,Investments_Clean!$F$2:$F$150,"Accepted") -> 1 | BM19: =IF(BL19=0,"",IF((COUNTIFS(Investments_Clean!$A$2:$A$150,A19,Investments_Clean!$D$2:$D$150,"VC/PE",Investments_Clean!$F$2:$F$150,"Accepted"))>0,1,0)) -> 1 | BN19: =IF(BL19=0,"",IF((COUNTIFS(Investments_Clean!$A$2:$A$150,A19,Investments_Clean!$D$2:$D$150,"Angel",Investments_Clean!$F$2:$F$150,"Accepted"))>0,1,0)) -> 0 | BO19: =IF(BL19=0,"",IF((COUNTIFS(Investments_Clean!$A$2:$A$150,A19,Investments_Clean!$D$2:$D$150,"Accelerator",Investments_Clean!$F$2:$F$150,"Accepted"))>0,1,0)) -> 0 | BP19: =IF(BL19=0,"",IF((COUNTIFS(Investments_Clean!$A$2:$A$150,A19,Investments_Clean!$D$2:$D$150,"Corporate",Investments_Clean!$F$2:$F$150,"Accepted"))>0,1,0)) -> 0 | BQ19: =IF(BL19=0,"",IF((COUNTIFS(Investments_Clean!$A$2:$A$150,A19,Investments_Clean!$D$2:$D$150,"Government",Investments_Clean!$F$2:$F$150,"Accepted"))>0,1,0)) -> 0 | BR19: =IF(BL19=0,"",IF((COUNTIFS(Investments_Clean!$A$2:$A$150,A19,Investments_Clean!$D$2:$D$150,"Grant/Philanthropic",Investments_Clean!$F$2:$F$150,"Accepted")+COUNTIFS(Investments_Clean!$A$2:$A$150,A19,Investments_Clean!$D$2:$D$150,"DFI/Impact",Investments_Clean!$F$2:$F$150,"Accepted"))>0,1,0)) -> 0 | CA19: 0 | CC19: =IF(I19="","",IFERROR(IF(INDEX(Macro_Lookup!$B$2:$B$31,MATCH(I19,Macro_Lookup!$A$2:$A$31,0))="","",INDEX(Macro_Lookup!$B$2:$B$31,MATCH(I19,Macro_Lookup!$A$2:$A$31,0))),"")) | CD19: =IF(I19="","",IFERROR(IF(INDEX(Macro_Lookup!$C$2:$C$31,MATCH(I19,Macro_Lookup!$A$2:$A$31,0))="","",INDEX(Macro_Lookup!$C$2:$C$31,MATCH(I19,Macro_Lookup!$A$2:$A$31,0))),"")) | CE19: =IF(BJ19="","",IFERROR(IF(INDEX(Macro_Lookup!$B$2:$B$31,MATCH(BJ19,Macro_Lookup!$A$2:$A$31,0))="","",INDEX(Macro_Lookup!$B$2:$B$31,MATCH(BJ19,Macro_Lookup!$A$2:$A$31,0))),"")) | CF19: =IF(BJ19="","",IFERROR(IF(INDEX(Macro_Lookup!$C$2:$C$31,MATCH(BJ19,Macro_Lookup!$A$2:$A$31,0))="","",INDEX(Macro_Lookup!$C$2:$C$31,MATCH(BJ19,Macro_Lookup!$A$2:$A$31,0))),"")) | CG19: 6 | CH19: Original 100 (BD-ST-001..100); see Version_Log v1 (2026-10-06) | CI19: 2026-10-06
A20: BD-ST-019 | B20: Priyoshop | C20: Bangladesh | D20: Dhaka | E20: 0 | F20: Independent startup | I20: 2021 | K20: year | L20: 46295 | M20: =IF(I20="","",(YEAR(L20)-I20)*12+MONTH(L20)-IF(J20="",1,J20)) -> 68 | N20: =IF(M20="","",ROUND(M20/12,2)) -> 5.67 | O20: E-commerce / B2B Retail | P20: E-commerce | Q20: B2B Retail Marketplace | R20: 1 | S20: 0 | T20: 1 | U20: 0 | V20: 0 | W20: 0 | X20: Active | Y20: 3 | Z20: 1 | AA20: 1 | AB20: Y Combinator | AF20: =IF(SUMIF(Founders_Clean!$A$2:$A$159,A20,Founders_Clean!$C$2:$C$159)=0,"",SUMIF(Founders_Clean!$A$2:$A$159,A20,Founders_Clean!$C$2:$C$159)) -> 2 | AG20: =IF(AF20="","",SUMIF(Founders_Clean!$A$2:$A$159,A20,Founders_Clean!$D$2:$D$159)) -> 1 | AH20: =IF(AF20="","",SUMIF(Founders_Clean!$A$2:$A$159,A20,Founders_Clean!$E$2:$E$159)) -> 1 | AI20: =IF(AF20="","",IF((AG20+AH20)=0,"",AH20/(AG20+AH20))) -> 0.5 | AJ20: =IF(AI20="","",IF(AH20>0,1,0)) -> 1 | AK20: =IF(AI20="","",ROUND(1-(AI20^2+(1-AI20)^2),3)) -> 0.5 | AM20: 2 | AN20: Master's/MBA/professional | AO20: 0 | AP20: 0 | AQ20: 1 | AR20: 20 | AS20: 17 | AT20: 150 | AU20: 51-200 | AV20: LinkedIn (Public_Macro_Data) | AX20: Active | AY20: High | BA20: 0 | BB20: 0 | BC20: 0 | BF20: =IF(OR(I20="",BC20=""),"",IF(BC20=1,(BD20-I20)*12+IF(BE20="",7,BE20)-IF(J20="",1,J20),M20)) -> 68 | BG20: 1 | BH20: 5000000 | BI20: round | BJ20: 2024 | BK20: 1 | BL20: =COUNTIFS(Investments_Clean!$A$2:$A$150,A20,Investments_Clean!$F$2:$F$150,"Accepted") -> 1 | BM20: =IF(BL20=0,"",IF((COUNTIFS(Investments_Clean!$A$2:$A$150,A20,Investments_Clean!$D$2:$D$150,"VC/PE",Investments_Clean!$F$2:$F$150,"Accepted"))>0,1,0)) -> 1 | BN20: =IF(BL20=0,"",IF((COUNTIFS(Investments_Clean!$A$2:$A$150,A20,Investments_Clean!$D$2:$D$150,"Angel",Investments_Clean!$F$2:$F$150,"Accepted"))>0,1,0)) -> 0 | BO20: =IF(BL20=0,"",IF((COUNTIFS(Investments_Clean!$A$2:$A$150,A20,Investments_Clean!$D$2:$D$150,"Accelerator",Investments_Clean!$F$2:$F$150,"Accepted"))>0,1,0)) -> 0 | BP20: =IF(BL20=0,"",IF((COUNTIFS(Investments_Clean!$A$2:$A$150,A20,Investments_Clean!$D$2:$D$150,"Corporate",Investments_Clean!$F$2:$F$150,"Accepted"))>0,1,0)) -> 0 | BQ20: =IF(BL20=0,"",IF((COUNTIFS(Investments_Clean!$A$2:$A$150,A20,Investments_Clean!$D$2:$D$150,"Government",Investments_Clean!$F$2:$F$150,"Accepted"))>0,1,0)) -> 0 | BR20: =IF(BL20=0,"",IF((COUNTIFS(Investments_Clean!$A$2:$A$150,A20,Investments_Clean!$D$2:$D$150,"Grant/Philanthropic",Investments_Clean!$F$2:$F$150,"Accepted")+COUNTIFS(Investments_Clean!$A$2:$A$150,A20,Investments_Clean!$D$2:$D$150,"DFI/Impact",Investments_Clean!$F$2:$F$150,"Accepted"))>0,1,0)) -> 0 | CA20: 0 | CC20: =IF(I20="","",IFERROR(IF(INDEX(Macro_Lookup!$B$2:$B$31,MATCH(I20,Macro_Lookup!$A$2:$A$31,0))="","",INDEX(Macro_Lookup!$B$2:$B$31,MATCH(I20,Macro_Lookup!$A$2:$A$31,0))),"")) | CD20: =IF(I20="","",IFERROR(IF(INDEX(Macro_Lookup!$C$2:$C$31,MATCH(I20,Macro_Lookup!$A$2:$A$31,0))="","",INDEX(Macro_Lookup!$C$2:$C$31,MATCH(I20,Macro_Lookup!$A$2:$A$31,0))),"")) | CE20: =IF(BJ20="","",IFERROR(IF(INDEX(Macro_Lookup!$B$2:$B$31,MATCH(BJ20,Macro_Lookup!$A$2:$A$31,0))="","",INDEX(Macro_Lookup!$B$2:$B$31,MATCH(BJ20,Macro_Lookup!$A$2:$A$31,0))),"")) | CF20: =IF(BJ20="","",IFERROR(IF(INDEX(Macro_Lookup!$C$2:$C$31,MATCH(BJ20,Macro_Lookup!$A$2:$A$31,0))="","",INDEX(Macro_Lookup!$C$2:$C$31,MATCH(BJ20,Macro_Lookup!$A$2:$A$31,0))),"")) | CG20: 2 | CH20: Original 100 (BD-ST-001..100); see Version_Log v1 (2026-10-06) | CI20: 2026-10-06
A21: BD-ST-020 | B21: Sindabad.com | C21: Bangladesh | D21: Dhaka | E21: 0 | F21: Independent startup | I21: 2015 | K21: year | L21: 46295 | M21: =IF(I21="","",(YEAR(L21)-I21)*12+MONTH(L21)-IF(J21="",1,J21)) -> 140 | N21: =IF(M21="","",ROUND(M21/12,2)) -> 11.67 | O21: E-commerce / B2B Procurement | P21: E-commerce | Q21: B2B Procurement | R21: 1 | S21: 0 | T21: 0 | U21: 0 | V21: 0 | W21: 0 | X21: Active | Y21: 3 | Z21: 1 | AF21: =IF(SUMIF(Founders_Clean!$A$2:$A$159,A21,Founders_Clean!$C$2:$C$159)=0,"",SUMIF(Founders_Clean!$A$2:$A$159,A21,Founders_Clean!$C$2:$C$159)) -> 1 | AG21: =IF(AF21="","",SUMIF(Founders_Clean!$A$2:$A$159,A21,Founders_Clean!$D$2:$D$159)) -> 1 | AH21: =IF(AF21="","",SUMIF(Founders_Clean!$A$2:$A$159,A21,Founders_Clean!$E$2:$E$159)) -> 0 | AI21: =IF(AF21="","",IF((AG21+AH21)=0,"",AH21/(AG21+AH21))) -> 0 | AJ21: =IF(AI21="","",IF(AH21>0,1,0)) -> 0 | AK21: =IF(AI21="","",ROUND(1-(AI21^2+(1-AI21)^2),3)) -> 0 | AQ21: 1 | AR21: 19 | AS21: 19 | AT21: 175 | AU21: 51-200 | AV21: LinkedIn (Public_Macro_Data) | AX21: Active | AY21: High | BA21: 0 | BB21: 0 | BC21: 0 | BF21: =IF(OR(I21="",BC21=""),"",IF(BC21=1,(BD21-I21)*12+IF(BE21="",7,BE21)-IF(J21="",1,J21),M21)) -> 140 | BG21: 1 | BH21: 4150000 | BI21: round | BJ21: 2019 | BK21: 1 | BL21: =COUNTIFS(Investments_Clean!$A$2:$A$150,A21,Investments_Clean!$F$2:$F$150,"Accepted") -> 2 | BM21: =IF(BL21=0,"",IF((COUNTIFS(Investments_Clean!$A$2:$A$150,A21,Investments_Clean!$D$2:$D$150,"VC/PE",Investments_Clean!$F$2:$F$150,"Accepted"))>0,1,0)) -> 1 | BN21: =IF(BL21=0,"",IF((COUNTIFS(Investments_Clean!$A$2:$A$150,A21,Investments_Clean!$D$2:$D$150,"Angel",Investments_Clean!$F$2:$F$150,"Accepted"))>0,1,0)) -> 0 | BO21: =IF(BL21=0,"",IF((COUNTIFS(Investments_Clean!$A$2:$A$150,A21,Investments_Clean!$D$2:$D$150,"Accelerator",Investments_Clean!$F$2:$F$150,"Accepted"))>0,1,0)) -> 0 | BP21: =IF(BL21=0,"",IF((COUNTIFS(Investments_Clean!$A$2:$A$150,A21,Investments_Clean!$D$2:$D$150,"Corporate",Investments_Clean!$F$2:$F$150,"Accepted"))>0,1,0)) -> 0 | BQ21: =IF(BL21=0,"",IF((COUNTIFS(Investments_Clean!$A$2:$A$150,A21,Investments_Clean!$D$2:$D$150,"Government",Investments_Clean!$F$2:$F$150,"Accepted"))>0,1,0)) -> 0 | BR21: =IF(BL21=0,"",IF((COUNTIFS(Investments_Clean!$A$2:$A$150,A21,Investments_Clean!$D$2:$D$150,"Grant/Philanthropic",Investments_Clean!$F$2:$F$150,"Accepted")+COUNTIFS(Investments_Clean!$A$2:$A$150,A21,Investments_Clean!$D$2:$D$150,"DFI/Impact",Investments_Clean!$F$2:$F$150,"Accepted"))>0,1,0)) -> 1 | CA21: 0 | CC21: =IF(I21="","",IFERROR(IF(INDEX(Macro_Lookup!$B$2:$B$31,MATCH(I21,Macro_Lookup!$A$2:$A$31,0))="","",INDEX(Macro_Lookup!$B$2:$B$31,MATCH(I21,Macro_Lookup!$A$2:$A$31,0))),"")) | CD21: =IF(I21="","",IFERROR(IF(INDEX(Macro_Lookup!$C$2:$C$31,MATCH(I21,Macro_Lookup!$A$2:$A$31,0))="","",INDEX(Macro_Lookup!$C$2:$C$31,MATCH(I21,Macro_Lookup!$A$2:$A$31,0))),"")) | CE21: =IF(BJ21="","",IFERROR(IF(INDEX(Macro_Lookup!$B$2:$B$31,MATCH(BJ21,Macro_Lookup!$A$2:$A$31,0))="","",INDEX(Macro_Lookup!$B$2:$B$31,MATCH(BJ21,Macro_Lookup!$A$2:$A$31,0))),"")) | CF21: =IF(BJ21="","",IFERROR(IF(INDEX(Macro_Lookup!$C$2:$C$31,MATCH(BJ21,Macro_Lookup!$A$2:$A$31,0))="","",INDEX(Macro_Lookup!$C$2:$C$31,MATCH(BJ21,Macro_Lookup!$A$2:$A$31,0))),"")) | CG21: 5 | CH21: Original 100 (BD-ST-001..100); see Version_Log v1 (2026-10-06) | CI21: 2026-10-06
A22: BD-ST-021 | B22: Shajgoj | C22: Bangladesh | D22: Dhaka | E22: 0 | F22: Independent startup | I22: 2013 | K22: year | L22: 46295 | M22: =IF(I22="","",(YEAR(L22)-I22)*12+MONTH(L22)-IF(J22="",1,J22)) -> 164 | N22: =IF(M22="","",ROUND(M22/12,2)) -> 13.67 | O22: E-commerce / Beauty | P22: E-commerce | Q22: D2C / e-commerce | R22: 0 | S22: 1 | T22: 0 | U22: 0 | V22: 0 | W22: 0 | X22: Live/Scaling | Y22: 3 | Z22: 1 | AA22: 1 | AB22: Surge (Sequoia India) | AF22: =IF(SUMIF(Founders_Clean!$A$2:$A$159,A22,Founders_Clean!$C$2:$C$159)=0,"",SUMIF(Founders_Clean!$A$2:$A$159,A22,Founders_Clean!$C$2:$C$159)) -> 3 | AG22: =IF(AF22="","",SUMIF(Founders_Clean!$A$2:$A$159,A22,Founders_Clean!$D$2:$D$159)) -> 1 | AH22: =IF(AF22="","",SUMIF(Founders_Clean!$A$2:$A$159,A22,Founders_Clean!$E$2:$E$159)) -> 1 | AI22: =IF(AF22="","",IF((AG22+AH22)=0,"",AH22/(AG22+AH22))) -> 0.5 | AJ22: =IF(AI22="","",IF(AH22>0,1,0)) -> 1 | AK22: =IF(AI22="","",ROUND(1-(AI22^2+(1-AI22)^2),3)) -> 0.5 | AM22: 1 | AN22: Bachelor's | AO22: 1 | AP22: 1 | AQ22: 0 | AR22: 10 | AS22: 9.5 | AX22: Active | AY22: High | BA22: 0 | BB22: 0 | BC22: 0 | BF22: =IF(OR(I22="",BC22=""),"",IF(BC22=1,(BD22-I22)*12+IF(BE22="",7,BE22)-IF(J22="",1,J22),M22)) -> 164 | BG22: 1 | BH22: 2150000 | BI22: round | BJ22: 2022 | BK22: 1 | BL22: =COUNTIFS(Investments_Clean!$A$2:$A$150,A22,Investments_Clean!$F$2:$F$150,"Accepted") -> 1 | BM22: =IF(BL22=0,"",IF((COUNTIFS(Investments_Clean!$A$2:$A$150,A22,Investments_Clean!$D$2:$D$150,"VC/PE",Investments_Clean!$F$2:$F$150,"Accepted"))>0,1,0)) -> 0 | BN22: =IF(BL22=0,"",IF((COUNTIFS(Investments_Clean!$A$2:$A$150,A22,Investments_Clean!$D$2:$D$150,"Angel",Investments_Clean!$F$2:$F$150,"Accepted"))>0,1,0)) -> 0 | BO22: =IF(BL22=0,"",IF((COUNTIFS(Investments_Clean!$A$2:$A$150,A22,Investments_Clean!$D$2:$D$150,"Accelerator",Investments_Clean!$F$2:$F$150,"Accepted"))>0,1,0)) -> 1 | BP22: =IF(BL22=0,"",IF((COUNTIFS(Investments_Clean!$A$2:$A$150,A22,Investments_Clean!$D$2:$D$150,"Corporate",Investments_Clean!$F$2:$F$150,"Accepted"))>0,1,0)) -> 0 | BQ22: =IF(BL22=0,"",IF((COUNTIFS(Investments_Clean!$A$2:$A$150,A22,Investments_Clean!$D$2:$D$150,"Government",Investments_Clean!$F$2:$F$150,"Accepted"))>0,1,0)) -> 0 | BR22: =IF(BL22=0,"",IF((COUNTIFS(Investments_Clean!$A$2:$A$150,A22,Investments_Clean!$D$2:$D$150,"Grant/Philanthropic",Investments_Clean!$F$2:$F$150,"Accepted")+COUNTIFS(Investments_Clean!$A$2:$A$150,A22,Investments_Clean!$D$2:$D$150,"DFI/Impact",Investments_Clean!$F$2:$F$150,"Accepted"))>0,1,0)) -> 0 | CA22: 0 | CC22: =IF(I22="","",IFERROR(IF(INDEX(Macro_Lookup!$B$2:$B$31,MATCH(I22,Macro_Lookup!$A$2:$A$31,0))="","",INDEX(Macro_Lookup!$B$2:$B$31,MATCH(I22,Macro_Lookup!$A$2:$A$31,0))),"")) | CD22: =IF(I22="","",IFERROR(IF(INDEX(Macro_Lookup!$C$2:$C$31,MATCH(I22,Macro_Lookup!$A$2:$A$31,0))="","",INDEX(Macro_Lookup!$C$2:$C$31,MATCH(I22,Macro_Lookup!$A$2:$A$31,0))),"")) | CE22: =IF(BJ22="","",IFERROR(IF(INDEX(Macro_Lookup!$B$2:$B$31,MATCH(BJ22,Macro_Lookup!$A$2:$A$31,0))="","",INDEX(Macro_Lookup!$B$2:$B$31,MATCH(BJ22,Macro_Lookup!$A$2:$A$31,0))),"")) | CF22: =IF(BJ22="","",IFERROR(IF(INDEX(Macro_Lookup!$C$2:$C$31,MATCH(BJ22,Macro_Lookup!$A$2:$A$31,0))="","",INDEX(Macro_Lookup!$C$2:$C$31,MATCH(BJ22,Macro_Lookup!$A$2:$A$31,0))),"")) | CG22: 3 | CH22: Original 100 (BD-ST-001..100); see Version_Log v1 (2026-10-06) | CI22: 2026-10-06
A23: BD-ST-022 | B23: Khaas Food | C23: Bangladesh | D23: Dhaka | E23: 0 | F23: Independent startup | I23: 2015 | K23: year | L23: 46295 | M23: =IF(I23="","",(YEAR(L23)-I23)*12+MONTH(L23)-IF(J23="",1,J23)) -> 140 | N23: =IF(M23="","",ROUND(M23/12,2)) -> 11.67 | O23: E-commerce / Agri-food | P23: E-commerce | Q23: D2C, online + retail | R23: 0 | S23: 1 | T23: 0 | U23: 0 | V23: 0 | W23: 0 | X23: Live/Scaling | Y23: 3 | Z23: 1 | AF23: =IF(SUMIF(Founders_Clean!$A$2:$A$159,A23,Founders_Clean!$C$2:$C$159)=0,"",SUMIF(Founders_Clean!$A$2:$A$159,A23,Founders_Clean!$C$2:$C$159)) -> 3 | AG23: =IF(AF23="","",SUMIF(Founders_Clean!$A$2:$A$159,A23,Founders_Clean!$D$2:$D$159)) -> 3 | AH23: =IF(AF23="","",SUMIF(Founders_Clean!$A$2:$A$159,A23,Founders_Clean!$E$2:$E$159)) -> 0 | AI23: =IF(AF23="","",IF((AG23+AH23)=0,"",AH23/(AG23+AH23))) -> 0 | AJ23: =IF(AI23="","",IF(AH23>0,1,0)) -> 0 | AK23: =IF(AI23="","",ROUND(1-(AI23^2+(1-AI23)^2),3)) -> 0 | AM23: 2 | AN23: Master's/MBA/professional | AO23: 0 | AP23: 0 | AQ23: 0 | AX23: Active | AY23: High | BA23: 0 | BB23: 0 | BC23: 0 | BF23: =IF(OR(I23="",BC23=""),"",IF(BC23=1,(BD23-I23)*12+IF(BE23="",7,BE23)-IF(J23="",1,J23),M23)) -> 140 | BG23: 0 | BH23: 0 | BI23: none | BK23: 0 | BL23: =COUNTIFS(Investments_Clean!$A$2:$A$150,A23,Investments_Clean!$F$2:$F$150,"Accepted") -> 0 | BM23: =IF(BL23=0,"",IF((COUNTIFS(Investments_Clean!$A$2:$A$150,A23,Investments_Clean!$D$2:$D$150,"VC/PE",Investments_Clean!$F$2:$F$150,"Accepted"))>0,1,0)) | BN23: =IF(BL23=0,"",IF((COUNTIFS(Investments_Clean!$A$2:$A$150,A23,Investments_Clean!$D$2:$D$150,"Angel",Investments_Clean!$F$2:$F$150,"Accepted"))>0,1,0)) | BO23: =IF(BL23=0,"",IF((COUNTIFS(Investments_Clean!$A$2:$A$150,A23,Investments_Clean!$D$2:$D$150,"Accelerator",Investments_Clean!$F$2:$F$150,"Accepted"))>0,1,0)) | BP23: =IF(BL23=0,"",IF((COUNTIFS(Investments_Clean!$A$2:$A$150,A23,Investments_Clean!$D$2:$D$150,"Corporate",Investments_Clean!$F$2:$F$150,"Accepted"))>0,1,0)) | BQ23: =IF(BL23=0,"",IF((COUNTIFS(Investments_Clean!$A$2:$A$150,A23,Investments_Clean!$D$2:$D$150,"Government",Investments_Clean!$F$2:$F$150,"Accepted"))>0,1,0)) | BR23: =IF(BL23=0,"",IF((COUNTIFS(Investments_Clean!$A$2:$A$150,A23,Investments_Clean!$D$2:$D$150,"Grant/Philanthropic",Investments_Clean!$F$2:$F$150,"Accepted")+COUNTIFS(Investments_Clean!$A$2:$A$150,A23,Investments_Clean!$D$2:$D$150,"DFI/Impact",Investments_Clean!$F$2:$F$150,"Accepted"))>0,1,0)) | CA23: 0 | CC23: =IF(I23="","",IFERROR(IF(INDEX(Macro_Lookup!$B$2:$B$31,MATCH(I23,Macro_Lookup!$A$2:$A$31,0))="","",INDEX(Macro_Lookup!$B$2:$B$31,MATCH(I23,Macro_Lookup!$A$2:$A$31,0))),"")) | CD23: =IF(I23="","",IFERROR(IF(INDEX(Macro_Lookup!$C$2:$C$31,MATCH(I23,Macro_Lookup!$A$2:$A$31,0))="","",INDEX(Macro_Lookup!$C$2:$C$31,MATCH(I23,Macro_Lookup!$A$2:$A$31,0))),"")) | CE23: =IF(BJ23="","",IFERROR(IF(INDEX(Macro_Lookup!$B$2:$B$31,MATCH(BJ23,Macro_Lookup!$A$2:$A$31,0))="","",INDEX(Macro_Lookup!$B$2:$B$31,MATCH(BJ23,Macro_Lookup!$A$2:$A$31,0))),"")) | CF23: =IF(BJ23="","",IFERROR(IF(INDEX(Macro_Lookup!$C$2:$C$31,MATCH(BJ23,Macro_Lookup!$A$2:$A$31,0))="","",INDEX(Macro_Lookup!$C$2:$C$31,MATCH(BJ23,Macro_Lookup!$A$2:$A$31,0))),"")) | CG23: 5 | CH23: Original 100 (BD-ST-001..100); see Version_Log v1 (2026-10-06) | CI23: 2026-10-06
A24: BD-ST-023 | B24: Pathao | C24: Bangladesh | D24: Dhaka | E24: 0 | F24: Independent startup | I24: 2015 | K24: year | L24: 46295 | M24: =IF(I24="","",(YEAR(L24)-I24)*12+MONTH(L24)-IF(J24="",1,J24)) -> 140 | N24: =IF(M24="","",ROUND(M24/12,2)) -> 11.67 | O24: Logistics / Ride-hailing | P24: Logistics/Travel | Q24: Marketplace, super-app | R24: 0 | S24: 0 | T24: 1 | U24: 0 | V24: 0 | W24: 0 | X24: Live/Scaling | Y24: 3 | Z24: 1 | AF24: =IF(SUMIF(Founders_Clean!$A$2:$A$159,A24,Founders_Clean!$C$2:$C$159)=0,"",SUMIF(Founders_Clean!$A$2:$A$159,A24,Founders_Clean!$C$2:$C$159)) -> 3 | AG24: =IF(AF24="","",SUMIF(Founders_Clean!$A$2:$A$159,A24,Founders_Clean!$D$2:$D$159)) -> 3 | AH24: =IF(AF24="","",SUMIF(Founders_Clean!$A$2:$A$159,A24,Founders_Clean!$E$2:$E$159)) -> 0 | AI24: =IF(AF24="","",IF((AG24+AH24)=0,"",AH24/(AG24+AH24))) -> 0 | AJ24: =IF(AI24="","",IF(AH24>0,1,0)) -> 0 | AK24: =IF(AI24="","",ROUND(1-(AI24^2+(1-AI24)^2),3)) -> 0 | AM24: 2 | AN24: Master's/MBA/professional | AO24: 1 | AP24: 0.5 | AQ24: 1 | AR24: 4 | AS24: 4 | AX24: Active | AY24: High | BA24: 0 | BB24: 0 | BC24: 0 | BF24: =IF(OR(I24="",BC24=""),"",IF(BC24=1,(BD24-I24)*12+IF(BE24="",7,BE24)-IF(J24="",1,J24),M24)) -> 140 | BG24: 1 | BH24: 12000000 | BI24: round | BJ24: 2024 | BK24: 1 | BL24: =COUNTIFS(Investments_Clean!$A$2:$A$150,A24,Investments_Clean!$F$2:$F$150,"Accepted") -> 1 | BM24: =IF(BL24=0,"",IF((COUNTIFS(Investments_Clean!$A$2:$A$150,A24,Investments_Clean!$D$2:$D$150,"VC/PE",Investments_Clean!$F$2:$F$150,"Accepted"))>0,1,0)) -> 1 | BN24: =IF(BL24=0,"",IF((COUNTIFS(Investments_Clean!$A$2:$A$150,A24,Investments_Clean!$D$2:$D$150,"Angel",Investments_Clean!$F$2:$F$150,"Accepted"))>0,1,0)) -> 0 | BO24: =IF(BL24=0,"",IF((COUNTIFS(Investments_Clean!$A$2:$A$150,A24,Investments_Clean!$D$2:$D$150,"Accelerator",Investments_Clean!$F$2:$F$150,"Accepted"))>0,1,0)) -> 0 | BP24: =IF(BL24=0,"",IF((COUNTIFS(Investments_Clean!$A$2:$A$150,A24,Investments_Clean!$D$2:$D$150,"Corporate",Investments_Clean!$F$2:$F$150,"Accepted"))>0,1,0)) -> 0 | BQ24: =IF(BL24=0,"",IF((COUNTIFS(Investments_Clean!$A$2:$A$150,A24,Investments_Clean!$D$2:$D$150,"Government",Investments_Clean!$F$2:$F$150,"Accepted"))>0,1,0)) -> 0 | BR24: =IF(BL24=0,"",IF((COUNTIFS(Investments_Clean!$A$2:$A$150,A24,Investments_Clean!$D$2:$D$150,"Grant/Philanthropic",Investments_Clean!$F$2:$F$150,"Accepted")+COUNTIFS(Investments_Clean!$A$2:$A$150,A24,Investments_Clean!$D$2:$D$150,"DFI/Impact",Investments_Clean!$F$2:$F$150,"Accepted"))>0,1,0)) -> 0 | CA24: 0 | CC24: =IF(I24="","",IFERROR(IF(INDEX(Macro_Lookup!$B$2:$B$31,MATCH(I24,Macro_Lookup!$A$2:$A$31,0))="","",INDEX(Macro_Lookup!$B$2:$B$31,MATCH(I24,Macro_Lookup!$A$2:$A$31,0))),"")) | CD24: =IF(I24="","",IFERROR(IF(INDEX(Macro_Lookup!$C$2:$C$31,MATCH(I24,Macro_Lookup!$A$2:$A$31,0))="","",INDEX(Macro_Lookup!$C$2:$C$31,MATCH(I24,Macro_Lookup!$A$2:$A$31,0))),"")) | CE24: =IF(BJ24="","",IFERROR(IF(INDEX(Macro_Lookup!$B$2:$B$31,MATCH(BJ24,Macro_Lookup!$A$2:$A$31,0))="","",INDEX(Macro_Lookup!$B$2:$B$31,MATCH(BJ24,Macro_Lookup!$A$2:$A$31,0))),"")) | CF24: =IF(BJ24="","",IFERROR(IF(INDEX(Macro_Lookup!$C$2:$C$31,MATCH(BJ24,Macro_Lookup!$A$2:$A$31,0))="","",INDEX(Macro_Lookup!$C$2:$C$31,MATCH(BJ24,Macro_Lookup!$A$2:$A$31,0))),"")) | CG24: 4 | CH24: Original 100 (BD-ST-001..100); see Version_Log v1 (2026-10-06) | CI24: 2026-10-06
A25: BD-ST-024 | B25: Shohoz | C25: Bangladesh | D25: Dhaka | E25: 0 | F25: Independent startup | I25: 2014 | K25: year | L25: 46295 | M25: =IF(I25="","",(YEAR(L25)-I25)*12+MONTH(L25)-IF(J25="",1,J25)) -> 152 | N25: =IF(M25="","",ROUND(M25/12,2)) -> 12.67 | O25: Logistics / Lifestyle Platform | P25: Logistics/Travel | Q25: B2C ticketing marketplace | R25: 0 | S25: 1 | T25: 1 | U25: 0 | V25: 0 | W25: 0 | X25: Live/Scaling | Y25: 3 | Z25: 1 | AF25: =IF(SUMIF(Founders_Clean!$A$2:$A$159,A25,Founders_Clean!$C$2:$C$159)=0,"",SUMIF(Founders_Clean!$A$2:$A$159,A25,Founders_Clean!$C$2:$C$159)) -> 1 | AG25: =IF(AF25="","",SUMIF(Founders_Clean!$A$2:$A$159,A25,Founders_Clean!$D$2:$D$159)) -> 0 | AH25: =IF(AF25="","",SUMIF(Founders_Clean!$A$2:$A$159,A25,Founders_Clean!$E$2:$E$159)) -> 1 | AI25: =IF(AF25="","",IF((AG25+AH25)=0,"",AH25/(AG25+AH25))) -> 1 | AJ25: =IF(AI25="","",IF(AH25>0,1,0)) -> 1 | AK25: =IF(AI25="","",ROUND(1-(AI25^2+(1-AI25)^2),3)) -> 0 | AM25: 2 | AN25: Master's/MBA/professional | AO25: 1 | AP25: 1 | AQ25: 0 | AR25: 13.5 | AS25: 13.5 | AX25: Active | AY25: High | BA25: 0 | BB25: 0 | BC25: 0 | BF25: =IF(OR(I25="",BC25=""),"",IF(BC25=1,(BD25-I25)*12+IF(BE25="",7,BE25)-IF(J25="",1,J25),M25)) -> 152 | BG25: 1 | BH25: 3440000 | BI25: round | BJ25: 2023 | BK25: 1 | BL25: =COUNTIFS(Investments_Clean!$A$2:$A$150,A25,Investments_Clean!$F$2:$F$150,"Accepted") -> 1 | BM25: =IF(BL25=0,"",IF((COUNTIFS(Investments_Clean!$A$2:$A$150,A25,Investments_Clean!$D$2:$D$150,"VC/PE",Investments_Clean!$F$2:$F$150,"Accepted"))>0,1,0)) -> 1 | BN25: =IF(BL25=0,"",IF((COUNTIFS(Investments_Clean!$A$2:$A$150,A25,Investments_Clean!$D$2:$D$150,"Angel",Investments_Clean!$F$2:$F$150,"Accepted"))>0,1,0)) -> 0 | BO25: =IF(BL25=0,"",IF((COUNTIFS(Investments_Clean!$A$2:$A$150,A25,Investments_Clean!$D$2:$D$150,"Accelerator",Investments_Clean!$F$2:$F$150,"Accepted"))>0,1,0)) -> 0 | BP25: =IF(BL25=0,"",IF((COUNTIFS(Investments_Clean!$A$2:$A$150,A25,Investments_Clean!$D$2:$D$150,"Corporate",Investments_Clean!$F$2:$F$150,"Accepted"))>0,1,0)) -> 0 | BQ25: =IF(BL25=0,"",IF((COUNTIFS(Investments_Clean!$A$2:$A$150,A25,Investments_Clean!$D$2:$D$150,"Government",Investments_Clean!$F$2:$F$150,"Accepted"))>0,1,0)) -> 0 | BR25: =IF(BL25=0,"",IF((COUNTIFS(Investments_Clean!$A$2:$A$150,A25,Investments_Clean!$D$2:$D$150,"Grant/Philanthropic",Investments_Clean!$F$2:$F$150,"Accepted")+COUNTIFS(Investments_Clean!$A$2:$A$150,A25,Investments_Clean!$D$2:$D$150,"DFI/Impact",Investments_Clean!$F$2:$F$150,"Accepted"))>0,1,0)) -> 0 | CA25: 0 | CC25: =IF(I25="","",IFERROR(IF(INDEX(Macro_Lookup!$B$2:$B$31,MATCH(I25,Macro_Lookup!$A$2:$A$31,0))="","",INDEX(Macro_Lookup!$B$2:$B$31,MATCH(I25,Macro_Lookup!$A$2:$A$31,0))),"")) | CD25: =IF(I25="","",IFERROR(IF(INDEX(Macro_Lookup!$C$2:$C$31,MATCH(I25,Macro_Lookup!$A$2:$A$31,0))="","",INDEX(Macro_Lookup!$C$2:$C$31,MATCH(I25,Macro_Lookup!$A$2:$A$31,0))),"")) | CE25: =IF(BJ25="","",IFERROR(IF(INDEX(Macro_Lookup!$B$2:$B$31,MATCH(BJ25,Macro_Lookup!$A$2:$A$31,0))="","",INDEX(Macro_Lookup!$B$2:$B$31,MATCH(BJ25,Macro_Lookup!$A$2:$A$31,0))),"")) | CF25: =IF(BJ25="","",IFERROR(IF(INDEX(Macro_Lookup!$C$2:$C$31,MATCH(BJ25,Macro_Lookup!$A$2:$A$31,0))="","",INDEX(Macro_Lookup!$C$2:$C$31,MATCH(BJ25,Macro_Lookup!$A$2:$A$31,0))),"")) | CG25: 4 | CH25: Original 100 (BD-ST-001..100); see Version_Log v1 (2026-10-06) | CI25: 2026-10-06
A26: BD-ST-025 | B26: eCourier | C26: Bangladesh | D26: Dhaka | E26: 0 | F26: Independent startup | I26: 2014 | K26: year | L26: 46295 | M26: =IF(I26="","",(YEAR(L26)-I26)*12+MONTH(L26)-IF(J26="",1,J26)) -> 152 | N26: =IF(M26="","",ROUND(M26/12,2)) -> 12.67 | O26: Logistics / Courier | P26: Logistics/Travel | Q26: B2B logistics | R26: 1 | S26: 0 | T26: 0 | U26: 0 | V26: 0 | W26: 0 | X26: Live/Scaling | Y26: 3 | Z26: 1 | AF26: =IF(SUMIF(Founders_Clean!$A$2:$A$159,A26,Founders_Clean!$C$2:$C$159)=0,"",SUMIF(Founders_Clean!$A$2:$A$159,A26,Founders_Clean!$C$2:$C$159)) -> 1 | AG26: =IF(AF26="","",SUMIF(Founders_Clean!$A$2:$A$159,A26,Founders_Clean!$D$2:$D$159)) -> 1 | AH26: =IF(AF26="","",SUMIF(Founders_Clean!$A$2:$A$159,A26,Founders_Clean!$E$2:$E$159)) -> 0 | AI26: =IF(AF26="","",IF((AG26+AH26)=0,"",AH26/(AG26+AH26))) -> 0 | AJ26: =IF(AI26="","",IF(AH26>0,1,0)) -> 0 | AK26: =IF(AI26="","",ROUND(1-(AI26^2+(1-AI26)^2),3)) -> 0 | AM26: 2 | AN26: Master's/MBA/professional | AO26: 1 | AP26: 1 | AQ26: 1 | AR26: 6 | AS26: 6 | AX26: Active | AY26: High | BA26: 0 | BB26: 0 | BC26: 0 | BF26: =IF(OR(I26="",BC26=""),"",IF(BC26=1,(BD26-I26)*12+IF(BE26="",7,BE26)-IF(J26="",1,J26),M26)) -> 152 | BG26: 1 | BJ26: 2015 | BK26: 1 | BL26: =COUNTIFS(Investments_Clean!$A$2:$A$150,A26,Investments_Clean!$F$2:$F$150,"Accepted") -> 0 | BM26: =IF(BL26=0,"",IF((COUNTIFS(Investments_Clean!$A$2:$A$150,A26,Investments_Clean!$D$2:$D$150,"VC/PE",Investments_Clean!$F$2:$F$150,"Accepted"))>0,1,0)) | BN26: =IF(BL26=0,"",IF((COUNTIFS(Investments_Clean!$A$2:$A$150,A26,Investments_Clean!$D$2:$D$150,"Angel",Investments_Clean!$F$2:$F$150,"Accepted"))>0,1,0)) | BO26: =IF(BL26=0,"",IF((COUNTIFS(Investments_Clean!$A$2:$A$150,A26,Investments_Clean!$D$2:$D$150,"Accelerator",Investments_Clean!$F$2:$F$150,"Accepted"))>0,1,0)) | BP26: =IF(BL26=0,"",IF((COUNTIFS(Investments_Clean!$A$2:$A$150,A26,Investments_Clean!$D$2:$D$150,"Corporate",Investments_Clean!$F$2:$F$150,"Accepted"))>0,1,0)) | BQ26: =IF(BL26=0,"",IF((COUNTIFS(Investments_Clean!$A$2:$A$150,A26,Investments_Clean!$D$2:$D$150,"Government",Investments_Clean!$F$2:$F$150,"Accepted"))>0,1,0)) | BR26: =IF(BL26=0,"",IF((COUNTIFS(Investments_Clean!$A$2:$A$150,A26,Investments_Clean!$D$2:$D$150,"Grant/Philanthropic",Investments_Clean!$F$2:$F$150,"Accepted")+COUNTIFS(Investments_Clean!$A$2:$A$150,A26,Investments_Clean!$D$2:$D$150,"DFI/Impact",Investments_Clean!$F$2:$F$150,"Accepted"))>0,1,0)) | CA26: 0 | CC26: =IF(I26="","",IFERROR(IF(INDEX(Macro_Lookup!$B$2:$B$31,MATCH(I26,Macro_Lookup!$A$2:$A$31,0))="","",INDEX(Macro_Lookup!$B$2:$B$31,MATCH(I26,Macro_Lookup!$A$2:$A$31,0))),"")) | CD26: =IF(I26="","",IFERROR(IF(INDEX(Macro_Lookup!$C$2:$C$31,MATCH(I26,Macro_Lookup!$A$2:$A$31,0))="","",INDEX(Macro_Lookup!$C$2:$C$31,MATCH(I26,Macro_Lookup!$A$2:$A$31,0))),"")) | CE26: =IF(BJ26="","",IFERROR(IF(INDEX(Macro_Lookup!$B$2:$B$31,MATCH(BJ26,Macro_Lookup!$A$2:$A$31,0))="","",INDEX(Macro_Lookup!$B$2:$B$31,MATCH(BJ26,Macro_Lookup!$A$2:$A$31,0))),"")) | CF26: =IF(BJ26="","",IFERROR(IF(INDEX(Macro_Lookup!$C$2:$C$31,MATCH(BJ26,Macro_Lookup!$A$2:$A$31,0))="","",INDEX(Macro_Lookup!$C$2:$C$31,MATCH(BJ26,Macro_Lookup!$A$2:$A$31,0))),"")) | CG26: 4 | CH26: Original 100 (BD-ST-001..100); see Version_Log v1 (2026-10-06) | CI26: 2026-10-06
A27: BD-ST-026 | B27: Truck Lagbe | C27: Bangladesh | D27: Dhaka | E27: 0 | F27: Independent startup | I27: 2017 | K27: year | L27: 46295 | M27: =IF(I27="","",(YEAR(L27)-I27)*12+MONTH(L27)-IF(J27="",1,J27)) -> 116 | N27: =IF(M27="","",ROUND(M27/12,2)) -> 9.67 | O27: Logistics / Freight | P27: Logistics/Travel | Q27: Marketplace, trucking (B2B/B2C) | R27: 1 | S27: 1 | T27: 1 | U27: 0 | V27: 0 | W27: 0 | X27: Live/Scaling | Y27: 3 | Z27: 1 | AF27: =IF(SUMIF(Founders_Clean!$A$2:$A$159,A27,Founders_Clean!$C$2:$C$159)=0,"",SUMIF(Founders_Clean!$A$2:$A$159,A27,Founders_Clean!$C$2:$C$159)) -> 2 | AG27: =IF(AF27="","",SUMIF(Founders_Clean!$A$2:$A$159,A27,Founders_Clean!$D$2:$D$159)) -> 2 | AH27: =IF(AF27="","",SUMIF(Founders_Clean!$A$2:$A$159,A27,Founders_Clean!$E$2:$E$159)) -> 0 | AI27: =IF(AF27="","",IF((AG27+AH27)=0,"",AH27/(AG27+AH27))) -> 0 | AJ27: =IF(AI27="","",IF(AH27>0,1,0)) -> 0 | AK27: =IF(AI27="","",ROUND(1-(AI27^2+(1-AI27)^2),3)) -> 0 | AM27: 1 | AN27: Bachelor's | AO27: 0 | AP27: 0 | AQ27: 0 | AR27: 14 | AS27: 14 | AX27: Active | AY27: High | BA27: 0 | BB27: 0 | BC27: 0 | BF27: =IF(OR(I27="",BC27=""),"",IF(BC27=1,(BD27-I27)*12+IF(BE27="",7,BE27)-IF(J27="",1,J27),M27)) -> 116 | BG27: 1 | BH27: 4000000 | BI27: round | BJ27: 2021 | BK27: 1 | BL27: =COUNTIFS(Investments_Clean!$A$2:$A$150,A27,Investments_Clean!$F$2:$F$150,"Accepted") -> 1 | BM27: =IF(BL27=0,"",IF((COUNTIFS(Investments_Clean!$A$2:$A$150,A27,Investments_Clean!$D$2:$D$150,"VC/PE",Investments_Clean!$F$2:$F$150,"Accepted"))>0,1,0)) -> 0 | BN27: =IF(BL27=0,"",IF((COUNTIFS(Investments_Clean!$A$2:$A$150,A27,Investments_Clean!$D$2:$D$150,"Angel",Investments_Clean!$F$2:$F$150,"Accepted"))>0,1,0)) -> 0 | BO27: =IF(BL27=0,"",IF((COUNTIFS(Investments_Clean!$A$2:$A$150,A27,Investments_Clean!$D$2:$D$150,"Accelerator",Investments_Clean!$F$2:$F$150,"Accepted"))>0,1,0)) -> 0 | BP27: =IF(BL27=0,"",IF((COUNTIFS(Investments_Clean!$A$2:$A$150,A27,Investments_Clean!$D$2:$D$150,"Corporate",Investments_Clean!$F$2:$F$150,"Accepted"))>0,1,0)) -> 0 | BQ27: =IF(BL27=0,"",IF((COUNTIFS(Investments_Clean!$A$2:$A$150,A27,Investments_Clean!$D$2:$D$150,"Government",Investments_Clean!$F$2:$F$150,"Accepted"))>0,1,0)) -> 0 | BR27: =IF(BL27=0,"",IF((COUNTIFS(Investments_Clean!$A$2:$A$150,A27,Investments_Clean!$D$2:$D$150,"Grant/Philanthropic",Investments_Clean!$F$2:$F$150,"Accepted")+COUNTIFS(Investments_Clean!$A$2:$A$150,A27,Investments_Clean!$D$2:$D$150,"DFI/Impact",Investments_Clean!$F$2:$F$150,"Accepted"))>0,1,0)) -> 1 | CA27: 0 | CC27: =IF(I27="","",IFERROR(IF(INDEX(Macro_Lookup!$B$2:$B$31,MATCH(I27,Macro_Lookup!$A$2:$A$31,0))="","",INDEX(Macro_Lookup!$B$2:$B$31,MATCH(I27,Macro_Lookup!$A$2:$A$31,0))),"")) | CD27: =IF(I27="","",IFERROR(IF(INDEX(Macro_Lookup!$C$2:$C$31,MATCH(I27,Macro_Lookup!$A$2:$A$31,0))="","",INDEX(Macro_Lookup!$C$2:$C$31,MATCH(I27,Macro_Lookup!$A$2:$A$31,0))),"")) | CE27: =IF(BJ27="","",IFERROR(IF(INDEX(Macro_Lookup!$B$2:$B$31,MATCH(BJ27,Macro_Lookup!$A$2:$A$31,0))="","",INDEX(Macro_Lookup!$B$2:$B$31,MATCH(BJ27,Macro_Lookup!$A$2:$A$31,0))),"")) | CF27: =IF(BJ27="","",IFERROR(IF(INDEX(Macro_Lookup!$C$2:$C$31,MATCH(BJ27,Macro_Lookup!$A$2:$A$31,0))="","",INDEX(Macro_Lookup!$C$2:$C$31,MATCH(BJ27,Macro_Lookup!$A$2:$A$31,0))),"")) | CG27: 4 | CH27: Original 100 (BD-ST-001..100); see Version_Log v1 (2026-10-06) | CI27: 2026-10-06
A28: BD-ST-027 | B28: Jatri | C28: Bangladesh | D28: Dhaka | E28: 0 | F28: Independent startup | I28: 2019 | K28: year | L28: 46295 | M28: =IF(I28="","",(YEAR(L28)-I28)*12+MONTH(L28)-IF(J28="",1,J28)) -> 92 | N28: =IF(M28="","",ROUND(M28/12,2)) -> 7.67 | O28: Logistics / Mass Mobility | P28: Logistics/Travel | Q28: B2B2C mass transit / travel commerce | R28: 1 | S28: 1 | T28: 0 | U28: 0 | V28: 0 | W28: 0 | X28: Live/Scaling | Y28: 3 | Z28: 1 | AF28: =IF(SUMIF(Founders_Clean!$A$2:$A$159,A28,Founders_Clean!$C$2:$C$159)=0,"",SUMIF(Founders_Clean!$A$2:$A$159,A28,Founders_Clean!$C$2:$C$159)) -> 3 | AG28: =IF(AF28="","",SUMIF(Founders_Clean!$A$2:$A$159,A28,Founders_Clean!$D$2:$D$159)) -> 3 | AH28: =IF(AF28="","",SUMIF(Founders_Clean!$A$2:$A$159,A28,Founders_Clean!$E$2:$E$159)) -> 0 | AI28: =IF(AF28="","",IF((AG28+AH28)=0,"",AH28/(AG28+AH28))) -> 0 | AJ28: =IF(AI28="","",IF(AH28>0,1,0)) -> 0 | AK28: =IF(AI28="","",ROUND(1-(AI28^2+(1-AI28)^2),3)) -> 0 | AQ28: 0 | AX28: Active | AY28: High | BA28: 0 | BB28: 0 | BC28: 0 | BF28: =IF(OR(I28="",BC28=""),"",IF(BC28=1,(BD28-I28)*12+IF(BE28="",7,BE28)-IF(J28="",1,J28),M28)) -> 92 | BG28: 1 | BJ28: 2020 | BK28: 1 | BL28: =COUNTIFS(Investments_Clean!$A$2:$A$150,A28,Investments_Clean!$F$2:$F$150,"Accepted") -> 1 | BM28: =IF(BL28=0,"",IF((COUNTIFS(Investments_Clean!$A$2:$A$150,A28,Investments_Clean!$D$2:$D$150,"VC/PE",Investments_Clean!$F$2:$F$150,"Accepted"))>0,1,0)) -> 0 | BN28: =IF(BL28=0,"",IF((COUNTIFS(Investments_Clean!$A$2:$A$150,A28,Investments_Clean!$D$2:$D$150,"Angel",Investments_Clean!$F$2:$F$150,"Accepted"))>0,1,0)) -> 1 | BO28: =IF(BL28=0,"",IF((COUNTIFS(Investments_Clean!$A$2:$A$150,A28,Investments_Clean!$D$2:$D$150,"Accelerator",Investments_Clean!$F$2:$F$150,"Accepted"))>0,1,0)) -> 0 | BP28: =IF(BL28=0,"",IF((COUNTIFS(Investments_Clean!$A$2:$A$150,A28,Investments_Clean!$D$2:$D$150,"Corporate",Investments_Clean!$F$2:$F$150,"Accepted"))>0,1,0)) -> 0 | BQ28: =IF(BL28=0,"",IF((COUNTIFS(Investments_Clean!$A$2:$A$150,A28,Investments_Clean!$D$2:$D$150,"Government",Investments_Clean!$F$2:$F$150,"Accepted"))>0,1,0)) -> 0 | BR28: =IF(BL28=0,"",IF((COUNTIFS(Investments_Clean!$A$2:$A$150,A28,Investments_Clean!$D$2:$D$150,"Grant/Philanthropic",Investments_Clean!$F$2:$F$150,"Accepted")+COUNTIFS(Investments_Clean!$A$2:$A$150,A28,Investments_Clean!$D$2:$D$150,"DFI/Impact",Investments_Clean!$F$2:$F$150,"Accepted"))>0,1,0)) -> 0 | CA28: 0 | CC28: =IF(I28="","",IFERROR(IF(INDEX(Macro_Lookup!$B$2:$B$31,MATCH(I28,Macro_Lookup!$A$2:$A$31,0))="","",INDEX(Macro_Lookup!$B$2:$B$31,MATCH(I28,Macro_Lookup!$A$2:$A$31,0))),"")) | CD28: =IF(I28="","",IFERROR(IF(INDEX(Macro_Lookup!$C$2:$C$31,MATCH(I28,Macro_Lookup!$A$2:$A$31,0))="","",INDEX(Macro_Lookup!$C$2:$C$31,MATCH(I28,Macro_Lookup!$A$2:$A$31,0))),"")) | CE28: =IF(BJ28="","",IFERROR(IF(INDEX(Macro_Lookup!$B$2:$B$31,MATCH(BJ28,Macro_Lookup!$A$2:$A$31,0))="","",INDEX(Macro_Lookup!$B$2:$B$31,MATCH(BJ28,Macro_Lookup!$A$2:$A$31,0))),"")) | CF28: =IF(BJ28="","",IFERROR(IF(INDEX(Macro_Lookup!$C$2:$C$31,MATCH(BJ28,Macro_Lookup!$A$2:$A$31,0))="","",INDEX(Macro_Lookup!$C$2:$C$31,MATCH(BJ28,Macro_Lookup!$A$2:$A$31,0))),"")) | CG28: 7 | CH28: Original 100 (BD-ST-001..100); see Version_Log v1 (2026-10-06) | CI28: 2026-10-06
A29: BD-ST-028 | B29: Shuttle | C29: Bangladesh | D29: Dhaka | E29: 0 | F29: Independent startup | I29: 2018 | K29: year | L29: 46295 | M29: =IF(I29="","",(YEAR(L29)-I29)*12+MONTH(L29)-IF(J29="",1,J29)) -> 104 | N29: =IF(M29="","",ROUND(M29/12,2)) -> 8.67 | O29: Logistics / Ride-sharing | P29: Logistics/Travel | Q29: Marketplace, ride-pooling | R29: 0 | S29: 0 | T29: 1 | U29: 0 | V29: 0 | W29: 0 | X29: Live/Scaling | Y29: 3 | Z29: 1 | AA29: 1 | AB29: Accelerating Asia | AF29: =IF(SUMIF(Founders_Clean!$A$2:$A$159,A29,Founders_Clean!$C$2:$C$159)=0,"",SUMIF(Founders_Clean!$A$2:$A$159,A29,Founders_Clean!$C$2:$C$159)) -> 3 | AG29: =IF(AF29="","",SUMIF(Founders_Clean!$A$2:$A$159,A29,Founders_Clean!$D$2:$D$159)) -> 3 | AH29: =IF(AF29="","",SUMIF(Founders_Clean!$A$2:$A$159,A29,Founders_Clean!$E$2:$E$159)) -> 0 | AI29: =IF(AF29="","",IF((AG29+AH29)=0,"",AH29/(AG29+AH29))) -> 0 | AJ29: =IF(AI29="","",IF(AH29>0,1,0)) -> 0 | AK29: =IF(AI29="","",ROUND(1-(AI29^2+(1-AI29)^2),3)) -> 0 | AM29: 1 | AN29: Bachelor's | AO29: 1 | AP29: 0.33333333 | AQ29: 1 | AR29: 2 | AS29: 2 | AX29: Active | AY29: High | BA29: 0 | BB29: 0 | BC29: 0 | BF29: =IF(OR(I29="",BC29=""),"",IF(BC29=1,(BD29-I29)*12+IF(BE29="",7,BE29)-IF(J29="",1,J29),M29)) -> 104 | BG29: 1 | BH29: 1500000 | BI29: round | BJ29: 2022 | BK29: 1 | BL29: =COUNTIFS(Investments_Clean!$A$2:$A$150,A29,Investments_Clean!$F$2:$F$150,"Accepted") -> 1 | BM29: =IF(BL29=0,"",IF((COUNTIFS(Investments_Clean!$A$2:$A$150,A29,Investments_Clean!$D$2:$D$150,"VC/PE",Investments_Clean!$F$2:$F$150,"Accepted"))>0,1,0)) -> 1 | BN29: =IF(BL29=0,"",IF((COUNTIFS(Investments_Clean!$A$2:$A$150,A29,Investments_Clean!$D$2:$D$150,"Angel",Investments_Clean!$F$2:$F$150,"Accepted"))>0,1,0)) -> 0 | BO29: =IF(BL29=0,"",IF((COUNTIFS(Investments_Clean!$A$2:$A$150,A29,Investments_Clean!$D$2:$D$150,"Accelerator",Investments_Clean!$F$2:$F$150,"Accepted"))>0,1,0)) -> 0 | BP29: =IF(BL29=0,"",IF((COUNTIFS(Investments_Clean!$A$2:$A$150,A29,Investments_Clean!$D$2:$D$150,"Corporate",Investments_Clean!$F$2:$F$150,"Accepted"))>0,1,0)) -> 0 | BQ29: =IF(BL29=0,"",IF((COUNTIFS(Investments_Clean!$A$2:$A$150,A29,Investments_Clean!$D$2:$D$150,"Government",Investments_Clean!$F$2:$F$150,"Accepted"))>0,1,0)) -> 0 | BR29: =IF(BL29=0,"",IF((COUNTIFS(Investments_Clean!$A$2:$A$150,A29,Investments_Clean!$D$2:$D$150,"Grant/Philanthropic",Investments_Clean!$F$2:$F$150,"Accepted")+COUNTIFS(Investments_Clean!$A$2:$A$150,A29,Investments_Clean!$D$2:$D$150,"DFI/Impact",Investments_Clean!$F$2:$F$150,"Accepted"))>0,1,0)) -> 0 | CA29: 0 | CC29: =IF(I29="","",IFERROR(IF(INDEX(Macro_Lookup!$B$2:$B$31,MATCH(I29,Macro_Lookup!$A$2:$A$31,0))="","",INDEX(Macro_Lookup!$B$2:$B$31,MATCH(I29,Macro_Lookup!$A$2:$A$31,0))),"")) | CD29: =IF(I29="","",IFERROR(IF(INDEX(Macro_Lookup!$C$2:$C$31,MATCH(I29,Macro_Lookup!$A$2:$A$31,0))="","",INDEX(Macro_Lookup!$C$2:$C$31,MATCH(I29,Macro_Lookup!$A$2:$A$31,0))),"")) | CE29: =IF(BJ29="","",IFERROR(IF(INDEX(Macro_Lookup!$B$2:$B$31,MATCH(BJ29,Macro_Lookup!$A$2:$A$31,0))="","",INDEX(Macro_Lookup!$B$2:$B$31,MATCH(BJ29,Macro_Lookup!$A$2:$A$31,0))),"")) | CF29: =IF(BJ29="","",IFERROR(IF(INDEX(Macro_Lookup!$C$2:$C$31,MATCH(BJ29,Macro_Lookup!$A$2:$A$31,0))="","",INDEX(Macro_Lookup!$C$2:$C$31,MATCH(BJ29,Macro_Lookup!$A$2:$A$31,0))),"")) | CG29: 3 | CH29: Original 100 (BD-ST-001..100); see Version_Log v1 (2026-10-06) | CI29: 2026-10-06
A30: BD-ST-029 | B30: Paperfly | C30: Bangladesh | D30: Dhaka | E30: 0 | F30: Independent startup | I30: 2016 | K30: year | L30: 46295 | M30: =IF(I30="","",(YEAR(L30)-I30)*12+MONTH(L30)-IF(J30="",1,J30)) -> 128 | N30: =IF(M30="","",ROUND(M30/12,2)) -> 10.67 | O30: Logistics / E-commerce Delivery | P30: Logistics/Travel | Q30: B2B/B2B2C fulfillment & logistics | R30: 1 | S30: 1 | T30: 0 | U30: 0 | V30: 0 | W30: 0 | X30: Live/Scaling | Y30: 3 | Z30: 1 | AF30: =IF(SUMIF(Founders_Clean!$A$2:$A$159,A30,Founders_Clean!$C$2:$C$159)=0,"",SUMIF(Founders_Clean!$A$2:$A$159,A30,Founders_Clean!$C$2:$C$159)) -> 4 | AG30: =IF(AF30="","",SUMIF(Founders_Clean!$A$2:$A$159,A30,Founders_Clean!$D$2:$D$159)) -> 4 | AH30: =IF(AF30="","",SUMIF(Founders_Clean!$A$2:$A$159,A30,Founders_Clean!$E$2:$E$159)) -> 0 | AI30: =IF(AF30="","",IF((AG30+AH30)=0,"",AH30/(AG30+AH30))) -> 0 | AJ30: =IF(AI30="","",IF(AH30>0,1,0)) -> 0 | AK30: =IF(AI30="","",ROUND(1-(AI30^2+(1-AI30)^2),3)) -> 0 | AX30: Active | AY30: High | BA30: 0 | BB30: 0 | BC30: 0 | BF30: =IF(OR(I30="",BC30=""),"",IF(BC30=1,(BD30-I30)*12+IF(BE30="",7,BE30)-IF(J30="",1,J30),M30)) -> 128 | BG30: 1 | BH30: 11000000 | BI30: round | BJ30: 2022 | BK30: 1 | BL30: =COUNTIFS(Investments_Clean!$A$2:$A$150,A30,Investments_Clean!$F$2:$F$150,"Accepted") -> 1 | BM30: =IF(BL30=0,"",IF((COUNTIFS(Investments_Clean!$A$2:$A$150,A30,Investments_Clean!$D$2:$D$150,"VC/PE",Investments_Clean!$F$2:$F$150,"Accepted"))>0,1,0)) -> 0 | BN30: =IF(BL30=0,"",IF((COUNTIFS(Investments_Clean!$A$2:$A$150,A30,Investments_Clean!$D$2:$D$150,"Angel",Investments_Clean!$F$2:$F$150,"Accepted"))>0,1,0)) -> 0 | BO30: =IF(BL30=0,"",IF((COUNTIFS(Investments_Clean!$A$2:$A$150,A30,Investments_Clean!$D$2:$D$150,"Accelerator",Investments_Clean!$F$2:$F$150,"Accepted"))>0,1,0)) -> 0 | BP30: =IF(BL30=0,"",IF((COUNTIFS(Investments_Clean!$A$2:$A$150,A30,Investments_Clean!$D$2:$D$150,"Corporate",Investments_Clean!$F$2:$F$150,"Accepted"))>0,1,0)) -> 1 | BQ30: =IF(BL30=0,"",IF((COUNTIFS(Investments_Clean!$A$2:$A$150,A30,Investments_Clean!$D$2:$D$150,"Government",Investments_Clean!$F$2:$F$150,"Accepted"))>0,1,0)) -> 0 | BR30: =IF(BL30=0,"",IF((COUNTIFS(Investments_Clean!$A$2:$A$150,A30,Investments_Clean!$D$2:$D$150,"Grant/Philanthropic",Investments_Clean!$F$2:$F$150,"Accepted")+COUNTIFS(Investments_Clean!$A$2:$A$150,A30,Investments_Clean!$D$2:$D$150,"DFI/Impact",Investments_Clean!$F$2:$F$150,"Accepted"))>0,1,0)) -> 0 | CA30: 0 | CC30: =IF(I30="","",IFERROR(IF(INDEX(Macro_Lookup!$B$2:$B$31,MATCH(I30,Macro_Lookup!$A$2:$A$31,0))="","",INDEX(Macro_Lookup!$B$2:$B$31,MATCH(I30,Macro_Lookup!$A$2:$A$31,0))),"")) | CD30: =IF(I30="","",IFERROR(IF(INDEX(Macro_Lookup!$C$2:$C$31,MATCH(I30,Macro_Lookup!$A$2:$A$31,0))="","",INDEX(Macro_Lookup!$C$2:$C$31,MATCH(I30,Macro_Lookup!$A$2:$A$31,0))),"")) | CE30: =IF(BJ30="","",IFERROR(IF(INDEX(Macro_Lookup!$B$2:$B$31,MATCH(BJ30,Macro_Lookup!$A$2:$A$31,0))="","",INDEX(Macro_Lookup!$B$2:$B$31,MATCH(BJ30,Macro_Lookup!$A$2:$A$31,0))),"")) | CF30: =IF(BJ30="","",IFERROR(IF(INDEX(Macro_Lookup!$C$2:$C$31,MATCH(BJ30,Macro_Lookup!$A$2:$A$31,0))="","",INDEX(Macro_Lookup!$C$2:$C$31,MATCH(BJ30,Macro_Lookup!$A$2:$A$31,0))),"")) | CG30: 8 | CH30: Original 100 (BD-ST-001..100); see Version_Log v1 (2026-10-06) | CI30: 2026-10-06
A31: BD-ST-030 | B31: Zantrik | C31: Bangladesh | D31: Dhaka | E31: 0 | F31: Independent startup | I31: 2017 | K31: year | L31: 46295 | M31: =IF(I31="","",(YEAR(L31)-I31)*12+MONTH(L31)-IF(J31="",1,J31)) -> 116 | N31: =IF(M31="","",ROUND(M31/12,2)) -> 9.67 | O31: Logistics / Roadside Assistance | P31: Logistics/Travel | Q31: Marketplace, on-demand auto services | R31: 0 | S31: 0 | T31: 1 | U31: 0 | V31: 0 | W31: 0 | X31: Live/Scaling | Y31: 3 | Z31: 1 | AA31: 1 | AB31: Accelerating Asia | AF31: =IF(SUMIF(Founders_Clean!$A$2:$A$159,A31,Founders_Clean!$C$2:$C$159)=0,"",SUMIF(Founders_Clean!$A$2:$A$159,A31,Founders_Clean!$C$2:$C$159)) -> 2 | AG31: =IF(AF31="","",SUMIF(Founders_Clean!$A$2:$A$159,A31,Founders_Clean!$D$2:$D$159)) -> 2 | AH31: =IF(AF31="","",SUMIF(Founders_Clean!$A$2:$A$159,A31,Founders_Clean!$E$2:$E$159)) -> 0 | AI31: =IF(AF31="","",IF((AG31+AH31)=0,"",AH31/(AG31+AH31))) -> 0 | AJ31: =IF(AI31="","",IF(AH31>0,1,0)) -> 0 | AK31: =IF(AI31="","",ROUND(1-(AI31^2+(1-AI31)^2),3)) -> 0 | AX31: Active | AY31: High | BA31: 0 | BB31: 0 | BC31: 0 | BF31: =IF(OR(I31="",BC31=""),"",IF(BC31=1,(BD31-I31)*12+IF(BE31="",7,BE31)-IF(J31="",1,J31),M31)) -> 116 | BG31: 1 | BH31: 1000000 | BI31: round | BJ31: 2022 | BK31: 1 | BL31: =COUNTIFS(Investments_Clean!$A$2:$A$150,A31,Investments_Clean!$F$2:$F$150,"Accepted") -> 1 | BM31: =IF(BL31=0,"",IF((COUNTIFS(Investments_Clean!$A$2:$A$150,A31,Investments_Clean!$D$2:$D$150,"VC/PE",Investments_Clean!$F$2:$F$150,"Accepted"))>0,1,0)) -> 0 | BN31: =IF(BL31=0,"",IF((COUNTIFS(Investments_Clean!$A$2:$A$150,A31,Investments_Clean!$D$2:$D$150,"Angel",Investments_Clean!$F$2:$F$150,"Accepted"))>0,1,0)) -> 0 | BO31: =IF(BL31=0,"",IF((COUNTIFS(Investments_Clean!$A$2:$A$150,A31,Investments_Clean!$D$2:$D$150,"Accelerator",Investments_Clean!$F$2:$F$150,"Accepted"))>0,1,0)) -> 0 | BP31: =IF(BL31=0,"",IF((COUNTIFS(Investments_Clean!$A$2:$A$150,A31,Investments_Clean!$D$2:$D$150,"Corporate",Investments_Clean!$F$2:$F$150,"Accepted"))>0,1,0)) -> 0 | BQ31: =IF(BL31=0,"",IF((COUNTIFS(Investments_Clean!$A$2:$A$150,A31,Investments_Clean!$D$2:$D$150,"Government",Investments_Clean!$F$2:$F$150,"Accepted"))>0,1,0)) -> 1 | BR31: =IF(BL31=0,"",IF((COUNTIFS(Investments_Clean!$A$2:$A$150,A31,Investments_Clean!$D$2:$D$150,"Grant/Philanthropic",Investments_Clean!$F$2:$F$150,"Accepted")+COUNTIFS(Investments_Clean!$A$2:$A$150,A31,Investments_Clean!$D$2:$D$150,"DFI/Impact",Investments_Clean!$F$2:$F$150,"Accepted"))>0,1,0)) -> 0 | CA31: 0 | CC31: =IF(I31="","",IFERROR(IF(INDEX(Macro_Lookup!$B$2:$B$31,MATCH(I31,Macro_Lookup!$A$2:$A$31,0))="","",INDEX(Macro_Lookup!$B$2:$B$31,MATCH(I31,Macro_Lookup!$A$2:$A$31,0))),"")) | CD31: =IF(I31="","",IFERROR(IF(INDEX(Macro_Lookup!$C$2:$C$31,MATCH(I31,Macro_Lookup!$A$2:$A$31,0))="","",INDEX(Macro_Lookup!$C$2:$C$31,MATCH(I31,Macro_Lookup!$A$2:$A$31,0))),"")) | CE31: =IF(BJ31="","",IFERROR(IF(INDEX(Macro_Lookup!$B$2:$B$31,MATCH(BJ31,Macro_Lookup!$A$2:$A$31,0))="","",INDEX(Macro_Lookup!$B$2:$B$31,MATCH(BJ31,Macro_Lookup!$A$2:$A$31,0))),"")) | CF31: =IF(BJ31="","",IFERROR(IF(INDEX(Macro_Lookup!$C$2:$C$31,MATCH(BJ31,Macro_Lookup!$A$2:$A$31,0))="","",INDEX(Macro_Lookup!$C$2:$C$31,MATCH(BJ31,Macro_Lookup!$A$2:$A$31,0))),"")) | CG31: 7 | CH31: Original 100 (BD-ST-001..100); see Version_Log v1 (2026-10-06) | CI31: 2026-10-06
A32: BD-ST-031 | B32: HungryNaki | C32: Bangladesh | D32: Dhaka | E32: 0 | F32: Independent startup | G32: BD-ST-014 | I32: 2013 | K32: year | L32: 46295 | M32: =IF(I32="","",(YEAR(L32)-I32)*12+MONTH(L32)-IF(J32="",1,J32)) -> 164 | N32: =IF(M32="","",ROUND(M32/12,2)) -> 13.67 | O32: Logistics / Food Delivery | P32: Logistics/Travel | Q32: Marketplace, food delivery | R32: 0 | S32: 0 | T32: 1 | U32: 0 | V32: 0 | W32: 0 | X32: Shut down | Y32: 3 | Z32: 1 | AF32: =IF(SUMIF(Founders_Clean!$A$2:$A$159,A32,Founders_Clean!$C$2:$C$159)=0,"",SUMIF(Founders_Clean!$A$2:$A$159,A32,Founders_Clean!$C$2:$C$159)) -> 3 | AG32: =IF(AF32="","",SUMIF(Founders_Clean!$A$2:$A$159,A32,Founders_Clean!$D$2:$D$159)) -> 3 | AH32: =IF(AF32="","",SUMIF(Founders_Clean!$A$2:$A$159,A32,Founders_Clean!$E$2:$E$159)) -> 0 | AI32: =IF(AF32="","",IF((AG32+AH32)=0,"",AH32/(AG32+AH32))) -> 0 | AJ32: =IF(AI32="","",IF(AH32>0,1,0)) -> 0 | AK32: =IF(AI32="","",ROUND(1-(AI32^2+(1-AI32)^2),3)) -> 0 | AX32: Closed | AY32: High | AZ32: Closed 2023-07 after Daraz acquisition (2021) | BA32: 1 | BB32: 0 | BC32: 1 | BD32: 2023 | BE32: 7 | BF32: =IF(OR(I32="",BC32=""),"",IF(BC32=1,(BD32-I32)*12+IF(BE32="",7,BE32)-IF(J32="",1,J32),M32)) -> 126 | BG32: 0 | BH32: 0 | BI32: none | BK32: 0 | BL32: =COUNTIFS(Investments_Clean!$A$2:$A$150,A32,Investments_Clean!$F$2:$F$150,"Accepted") -> 1 | BM32: =IF(BL32=0,"",IF((COUNTIFS(Investments_Clean!$A$2:$A$150,A32,Investments_Clean!$D$2:$D$150,"VC/PE",Investments_Clean!$F$2:$F$150,"Accepted"))>0,1,0)) -> 0 | BN32: =IF(BL32=0,"",IF((COUNTIFS(Investments_Clean!$A$2:$A$150,A32,Investments_Clean!$D$2:$D$150,"Angel",Investments_Clean!$F$2:$F$150,"Accepted"))>0,1,0)) -> 0 | BO32: =IF(BL32=0,"",IF((COUNTIFS(Investments_Clean!$A$2:$A$150,A32,Investments_Clean!$D$2:$D$150,"Accelerator",Investments_Clean!$F$2:$F$150,"Accepted"))>0,1,0)) -> 0 | BP32: =IF(BL32=0,"",IF((COUNTIFS(Investments_Clean!$A$2:$A$150,A32,Investments_Clean!$D$2:$D$150,"Corporate",Investments_Clean!$F$2:$F$150,"Accepted"))>0,1,0)) -> 1 | BQ32: =IF(BL32=0,"",IF((COUNTIFS(Investments_Clean!$A$2:$A$150,A32,Investments_Clean!$D$2:$D$150,"Government",Investments_Clean!$F$2:$F$150,"Accepted"))>0,1,0)) -> 0 | BR32: =IF(BL32=0,"",IF((COUNTIFS(Investments_Clean!$A$2:$A$150,A32,Investments_Clean!$D$2:$D$150,"Grant/Philanthropic",Investments_Clean!$F$2:$F$150,"Accepted")+COUNTIFS(Investments_Clean!$A$2:$A$150,A32,Investments_Clean!$D$2:$D$150,"DFI/Impact",Investments_Clean!$F$2:$F$150,"Accepted"))>0,1,0)) -> 0 | CA32: 0 | CC32: =IF(I32="","",IFERROR(IF(INDEX(Macro_Lookup!$B$2:$B$31,MATCH(I32,Macro_Lookup!$A$2:$A$31,0))="","",INDEX(Macro_Lookup!$B$2:$B$31,MATCH(I32,Macro_Lookup!$A$2:$A$31,0))),"")) | CD32: =IF(I32="","",IFERROR(IF(INDEX(Macro_Lookup!$C$2:$C$31,MATCH(I32,Macro_Lookup!$A$2:$A$31,0))="","",INDEX(Macro_Lookup!$C$2:$C$31,MATCH(I32,Macro_Lookup!$A$2:$A$31,0))),"")) | CE32: =IF(BJ32="","",IFERROR(IF(INDEX(Macro_Lookup!$B$2:$B$31,MATCH(BJ32,Macro_Lookup!$A$2:$A$31,0))="","",INDEX(Macro_Lookup!$B$2:$B$31,MATCH(BJ32,Macro_Lookup!$A$2:$A$31,0))),"")) | CF32: =IF(BJ32="","",IFERROR(IF(INDEX(Macro_Lookup!$C$2:$C$31,MATCH(BJ32,Macro_Lookup!$A$2:$A$31,0))="","",INDEX(Macro_Lookup!$C$2:$C$31,MATCH(BJ32,Macro_Lookup!$A$2:$A$31,0))),"")) | CG32: 8 | CH32: Original 100 (BD-ST-001..100); see Version_Log v1 (2026-10-06) | CI32: 2026-10-06
A33: BD-ST-032 | B33: Foodpanda Bangladesh | C33: Bangladesh | D33: Dhaka | E33: 0 | F33: Independent startup | I33: 2013 | K33: year | L33: 46295 | M33: =IF(I33="","",(YEAR(L33)-I33)*12+MONTH(L33)-IF(J33="",1,J33)) -> 164 | N33: =IF(M33="","",ROUND(M33/12,2)) -> 13.67 | O33: Logistics / Food Delivery | P33: Logistics/Travel | Q33: Marketplace, food & grocery delivery | R33: 0 | S33: 0 | T33: 1 | U33: 0 | V33: 0 | W33: 0 | X33: Live/Scaling | Y33: 3 | Z33: 1 | AF33: =IF(SUMIF(Founders_Clean!$A$2:$A$159,A33,Founders_Clean!$C$2:$C$159)=0,"",SUMIF(Founders_Clean!$A$2:$A$159,A33,Founders_Clean!$C$2:$C$159)) -> 2 | AG33: =IF(AF33="","",SUMIF(Founders_Clean!$A$2:$A$159,A33,Founders_Clean!$D$2:$D$159)) -> 1 | AH33: =IF(AF33="","",SUMIF(Founders_Clean!$A$2:$A$159,A33,Founders_Clean!$E$2:$E$159)) -> 1 | AI33: =IF(AF33="","",IF((AG33+AH33)=0,"",AH33/(AG33+AH33))) -> 0.5 | AJ33: =IF(AI33="","",IF(AH33>0,1,0)) -> 1 | AK33: =IF(AI33="","",ROUND(1-(AI33^2+(1-AI33)^2),3)) -> 0.5 | AX33: Active | AY33: High | BA33: 1 | BB33: 0 | BC33: 0 | BF33: =IF(OR(I33="",BC33=""),"",IF(BC33=1,(BD33-I33)*12+IF(BE33="",7,BE33)-IF(J33="",1,J33),M33)) -> 164 | BK33: 1 | BL33: =COUNTIFS(Investments_Clean!$A$2:$A$150,A33,Investments_Clean!$F$2:$F$150,"Accepted") -> 1 | BM33: =IF(BL33=0,"",IF((COUNTIFS(Investments_Clean!$A$2:$A$150,A33,Investments_Clean!$D$2:$D$150,"VC/PE",Investments_Clean!$F$2:$F$150,"Accepted"))>0,1,0)) -> 0 | BN33: =IF(BL33=0,"",IF((COUNTIFS(Investments_Clean!$A$2:$A$150,A33,Investments_Clean!$D$2:$D$150,"Angel",Investments_Clean!$F$2:$F$150,"Accepted"))>0,1,0)) -> 0 | BO33: =IF(BL33=0,"",IF((COUNTIFS(Investments_Clean!$A$2:$A$150,A33,Investments_Clean!$D$2:$D$150,"Accelerator",Investments_Clean!$F$2:$F$150,"Accepted"))>0,1,0)) -> 0 | BP33: =IF(BL33=0,"",IF((COUNTIFS(Investments_Clean!$A$2:$A$150,A33,Investments_Clean!$D$2:$D$150,"Corporate",Investments_Clean!$F$2:$F$150,"Accepted"))>0,1,0)) -> 1 | BQ33: =IF(BL33=0,"",IF((COUNTIFS(Investments_Clean!$A$2:$A$150,A33,Investments_Clean!$D$2:$D$150,"Government",Investments_Clean!$F$2:$F$150,"Accepted"))>0,1,0)) -> 0 | BR33: =IF(BL33=0,"",IF((COUNTIFS(Investments_Clean!$A$2:$A$150,A33,Investments_Clean!$D$2:$D$150,"Grant/Philanthropic",Investments_Clean!$F$2:$F$150,"Accepted")+COUNTIFS(Investments_Clean!$A$2:$A$150,A33,Investments_Clean!$D$2:$D$150,"DFI/Impact",Investments_Clean!$F$2:$F$150,"Accepted"))>0,1,0)) -> 0 | CA33: 0 | CC33: =IF(I33="","",IFERROR(IF(INDEX(Macro_Lookup!$B$2:$B$31,MATCH(I33,Macro_Lookup!$A$2:$A$31,0))="","",INDEX(Macro_Lookup!$B$2:$B$31,MATCH(I33,Macro_Lookup!$A$2:$A$31,0))),"")) | CD33: =IF(I33="","",IFERROR(IF(INDEX(Macro_Lookup!$C$2:$C$31,MATCH(I33,Macro_Lookup!$A$2:$A$31,0))="","",INDEX(Macro_Lookup!$C$2:$C$31,MATCH(I33,Macro_Lookup!$A$2:$A$31,0))),"")) | CE33: =IF(BJ33="","",IFERROR(IF(INDEX(Macro_Lookup!$B$2:$B$31,MATCH(BJ33,Macro_Lookup!$A$2:$A$31,0))="","",INDEX(Macro_Lookup!$B$2:$B$31,MATCH(BJ33,Macro_Lookup!$A$2:$A$31,0))),"")) | CF33: =IF(BJ33="","",IFERROR(IF(INDEX(Macro_Lookup!$C$2:$C$31,MATCH(BJ33,Macro_Lookup!$A$2:$A$31,0))="","",INDEX(Macro_Lookup!$C$2:$C$31,MATCH(BJ33,Macro_Lookup!$A$2:$A$31,0))),"")) | CG33: 8 | CH33: Original 100 (BD-ST-001..100); see Version_Log v1 (2026-10-06) | CI33: 2026-10-06
A34: BD-ST-033 | B34: GoZayaan | C34: Bangladesh | D34: Dhaka | E34: 0 | F34: Independent startup | I34: 2017 | K34: year | L34: 46295 | M34: =IF(I34="","",(YEAR(L34)-I34)*12+MONTH(L34)-IF(J34="",1,J34)) -> 116 | N34: =IF(M34="","",ROUND(M34/12,2)) -> 9.67 | O34: Travel / Tourism | P34: Logistics/Travel | Q34: OTA marketplace | R34: 0 | S34: 0 | T34: 1 | U34: 0 | V34: 0 | W34: 0 | X34: Live/Scaling | Y34: 3 | Z34: 1 | AF34: =IF(SUMIF(Founders_Clean!$A$2:$A$159,A34,Founders_Clean!$C$2:$C$159)=0,"",SUMIF(Founders_Clean!$A$2:$A$159,A34,Founders_Clean!$C$2:$C$159)) -> 1 | AG34: =IF(AF34="","",SUMIF(Founders_Clean!$A$2:$A$159,A34,Founders_Clean!$D$2:$D$159)) -> 1 | AH34: =IF(AF34="","",SUMIF(Founders_Clean!$A$2:$A$159,A34,Founders_Clean!$E$2:$E$159)) -> 0 | AI34: =IF(AF34="","",IF((AG34+AH34)=0,"",AH34/(AG34+AH34))) -> 0 | AJ34: =IF(AI34="","",IF(AH34>0,1,0)) -> 0 | AK34: =IF(AI34="","",ROUND(1-(AI34^2+(1-AI34)^2),3)) -> 0 | AM34: 1 | AN34: Bachelor's | AO34: 1 | AP34: 1 | AQ34: 1 | AR34: 9 | AS34: 9 | AX34: Active | AY34: High | BA34: 0 | BB34: 0 | BC34: 0 | BF34: =IF(OR(I34="",BC34=""),"",IF(BC34=1,(BD34-I34)*12+IF(BE34="",7,BE34)-IF(J34="",1,J34),M34)) -> 116 | BG34: 1 | BH34: 4600000 | BI34: round | BJ34: 2022 | BK34: 1 | BL34: =COUNTIFS(Investments_Clean!$A$2:$A$150,A34,Investments_Clean!$F$2:$F$150,"Accepted") -> 1 | BM34: =IF(BL34=0,"",IF((COUNTIFS(Investments_Clean!$A$2:$A$150,A34,Investments_Clean!$D$2:$D$150,"VC/PE",Investments_Clean!$F$2:$F$150,"Accepted"))>0,1,0)) -> 1 | BN34: =IF(BL34=0,"",IF((COUNTIFS(Investments_Clean!$A$2:$A$150,A34,Investments_Clean!$D$2:$D$150,"Angel",Investments_Clean!$F$2:$F$150,"Accepted"))>0,1,0)) -> 0 | BO34: =IF(BL34=0,"",IF((COUNTIFS(Investments_Clean!$A$2:$A$150,A34,Investments_Clean!$D$2:$D$150,"Accelerator",Investments_Clean!$F$2:$F$150,"Accepted"))>0,1,0)) -> 0 | BP34: =IF(BL34=0,"",IF((COUNTIFS(Investments_Clean!$A$2:$A$150,A34,Investments_Clean!$D$2:$D$150,"Corporate",Investments_Clean!$F$2:$F$150,"Accepted"))>0,1,0)) -> 0 | BQ34: =IF(BL34=0,"",IF((COUNTIFS(Investments_Clean!$A$2:$A$150,A34,Investments_Clean!$D$2:$D$150,"Government",Investments_Clean!$F$2:$F$150,"Accepted"))>0,1,0)) -> 0 | BR34: =IF(BL34=0,"",IF((COUNTIFS(Investments_Clean!$A$2:$A$150,A34,Investments_Clean!$D$2:$D$150,"Grant/Philanthropic",Investments_Clean!$F$2:$F$150,"Accepted")+COUNTIFS(Investments_Clean!$A$2:$A$150,A34,Investments_Clean!$D$2:$D$150,"DFI/Impact",Investments_Clean!$F$2:$F$150,"Accepted"))>0,1,0)) -> 0 | CA34: 0 | CC34: =IF(I34="","",IFERROR(IF(INDEX(Macro_Lookup!$B$2:$B$31,MATCH(I34,Macro_Lookup!$A$2:$A$31,0))="","",INDEX(Macro_Lookup!$B$2:$B$31,MATCH(I34,Macro_Lookup!$A$2:$A$31,0))),"")) | CD34: =IF(I34="","",IFERROR(IF(INDEX(Macro_Lookup!$C$2:$C$31,MATCH(I34,Macro_Lookup!$A$2:$A$31,0))="","",INDEX(Macro_Lookup!$C$2:$C$31,MATCH(I34,Macro_Lookup!$A$2:$A$31,0))),"")) | CE34: =IF(BJ34="","",IFERROR(IF(INDEX(Macro_Lookup!$B$2:$B$31,MATCH(BJ34,Macro_Lookup!$A$2:$A$31,0))="","",INDEX(Macro_Lookup!$B$2:$B$31,MATCH(BJ34,Macro_Lookup!$A$2:$A$31,0))),"")) | CF34: =IF(BJ34="","",IFERROR(IF(INDEX(Macro_Lookup!$C$2:$C$31,MATCH(BJ34,Macro_Lookup!$A$2:$A$31,0))="","",INDEX(Macro_Lookup!$C$2:$C$31,MATCH(BJ34,Macro_Lookup!$A$2:$A$31,0))),"")) | CG34: 4 | CH34: Original 100 (BD-ST-001..100); see Version_Log v1 (2026-10-06) | CI34: 2026-10-06
A35: BD-ST-034 | B35: ShareTrip | C35: Bangladesh | D35: Dhaka | E35: 0 | F35: Independent startup | I35: 2014 | K35: year | L35: 46295 | M35: =IF(I35="","",(YEAR(L35)-I35)*12+MONTH(L35)-IF(J35="",1,J35)) -> 152 | N35: =IF(M35="","",ROUND(M35/12,2)) -> 12.67 | O35: Travel / Tourism | P35: Logistics/Travel | Q35: OTA marketplace | R35: 0 | S35: 0 | T35: 1 | U35: 0 | V35: 0 | W35: 0 | X35: Live/Scaling | Y35: 3 | Z35: 1 | AF35: =IF(SUMIF(Founders_Clean!$A$2:$A$159,A35,Founders_Clean!$C$2:$C$159)=0,"",SUMIF(Founders_Clean!$A$2:$A$159,A35,Founders_Clean!$C$2:$C$159)) -> 2 | AG35: =IF(AF35="","",SUMIF(Founders_Clean!$A$2:$A$159,A35,Founders_Clean!$D$2:$D$159)) -> 1 | AH35: =IF(AF35="","",SUMIF(Founders_Clean!$A$2:$A$159,A35,Founders_Clean!$E$2:$E$159)) -> 1 | AI35: =IF(AF35="","",IF((AG35+AH35)=0,"",AH35/(AG35+AH35))) -> 0.5 | AJ35: =IF(AI35="","",IF(AH35>0,1,0)) -> 1 | AK35: =IF(AI35="","",ROUND(1-(AI35^2+(1-AI35)^2),3)) -> 0.5 | AM35: 1 | AN35: Bachelor's | AO35: 0 | AP35: 0 | AQ35: 0 | AR35: 10 | AS35: 10 | AX35: Active | AY35: High | BA35: 0 | BB35: 0 | BC35: 0 | BF35: =IF(OR(I35="",BC35=""),"",IF(BC35=1,(BD35-I35)*12+IF(BE35="",7,BE35)-IF(J35="",1,J35),M35)) -> 152 | BG35: 1 | BH35: 500000 | BI35: round | BJ35: 2022 | BK35: 1 | BL35: =COUNTIFS(Investments_Clean!$A$2:$A$150,A35,Investments_Clean!$F$2:$F$150,"Accepted") -> 1 | BM35: =IF(BL35=0,"",IF((COUNTIFS(Investments_Clean!$A$2:$A$150,A35,Investments_Clean!$D$2:$D$150,"VC/PE",Investments_Clean!$F$2:$F$150,"Accepted"))>0,1,0)) -> 0 | BN35: =IF(BL35=0,"",IF((COUNTIFS(Investments_Clean!$A$2:$A$150,A35,Investments_Clean!$D$2:$D$150,"Angel",Investments_Clean!$F$2:$F$150,"Accepted"))>0,1,0)) -> 0 | BO35: =IF(BL35=0,"",IF((COUNTIFS(Investments_Clean!$A$2:$A$150,A35,Investments_Clean!$D$2:$D$150,"Accelerator",Investments_Clean!$F$2:$F$150,"Accepted"))>0,1,0)) -> 0 | BP35: =IF(BL35=0,"",IF((COUNTIFS(Investments_Clean!$A$2:$A$150,A35,Investments_Clean!$D$2:$D$150,"Corporate",Investments_Clean!$F$2:$F$150,"Accepted"))>0,1,0)) -> 0 | BQ35: =IF(BL35=0,"",IF((COUNTIFS(Investments_Clean!$A$2:$A$150,A35,Investments_Clean!$D$2:$D$150,"Government",Investments_Clean!$F$2:$F$150,"Accepted"))>0,1,0)) -> 1 | BR35: =IF(BL35=0,"",IF((COUNTIFS(Investments_Clean!$A$2:$A$150,A35,Investments_Clean!$D$2:$D$150,"Grant/Philanthropic",Investments_Clean!$F$2:$F$150,"Accepted")+COUNTIFS(Investments_Clean!$A$2:$A$150,A35,Investments_Clean!$D$2:$D$150,"DFI/Impact",Investments_Clean!$F$2:$F$150,"Accepted"))>0,1,0)) -> 0 | CA35: 0 | CC35: =IF(I35="","",IFERROR(IF(INDEX(Macro_Lookup!$B$2:$B$31,MATCH(I35,Macro_Lookup!$A$2:$A$31,0))="","",INDEX(Macro_Lookup!$B$2:$B$31,MATCH(I35,Macro_Lookup!$A$2:$A$31,0))),"")) | CD35: =IF(I35="","",IFERROR(IF(INDEX(Macro_Lookup!$C$2:$C$31,MATCH(I35,Macro_Lookup!$A$2:$A$31,0))="","",INDEX(Macro_Lookup!$C$2:$C$31,MATCH(I35,Macro_Lookup!$A$2:$A$31,0))),"")) | CE35: =IF(BJ35="","",IFERROR(IF(INDEX(Macro_Lookup!$B$2:$B$31,MATCH(BJ35,Macro_Lookup!$A$2:$A$31,0))="","",INDEX(Macro_Lookup!$B$2:$B$31,MATCH(BJ35,Macro_Lookup!$A$2:$A$31,0))),"")) | CF35: =IF(BJ35="","",IFERROR(IF(INDEX(Macro_Lookup!$C$2:$C$31,MATCH(BJ35,Macro_Lookup!$A$2:$A$31,0))="","",INDEX(Macro_Lookup!$C$2:$C$31,MATCH(BJ35,Macro_Lookup!$A$2:$A$31,0))),"")) | CG35: 4 | CH35: Original 100 (BD-ST-001..100); see Version_Log v1 (2026-10-06) | CI35: 2026-10-06
A36: BD-ST-035 | B36: Bproperty | C36: Bangladesh | D36: Dhaka | E36: 0 | F36: Independent startup | I36: 2016 | K36: year | L36: 46295 | M36: =IF(I36="","",(YEAR(L36)-I36)*12+MONTH(L36)-IF(J36="",1,J36)) -> 128 | N36: =IF(M36="","",ROUND(M36/12,2)) -> 10.67 | O36: Real Estate / PropTech | P36: Other | Q36: Marketplace, real estate brokerage | R36: 0 | S36: 0 | T36: 1 | U36: 0 | V36: 0 | W36: 0 | X36: Unclear, possibly inactive | AF36: =IF(SUMIF(Founders_Clean!$A$2:$A$159,A36,Founders_Clean!$C$2:$C$159)=0,"",SUMIF(Founders_Clean!$A$2:$A$159,A36,Founders_Clean!$C$2:$C$159)) -> 1 | AG36: =IF(AF36="","",SUMIF(Founders_Clean!$A$2:$A$159,A36,Founders_Clean!$D$2:$D$159)) -> 1 | AH36: =IF(AF36="","",SUMIF(Founders_Clean!$A$2:$A$159,A36,Founders_Clean!$E$2:$E$159)) -> 0 | AI36: =IF(AF36="","",IF((AG36+AH36)=0,"",AH36/(AG36+AH36))) -> 0 | AJ36: =IF(AI36="","",IF(AH36>0,1,0)) -> 0 | AK36: =IF(AI36="","",ROUND(1-(AI36^2+(1-AI36)^2),3)) -> 0 | AX36: Unknown | AY36: Low | AZ36: Status unclear (acquired by DCG 2023; Rupayan investment 2025) | BA36: 1 | BB36: 0 | BF36: =IF(OR(I36="",BC36=""),"",IF(BC36=1,(BD36-I36)*12+IF(BE36="",7,BE36)-IF(J36="",1,J36),M36)) | BK36: 1 | BL36: =COUNTIFS(Investments_Clean!$A$2:$A$150,A36,Investments_Clean!$F$2:$F$150,"Accepted") -> 3 | BM36: =IF(BL36=0,"",IF((COUNTIFS(Investments_Clean!$A$2:$A$150,A36,Investments_Clean!$D$2:$D$150,"VC/PE",Investments_Clean!$F$2:$F$150,"Accepted"))>0,1,0)) -> 0 | BN36: =IF(BL36=0,"",IF((COUNTIFS(Investments_Clean!$A$2:$A$150,A36,Investments_Clean!$D$2:$D$150,"Angel",Investments_Clean!$F$2:$F$150,"Accepted"))>0,1,0)) -> 0 | BO36: =IF(BL36=0,"",IF((COUNTIFS(Investments_Clean!$A$2:$A$150,A36,Investments_Clean!$D$2:$D$150,"Accelerator",Investments_Clean!$F$2:$F$150,"Accepted"))>0,1,0)) -> 0 | BP36: =IF(BL36=0,"",IF((COUNTIFS(Investments_Clean!$A$2:$A$150,A36,Investments_Clean!$D$2:$D$150,"Corporate",Investments_Clean!$F$2:$F$150,"Accepted"))>0,1,0)) -> 1 | BQ36: =IF(BL36=0,"",IF((COUNTIFS(Investments_Clean!$A$2:$A$150,A36,Investments_Clean!$D$2:$D$150,"Government",Investments_Clean!$F$2:$F$150,"Accepted"))>0,1,0)) -> 0 | BR36: =IF(BL36=0,"",IF((COUNTIFS(Investments_Clean!$A$2:$A$150,A36,Investments_Clean!$D$2:$D$150,"Grant/Philanthropic",Investments_Clean!$F$2:$F$150,"Accepted")+COUNTIFS(Investments_Clean!$A$2:$A$150,A36,Investments_Clean!$D$2:$D$150,"DFI/Impact",Investments_Clean!$F$2:$F$150,"Accepted"))>0,1,0)) -> 0 | CA36: 0 | CC36: =IF(I36="","",IFERROR(IF(INDEX(Macro_Lookup!$B$2:$B$31,MATCH(I36,Macro_Lookup!$A$2:$A$31,0))="","",INDEX(Macro_Lookup!$B$2:$B$31,MATCH(I36,Macro_Lookup!$A$2:$A$31,0))),"")) | CD36: =IF(I36="","",IFERROR(IF(INDEX(Macro_Lookup!$C$2:$C$31,MATCH(I36,Macro_Lookup!$A$2:$A$31,0))="","",INDEX(Macro_Lookup!$C$2:$C$31,MATCH(I36,Macro_Lookup!$A$2:$A$31,0))),"")) | CE36: =IF(BJ36="","",IFERROR(IF(INDEX(Macro_Lookup!$B$2:$B$31,MATCH(BJ36,Macro_Lookup!$A$2:$A$31,0))="","",INDEX(Macro_Lookup!$B$2:$B$31,MATCH(BJ36,Macro_Lookup!$A$2:$A$31,0))),"")) | CF36: =IF(BJ36="","",IFERROR(IF(INDEX(Macro_Lookup!$C$2:$C$31,MATCH(BJ36,Macro_Lookup!$A$2:$A$31,0))="","",INDEX(Macro_Lookup!$C$2:$C$31,MATCH(BJ36,Macro_Lookup!$A$2:$A$31,0))),"")) | CG36: 8 | CH36: Original 100 (BD-ST-001..100); see Version_Log v1 (2026-10-06) | CI36: 2026-10-06
A37: BD-ST-036 | B37: 10 Minute School | C37: Bangladesh | D37: Dhaka | E37: 0 | F37: Independent startup | I37: 2015 | K37: year | L37: 46295 | M37: =IF(I37="","",(YEAR(L37)-I37)*12+MONTH(L37)-IF(J37="",1,J37)) -> 140 | N37: =IF(M37="","",ROUND(M37/12,2)) -> 11.67 | O37: EdTech | P37: EdTech | Q37: B2C EdTech subscription | R37: 0 | S37: 1 | T37: 0 | U37: 1 | V37: 0 | W37: 0 | X37: Live/Scaling | Y37: 3 | Z37: 1 | AA37: 1 | AB37: Surge (Sequoia/Peak XV) | AF37: =IF(SUMIF(Founders_Clean!$A$2:$A$159,A37,Founders_Clean!$C$2:$C$159)=0,"",SUMIF(Founders_Clean!$A$2:$A$159,A37,Founders_Clean!$C$2:$C$159)) -> 1 | AG37: =IF(AF37="","",SUMIF(Founders_Clean!$A$2:$A$159,A37,Founders_Clean!$D$2:$D$159)) -> 1 | AH37: =IF(AF37="","",SUMIF(Founders_Clean!$A$2:$A$159,A37,Founders_Clean!$E$2:$E$159)) -> 0 | AI37: =IF(AF37="","",IF((AG37+AH37)=0,"",AH37/(AG37+AH37))) -> 0 | AJ37: =IF(AI37="","",IF(AH37>0,1,0)) -> 0 | AK37: =IF(AI37="","",ROUND(1-(AI37^2+(1-AI37)^2),3)) -> 0 | AM37: 1 | AN37: Bachelor's | AO37: 0 | AP37: 0 | AQ37: 0 | AR37: 0 | AS37: 0 | AX37: Active | AY37: High | BA37: 0 | BB37: 0 | BC37: 0 | BF37: =IF(OR(I37="",BC37=""),"",IF(BC37=1,(BD37-I37)*12+IF(BE37="",7,BE37)-IF(J37="",1,J37),M37)) -> 140 | BG37: 1 | BH37: 5500000 | BI37: round | BJ37: 2023 | BK37: 1 | BL37: =COUNTIFS(Investments_Clean!$A$2:$A$150,A37,Investments_Clean!$F$2:$F$150,"Accepted") -> 1 | BM37: =IF(BL37=0,"",IF((COUNTIFS(Investments_Clean!$A$2:$A$150,A37,Investments_Clean!$D$2:$D$150,"VC/PE",Investments_Clean!$F$2:$F$150,"Accepted"))>0,1,0)) -> 1 | BN37: =IF(BL37=0,"",IF((COUNTIFS(Investments_Clean!$A$2:$A$150,A37,Investments_Clean!$D$2:$D$150,"Angel",Investments_Clean!$F$2:$F$150,"Accepted"))>0,1,0)) -> 0 | BO37: =IF(BL37=0,"",IF((COUNTIFS(Investments_Clean!$A$2:$A$150,A37,Investments_Clean!$D$2:$D$150,"Accelerator",Investments_Clean!$F$2:$F$150,"Accepted"))>0,1,0)) -> 0 | BP37: =IF(BL37=0,"",IF((COUNTIFS(Investments_Clean!$A$2:$A$150,A37,Investments_Clean!$D$2:$D$150,"Corporate",Investments_Clean!$F$2:$F$150,"Accepted"))>0,1,0)) -> 0 | BQ37: =IF(BL37=0,"",IF((COUNTIFS(Investments_Clean!$A$2:$A$150,A37,Investments_Clean!$D$2:$D$150,"Government",Investments_Clean!$F$2:$F$150,"Accepted"))>0,1,0)) -> 0 | BR37: =IF(BL37=0,"",IF((COUNTIFS(Investments_Clean!$A$2:$A$150,A37,Investments_Clean!$D$2:$D$150,"Grant/Philanthropic",Investments_Clean!$F$2:$F$150,"Accepted")+COUNTIFS(Investments_Clean!$A$2:$A$150,A37,Investments_Clean!$D$2:$D$150,"DFI/Impact",Investments_Clean!$F$2:$F$150,"Accepted"))>0,1,0)) -> 0 | CA37: 0 | CC37: =IF(I37="","",IFERROR(IF(INDEX(Macro_Lookup!$B$2:$B$31,MATCH(I37,Macro_Lookup!$A$2:$A$31,0))="","",INDEX(Macro_Lookup!$B$2:$B$31,MATCH(I37,Macro_Lookup!$A$2:$A$31,0))),"")) | CD37: =IF(I37="","",IFERROR(IF(INDEX(Macro_Lookup!$C$2:$C$31,MATCH(I37,Macro_Lookup!$A$2:$A$31,0))="","",INDEX(Macro_Lookup!$C$2:$C$31,MATCH(I37,Macro_Lookup!$A$2:$A$31,0))),"")) | CE37: =IF(BJ37="","",IFERROR(IF(INDEX(Macro_Lookup!$B$2:$B$31,MATCH(BJ37,Macro_Lookup!$A$2:$A$31,0))="","",INDEX(Macro_Lookup!$B$2:$B$31,MATCH(BJ37,Macro_Lookup!$A$2:$A$31,0))),"")) | CF37: =IF(BJ37="","",IFERROR(IF(INDEX(Macro_Lookup!$C$2:$C$31,MATCH(BJ37,Macro_Lookup!$A$2:$A$31,0))="","",INDEX(Macro_Lookup!$C$2:$C$31,MATCH(BJ37,Macro_Lookup!$A$2:$A$31,0))),"")) | CG37: 3 | CH37: Original 100 (BD-ST-001..100); see Version_Log v1 (2026-10-06) | CI37: 2026-10-06
A38: BD-ST-037 | B38: Shikho | C38: Bangladesh | D38: Dhaka | E38: 0 | F38: Independent startup | I38: 2019 | K38: year | L38: 46295 | M38: =IF(I38="","",(YEAR(L38)-I38)*12+MONTH(L38)-IF(J38="",1,J38)) -> 92 | N38: =IF(M38="","",ROUND(M38/12,2)) -> 7.67 | O38: EdTech | P38: EdTech | Q38: B2C EdTech subscription | R38: 0 | S38: 1 | T38: 0 | U38: 1 | V38: 0 | W38: 0 | X38: Live/Scaling | Y38: 3 | Z38: 1 | AF38: =IF(SUMIF(Founders_Clean!$A$2:$A$159,A38,Founders_Clean!$C$2:$C$159)=0,"",SUMIF(Founders_Clean!$A$2:$A$159,A38,Founders_Clean!$C$2:$C$159)) -> 2 | AG38: =IF(AF38="","",SUMIF(Founders_Clean!$A$2:$A$159,A38,Founders_Clean!$D$2:$D$159)) -> 2 | AH38: =IF(AF38="","",SUMIF(Founders_Clean!$A$2:$A$159,A38,Founders_Clean!$E$2:$E$159)) -> 0 | AI38: =IF(AF38="","",IF((AG38+AH38)=0,"",AH38/(AG38+AH38))) -> 0 | AJ38: =IF(AI38="","",IF(AH38>0,1,0)) -> 0 | AK38: =IF(AI38="","",ROUND(1-(AI38^2+(1-AI38)^2),3)) -> 0 | AM38: 1 | AN38: Bachelor's | AO38: 0 | AP38: 0 | AQ38: 0 | AR38: 10 | AS38: 9.5 | AX38: Active | AY38: High | BA38: 0 | BB38: 0 | BC38: 0 | BF38: =IF(OR(I38="",BC38=""),"",IF(BC38=1,(BD38-I38)*12+IF(BE38="",7,BE38)-IF(J38="",1,J38),M38)) -> 92 | BG38: 1 | BH38: 4000000 | BI38: round | BJ38: 2022 | BK38: 1 | BL38: =COUNTIFS(Investments_Clean!$A$2:$A$150,A38,Investments_Clean!$F$2:$F$150,"Accepted") -> 1 | BM38: =IF(BL38=0,"",IF((COUNTIFS(Investments_Clean!$A$2:$A$150,A38,Investments_Clean!$D$2:$D$150,"VC/PE",Investments_Clean!$F$2:$F$150,"Accepted"))>0,1,0)) -> 1 | BN38: =IF(BL38=0,"",IF((COUNTIFS(Investments_Clean!$A$2:$A$150,A38,Investments_Clean!$D$2:$D$150,"Angel",Investments_Clean!$F$2:$F$150,"Accepted"))>0,1,0)) -> 0 | BO38: =IF(BL38=0,"",IF((COUNTIFS(Investments_Clean!$A$2:$A$150,A38,Investments_Clean!$D$2:$D$150,"Accelerator",Investments_Clean!$F$2:$F$150,"Accepted"))>0,1,0)) -> 0 | BP38: =IF(BL38=0,"",IF((COUNTIFS(Investments_Clean!$A$2:$A$150,A38,Investments_Clean!$D$2:$D$150,"Corporate",Investments_Clean!$F$2:$F$150,"Accepted"))>0,1,0)) -> 0 | BQ38: =IF(BL38=0,"",IF((COUNTIFS(Investments_Clean!$A$2:$A$150,A38,Investments_Clean!$D$2:$D$150,"Government",Investments_Clean!$F$2:$F$150,"Accepted"))>0,1,0)) -> 0 | BR38: =IF(BL38=0,"",IF((COUNTIFS(Investments_Clean!$A$2:$A$150,A38,Investments_Clean!$D$2:$D$150,"Grant/Philanthropic",Investments_Clean!$F$2:$F$150,"Accepted")+COUNTIFS(Investments_Clean!$A$2:$A$150,A38,Investments_Clean!$D$2:$D$150,"DFI/Impact",Investments_Clean!$F$2:$F$150,"Accepted"))>0,1,0)) -> 0 | CA38: 0 | CC38: =IF(I38="","",IFERROR(IF(INDEX(Macro_Lookup!$B$2:$B$31,MATCH(I38,Macro_Lookup!$A$2:$A$31,0))="","",INDEX(Macro_Lookup!$B$2:$B$31,MATCH(I38,Macro_Lookup!$A$2:$A$31,0))),"")) | CD38: =IF(I38="","",IFERROR(IF(INDEX(Macro_Lookup!$C$2:$C$31,MATCH(I38,Macro_Lookup!$A$2:$A$31,0))="","",INDEX(Macro_Lookup!$C$2:$C$31,MATCH(I38,Macro_Lookup!$A$2:$A$31,0))),"")) | CE38: =IF(BJ38="","",IFERROR(IF(INDEX(Macro_Lookup!$B$2:$B$31,MATCH(BJ38,Macro_Lookup!$A$2:$A$31,0))="","",INDEX(Macro_Lookup!$B$2:$B$31,MATCH(BJ38,Macro_Lookup!$A$2:$A$31,0))),"")) | CF38: =IF(BJ38="","",IFERROR(IF(INDEX(Macro_Lookup!$C$2:$C$31,MATCH(BJ38,Macro_Lookup!$A$2:$A$31,0))="","",INDEX(Macro_Lookup!$C$2:$C$31,MATCH(BJ38,Macro_Lookup!$A$2:$A$31,0))),"")) | CG38: 4 | CH38: Original 100 (BD-ST-001..100); see Version_Log v1 (2026-10-06) | CI38: 2026-10-06
A39: BD-ST-038 | B39: Bohubrihi | C39: Bangladesh | D39: Dhaka | E39: 0 | F39: Independent startup | G39: BD-ST-037 | I39: 2016 | K39: year | L39: 46295 | M39: =IF(I39="","",(YEAR(L39)-I39)*12+MONTH(L39)-IF(J39="",1,J39)) -> 128 | N39: =IF(M39="","",ROUND(M39/12,2)) -> 10.67 | O39: EdTech | P39: EdTech | Q39: B2C EdTech marketplace | R39: 0 | S39: 1 | T39: 1 | U39: 0 | V39: 0 | W39: 0 | X39: Acquired | Y39: 3 | Z39: 1 | AF39: =IF(SUMIF(Founders_Clean!$A$2:$A$159,A39,Founders_Clean!$C$2:$C$159)=0,"",SUMIF(Founders_Clean!$A$2:$A$159,A39,Founders_Clean!$C$2:$C$159)) -> 2 | AG39: =IF(AF39="","",SUMIF(Founders_Clean!$A$2:$A$159,A39,Founders_Clean!$D$2:$D$159)) -> 2 | AH39: =IF(AF39="","",SUMIF(Founders_Clean!$A$2:$A$159,A39,Founders_Clean!$E$2:$E$159)) -> 0 | AI39: =IF(AF39="","",IF((AG39+AH39)=0,"",AH39/(AG39+AH39))) -> 0 | AJ39: =IF(AI39="","",IF(AH39>0,1,0)) -> 0 | AK39: =IF(AI39="","",ROUND(1-(AI39^2+(1-AI39)^2),3)) -> 0 | AX39: Acquired | AY39: High | BA39: 1 | BB39: 0 | BC39: 0 | BF39: =IF(OR(I39="",BC39=""),"",IF(BC39=1,(BD39-I39)*12+IF(BE39="",7,BE39)-IF(J39="",1,J39),M39)) -> 128 | BL39: =COUNTIFS(Investments_Clean!$A$2:$A$150,A39,Investments_Clean!$F$2:$F$150,"Accepted") -> 0 | BM39: =IF(BL39=0,"",IF((COUNTIFS(Investments_Clean!$A$2:$A$150,A39,Investments_Clean!$D$2:$D$150,"VC/PE",Investments_Clean!$F$2:$F$150,"Accepted"))>0,1,0)) | BN39: =IF(BL39=0,"",IF((COUNTIFS(Investments_Clean!$A$2:$A$150,A39,Investments_Clean!$D$2:$D$150,"Angel",Investments_Clean!$F$2:$F$150,"Accepted"))>0,1,0)) | BO39: =IF(BL39=0,"",IF((COUNTIFS(Investments_Clean!$A$2:$A$150,A39,Investments_Clean!$D$2:$D$150,"Accelerator",Investments_Clean!$F$2:$F$150,"Accepted"))>0,1,0)) | BP39: =IF(BL39=0,"",IF((COUNTIFS(Investments_Clean!$A$2:$A$150,A39,Investments_Clean!$D$2:$D$150,"Corporate",Investments_Clean!$F$2:$F$150,"Accepted"))>0,1,0)) | BQ39: =IF(BL39=0,"",IF((COUNTIFS(Investments_Clean!$A$2:$A$150,A39,Investments_Clean!$D$2:$D$150,"Government",Investments_Clean!$F$2:$F$150,"Accepted"))>0,1,0)) | BR39: =IF(BL39=0,"",IF((COUNTIFS(Investments_Clean!$A$2:$A$150,A39,Investments_Clean!$D$2:$D$150,"Grant/Philanthropic",Investments_Clean!$F$2:$F$150,"Accepted")+COUNTIFS(Investments_Clean!$A$2:$A$150,A39,Investments_Clean!$D$2:$D$150,"DFI/Impact",Investments_Clean!$F$2:$F$150,"Accepted"))>0,1,0)) | CA39: 0 | CC39: =IF(I39="","",IFERROR(IF(INDEX(Macro_Lookup!$B$2:$B$31,MATCH(I39,Macro_Lookup!$A$2:$A$31,0))="","",INDEX(Macro_Lookup!$B$2:$B$31,MATCH(I39,Macro_Lookup!$A$2:$A$31,0))),"")) | CD39: =IF(I39="","",IFERROR(IF(INDEX(Macro_Lookup!$C$2:$C$31,MATCH(I39,Macro_Lookup!$A$2:$A$31,0))="","",INDEX(Macro_Lookup!$C$2:$C$31,MATCH(I39,Macro_Lookup!$A$2:$A$31,0))),"")) | CE39: =IF(BJ39="","",IFERROR(IF(INDEX(Macro_Lookup!$B$2:$B$31,MATCH(BJ39,Macro_Lookup!$A$2:$A$31,0))="","",INDEX(Macro_Lookup!$B$2:$B$31,MATCH(BJ39,Macro_Lookup!$A$2:$A$31,0))),"")) | CF39: =IF(BJ39="","",IFERROR(IF(INDEX(Macro_Lookup!$C$2:$C$31,MATCH(BJ39,Macro_Lookup!$A$2:$A$31,0))="","",INDEX(Macro_Lookup!$C$2:$C$31,MATCH(BJ39,Macro_Lookup!$A$2:$A$31,0))),"")) | CG39: 8 | CH39: Original 100 (BD-ST-001..100); see Version_Log v1 (2026-10-06) | CI39: 2026-10-06
A40: BD-ST-039 | B40: Thrive EdTech | C40: Bangladesh | D40: Dhaka | E40: 0 | F40: Independent startup | I40: 2019 | K40: year | L40: 46295 | M40: =IF(I40="","",(YEAR(L40)-I40)*12+MONTH(L40)-IF(J40="",1,J40)) -> 92 | N40: =IF(M40="","",ROUND(M40/12,2)) -> 7.67 | O40: EdTech | P40: EdTech | Q40: B2B2C EdTech SaaS | R40: 1 | S40: 1 | T40: 0 | U40: 1 | V40: 0 | W40: 0 | X40: Live/Scaling | Y40: 3 | Z40: 1 | AA40: 1 | AB40: NSU Startups Next | AF40: =IF(SUMIF(Founders_Clean!$A$2:$A$159,A40,Founders_Clean!$C$2:$C$159)=0,"",SUMIF(Founders_Clean!$A$2:$A$159,A40,Founders_Clean!$C$2:$C$159)) -> 1 | AG40: =IF(AF40="","",SUMIF(Founders_Clean!$A$2:$A$159,A40,Founders_Clean!$D$2:$D$159)) -> 1 | AH40: =IF(AF40="","",SUMIF(Founders_Clean!$A$2:$A$159,A40,Founders_Clean!$E$2:$E$159)) -> 0 | AI40: =IF(AF40="","",IF((AG40+AH40)=0,"",AH40/(AG40+AH40))) -> 0 | AJ40: =IF(AI40="","",IF(AH40>0,1,0)) -> 0 | AK40: =IF(AI40="","",ROUND(1-(AI40^2+(1-AI40)^2),3)) -> 0 | AX40: Active | AY40: High | BA40: 0 | BB40: 0 | BC40: 0 | BF40: =IF(OR(I40="",BC40=""),"",IF(BC40=1,(BD40-I40)*12+IF(BE40="",7,BE40)-IF(J40="",1,J40),M40)) -> 92 | BG40: 1 | BH40: 180000 | BI40: round | BJ40: 2021 | BK40: 1 | BL40: =COUNTIFS(Investments_Clean!$A$2:$A$150,A40,Investments_Clean!$F$2:$F$150,"Accepted") -> 1 | BM40: =IF(BL40=0,"",IF((COUNTIFS(Investments_Clean!$A$2:$A$150,A40,Investments_Clean!$D$2:$D$150,"VC/PE",Investments_Clean!$F$2:$F$150,"Accepted"))>0,1,0)) -> 0 | BN40: =IF(BL40=0,"",IF((COUNTIFS(Investments_Clean!$A$2:$A$150,A40,Investments_Clean!$D$2:$D$150,"Angel",Investments_Clean!$F$2:$F$150,"Accepted"))>0,1,0)) -> 0 | BO40: =IF(BL40=0,"",IF((COUNTIFS(Investments_Clean!$A$2:$A$150,A40,Investments_Clean!$D$2:$D$150,"Accelerator",Investments_Clean!$F$2:$F$150,"Accepted"))>0,1,0)) -> 0 | BP40: =IF(BL40=0,"",IF((COUNTIFS(Investments_Clean!$A$2:$A$150,A40,Investments_Clean!$D$2:$D$150,"Corporate",Investments_Clean!$F$2:$F$150,"Accepted"))>0,1,0)) -> 1 | BQ40: =IF(BL40=0,"",IF((COUNTIFS(Investments_Clean!$A$2:$A$150,A40,Investments_Clean!$D$2:$D$150,"Government",Investments_Clean!$F$2:$F$150,"Accepted"))>0,1,0)) -> 0 | BR40: =IF(BL40=0,"",IF((COUNTIFS(Investments_Clean!$A$2:$A$150,A40,Investments_Clean!$D$2:$D$150,"Grant/Philanthropic",Investments_Clean!$F$2:$F$150,"Accepted")+COUNTIFS(Investments_Clean!$A$2:$A$150,A40,Investments_Clean!$D$2:$D$150,"DFI/Impact",Investments_Clean!$F$2:$F$150,"Accepted"))>0,1,0)) -> 0 | CA40: 0 | CC40: =IF(I40="","",IFERROR(IF(INDEX(Macro_Lookup!$B$2:$B$31,MATCH(I40,Macro_Lookup!$A$2:$A$31,0))="","",INDEX(Macro_Lookup!$B$2:$B$31,MATCH(I40,Macro_Lookup!$A$2:$A$31,0))),"")) | CD40: =IF(I40="","",IFERROR(IF(INDEX(Macro_Lookup!$C$2:$C$31,MATCH(I40,Macro_Lookup!$A$2:$A$31,0))="","",INDEX(Macro_Lookup!$C$2:$C$31,MATCH(I40,Macro_Lookup!$A$2:$A$31,0))),"")) | CE40: =IF(BJ40="","",IFERROR(IF(INDEX(Macro_Lookup!$B$2:$B$31,MATCH(BJ40,Macro_Lookup!$A$2:$A$31,0))="","",INDEX(Macro_Lookup!$B$2:$B$31,MATCH(BJ40,Macro_Lookup!$A$2:$A$31,0))),"")) | CF40: =IF(BJ40="","",IFERROR(IF(INDEX(Macro_Lookup!$C$2:$C$31,MATCH(BJ40,Macro_Lookup!$A$2:$A$31,0))="","",INDEX(Macro_Lookup!$C$2:$C$31,MATCH(BJ40,Macro_Lookup!$A$2:$A$31,0))),"")) | CG40: 7 | CH40: Original 100 (BD-ST-001..100); see Version_Log v1 (2026-10-06) | CI40: 2026-10-06
A41: BD-ST-040 | B41: Durbin Academy | C41: Bangladesh | D41: Dhaka | E41: 0 | F41: Independent startup | K41: unknown | L41: 46295 | M41: =IF(I41="","",(YEAR(L41)-I41)*12+MONTH(L41)-IF(J41="",1,J41)) | N41: =IF(M41="","",ROUND(M41/12,2)) | O41: EdTech | P41: EdTech | Q41: B2C EdTech content platform | R41: 0 | S41: 1 | T41: 0 | U41: 0 | V41: 0 | W41: 0 | X41: Unclear | AF41: =IF(SUMIF(Founders_Clean!$A$2:$A$159,A41,Founders_Clean!$C$2:$C$159)=0,"",SUMIF(Founders_Clean!$A$2:$A$159,A41,Founders_Clean!$C$2:$C$159)) -> 1 | AG41: =IF(AF41="","",SUMIF(Founders_Clean!$A$2:$A$159,A41,Founders_Clean!$D$2:$D$159)) -> 1 | AH41: =IF(AF41="","",SUMIF(Founders_Clean!$A$2:$A$159,A41,Founders_Clean!$E$2:$E$159)) -> 0 | AI41: =IF(AF41="","",IF((AG41+AH41)=0,"",AH41/(AG41+AH41))) -> 0 | AJ41: =IF(AI41="","",IF(AH41>0,1,0)) -> 0 | AK41: =IF(AI41="","",ROUND(1-(AI41^2+(1-AI41)^2),3)) -> 0 | AX41: Unknown | AY41: Low | AZ41: Status unclear in source | BB41: 0 | BF41: =IF(OR(I41="",BC41=""),"",IF(BC41=1,(BD41-I41)*12+IF(BE41="",7,BE41)-IF(J41="",1,J41),M41)) | BL41: =COUNTIFS(Investments_Clean!$A$2:$A$150,A41,Investments_Clean!$F$2:$F$150,"Accepted") -> 0 | BM41: =IF(BL41=0,"",IF((COUNTIFS(Investments_Clean!$A$2:$A$150,A41,Investments_Clean!$D$2:$D$150,"VC/PE",Investments_Clean!$F$2:$F$150,"Accepted"))>0,1,0)) | BN41: =IF(BL41=0,"",IF((COUNTIFS(Investments_Clean!$A$2:$A$150,A41,Investments_Clean!$D$2:$D$150,"Angel",Investments_Clean!$F$2:$F$150,"Accepted"))>0,1,0)) | BO41: =IF(BL41=0,"",IF((COUNTIFS(Investments_Clean!$A$2:$A$150,A41,Investments_Clean!$D$2:$D$150,"Accelerator",Investments_Clean!$F$2:$F$150,"Accepted"))>0,1,0)) | BP41: =IF(BL41=0,"",IF((COUNTIFS(Investments_Clean!$A$2:$A$150,A41,Investments_Clean!$D$2:$D$150,"Corporate",Investments_Clean!$F$2:$F$150,"Accepted"))>0,1,0)) | BQ41: =IF(BL41=0,"",IF((COUNTIFS(Investments_Clean!$A$2:$A$150,A41,Investments_Clean!$D$2:$D$150,"Government",Investments_Clean!$F$2:$F$150,"Accepted"))>0,1,0)) | BR41: =IF(BL41=0,"",IF((COUNTIFS(Investments_Clean!$A$2:$A$150,A41,Investments_Clean!$D$2:$D$150,"Grant/Philanthropic",Investments_Clean!$F$2:$F$150,"Accepted")+COUNTIFS(Investments_Clean!$A$2:$A$150,A41,Investments_Clean!$D$2:$D$150,"DFI/Impact",Investments_Clean!$F$2:$F$150,"Accepted"))>0,1,0)) | CA41: 0 | CC41: =IF(I41="","",IFERROR(IF(INDEX(Macro_Lookup!$B$2:$B$31,MATCH(I41,Macro_Lookup!$A$2:$A$31,0))="","",INDEX(Macro_Lookup!$B$2:$B$31,MATCH(I41,Macro_Lookup!$A$2:$A$31,0))),"")) | CD41: =IF(I41="","",IFERROR(IF(INDEX(Macro_Lookup!$C$2:$C$31,MATCH(I41,Macro_Lookup!$A$2:$A$31,0))="","",INDEX(Macro_Lookup!$C$2:$C$31,MATCH(I41,Macro_Lookup!$A$2:$A$31,0))),"")) | CE41: =IF(BJ41="","",IFERROR(IF(INDEX(Macro_Lookup!$B$2:$B$31,MATCH(BJ41,Macro_Lookup!$A$2:$A$31,0))="","",INDEX(Macro_Lookup!$B$2:$B$31,MATCH(BJ41,Macro_Lookup!$A$2:$A$31,0))),"")) | CF41: =IF(BJ41="","",IFERROR(IF(INDEX(Macro_Lookup!$C$2:$C$31,MATCH(BJ41,Macro_Lookup!$A$2:$A$31,0))="","",INDEX(Macro_Lookup!$C$2:$C$31,MATCH(BJ41,Macro_Lookup!$A$2:$A$31,0))),"")) | CG41: 8 | CH41: Original 100 (BD-ST-001..100); see Version_Log v1 (2026-10-06) | CI41: 2026-10-06
A42: BD-ST-041 | B42: Upskill | C42: Bangladesh | D42: Dhaka | E42: 0 | F42: Independent startup | I42: 2018 | K42: year | L42: 46295 | M42: =IF(I42="","",(YEAR(L42)-I42)*12+MONTH(L42)-IF(J42="",1,J42)) -> 104 | N42: =IF(M42="","",ROUND(M42/12,2)) -> 8.67 | O42: EdTech | P42: EdTech | Q42: B2B / B2C | R42: 1 | S42: 1 | T42: 0 | U42: 0 | V42: 0 | W42: 0 | X42: Live and Scaling | Y42: 3 | Z42: 1 | AA42: 1 | AB42: GP Accelerator | AF42: =IF(SUMIF(Founders_Clean!$A$2:$A$159,A42,Founders_Clean!$C$2:$C$159)=0,"",SUMIF(Founders_Clean!$A$2:$A$159,A42,Founders_Clean!$C$2:$C$159)) -> 3 | AG42: =IF(AF42="","",SUMIF(Founders_Clean!$A$2:$A$159,A42,Founders_Clean!$D$2:$D$159)) -> 3 | AH42: =IF(AF42="","",SUMIF(Founders_Clean!$A$2:$A$159,A42,Founders_Clean!$E$2:$E$159)) -> 0 | AI42: =IF(AF42="","",IF((AG42+AH42)=0,"",AH42/(AG42+AH42))) -> 0 | AJ42: =IF(AI42="","",IF(AH42>0,1,0)) -> 0 | AK42: =IF(AI42="","",ROUND(1-(AI42^2+(1-AI42)^2),3)) -> 0 | AL42: 27.5 | AX42: Active | AY42: High | BA42: 0 | BB42: 0 | BC42: 0 | BF42: =IF(OR(I42="",BC42=""),"",IF(BC42=1,(BD42-I42)*12+IF(BE42="",7,BE42)-IF(J42="",1,J42),M42)) -> 104 | BG42: 1 | BH42: 200000 | BI42: cumulative | BJ42: 2021 | BK42: 1 | BL42: =COUNTIFS(Investments_Clean!$A$2:$A$150,A42,Investments_Clean!$F$2:$F$150,"Accepted") -> 3 | BM42: =IF(BL42=0,"",IF((COUNTIFS(Investments_Clean!$A$2:$A$150,A42,Investments_Clean!$D$2:$D$150,"VC/PE",Investments_Clean!$F$2:$F$150,"Accepted"))>0,1,0)) -> 0 | BN42: =IF(BL42=0,"",IF((COUNTIFS(Investments_Clean!$A$2:$A$150,A42,Investments_Clean!$D$2:$D$150,"Angel",Investments_Clean!$F$2:$F$150,"Accepted"))>0,1,0)) -> 1 | BO42: =IF(BL42=0,"",IF((COUNTIFS(Investments_Clean!$A$2:$A$150,A42,Investments_Clean!$D$2:$D$150,"Accelerator",Investments_Clean!$F$2:$F$150,"Accepted"))>0,1,0)) -> 1 | BP42: =IF(BL42=0,"",IF((COUNTIFS(Investments_Clean!$A$2:$A$150,A42,Investments_Clean!$D$2:$D$150,"Corporate",Investments_Clean!$F$2:$F$150,"Accepted"))>0,1,0)) -> 0 | BQ42: =IF(BL42=0,"",IF((COUNTIFS(Investments_Clean!$A$2:$A$150,A42,Investments_Clean!$D$2:$D$150,"Government",Investments_Clean!$F$2:$F$150,"Accepted"))>0,1,0)) -> 0 | BR42: =IF(BL42=0,"",IF((COUNTIFS(Investments_Clean!$A$2:$A$150,A42,Investments_Clean!$D$2:$D$150,"Grant/Philanthropic",Investments_Clean!$F$2:$F$150,"Accepted")+COUNTIFS(Investments_Clean!$A$2:$A$150,A42,Investments_Clean!$D$2:$D$150,"DFI/Impact",Investments_Clean!$F$2:$F$150,"Accepted"))>0,1,0)) -> 0 | CA42: 0 | CC42: =IF(I42="","",IFERROR(IF(INDEX(Macro_Lookup!$B$2:$B$31,MATCH(I42,Macro_Lookup!$A$2:$A$31,0))="","",INDEX(Macro_Lookup!$B$2:$B$31,MATCH(I42,Macro_Lookup!$A$2:$A$31,0))),"")) | CD42: =IF(I42="","",IFERROR(IF(INDEX(Macro_Lookup!$C$2:$C$31,MATCH(I42,Macro_Lookup!$A$2:$A$31,0))="","",INDEX(Macro_Lookup!$C$2:$C$31,MATCH(I42,Macro_Lookup!$A$2:$A$31,0))),"")) | CE42: =IF(BJ42="","",IFERROR(IF(INDEX(Macro_Lookup!$B$2:$B$31,MATCH(BJ42,Macro_Lookup!$A$2:$A$31,0))="","",INDEX(Macro_Lookup!$B$2:$B$31,MATCH(BJ42,Macro_Lookup!$A$2:$A$31,0))),"")) | CF42: =IF(BJ42="","",IFERROR(IF(INDEX(Macro_Lookup!$C$2:$C$31,MATCH(BJ42,Macro_Lookup!$A$2:$A$31,0))="","",INDEX(Macro_Lookup!$C$2:$C$31,MATCH(BJ42,Macro_Lookup!$A$2:$A$31,0))),"")) | CG42: 7 | CH42: Original 100 (BD-ST-001..100); see Version_Log v1 (2026-10-06) | CI42: 2026-10-06
A43: BD-ST-042 | B43: Interactive Cares | C43: Bangladesh | D43: Dhaka | E43: 0 | F43: Independent startup | I43: 2020 | K43: year | L43: 46295 | M43: =IF(I43="","",(YEAR(L43)-I43)*12+MONTH(L43)-IF(J43="",1,J43)) -> 80 | N43: =IF(M43="","",ROUND(M43/12,2)) -> 6.67 | O43: EdTech | P43: EdTech | Q43: B2C / SaaS | R43: 0 | S43: 1 | T43: 0 | U43: 1 | V43: 0 | W43: 0 | X43: Live and Scaling | Y43: 3 | Z43: 1 | AA43: 1 | AB43: Accelerating Asia, SuperCharger Ventures | AC43: 1 | AD43: 100000 | AE43: Investment_Decisions | AF43: =IF(SUMIF(Founders_Clean!$A$2:$A$159,A43,Founders_Clean!$C$2:$C$159)=0,"",SUMIF(Founders_Clean!$A$2:$A$159,A43,Founders_Clean!$C$2:$C$159)) -> 2 | AG43: =IF(AF43="","",SUMIF(Founders_Clean!$A$2:$A$159,A43,Founders_Clean!$D$2:$D$159)) -> 1 | AH43: =IF(AF43="","",SUMIF(Founders_Clean!$A$2:$A$159,A43,Founders_Clean!$E$2:$E$159)) -> 1 | AI43: =IF(AF43="","",IF((AG43+AH43)=0,"",AH43/(AG43+AH43))) -> 0.5 | AJ43: =IF(AI43="","",IF(AH43>0,1,0)) -> 1 | AK43: =IF(AI43="","",ROUND(1-(AI43^2+(1-AI43)^2),3)) -> 0.5 | AL43: 25 | AX43: Active | AY43: Low | AZ43: Founder/CEO detained April 2026 (embezzlement/money-laundering allegations); company status unclear | BA43: 0 | BB43: 0 | BC43: 0 | BF43: =IF(OR(I43="",BC43=""),"",IF(BC43=1,(BD43-I43)*12+IF(BE43="",7,BE43)-IF(J43="",1,J43),M43)) -> 80 | BG43: 1 | BH43: 450000 | BI43: cumulative | BJ43: 2024 | BK43: 1 | BL43: =COUNTIFS(Investments_Clean!$A$2:$A$150,A43,Investments_Clean!$F$2:$F$150,"Accepted") -> 6 | BM43: =IF(BL43=0,"",IF((COUNTIFS(Investments_Clean!$A$2:$A$150,A43,Investments_Clean!$D$2:$D$150,"VC/PE",Investments_Clean!$F$2:$F$150,"Accepted"))>0,1,0)) -> 1 | BN43: =IF(BL43=0,"",IF((COUNTIFS(Investments_Clean!$A$2:$A$150,A43,Investments_Clean!$D$2:$D$150,"Angel",Investments_Clean!$F$2:$F$150,"Accepted"))>0,1,0)) -> 1 | BO43: =IF(BL43=0,"",IF((COUNTIFS(Investments_Clean!$A$2:$A$150,A43,Investments_Clean!$D$2:$D$150,"Accelerator",Investments_Clean!$F$2:$F$150,"Accepted"))>0,1,0)) -> 1 | BP43: =IF(BL43=0,"",IF((COUNTIFS(Investments_Clean!$A$2:$A$150,A43,Investments_Clean!$D$2:$D$150,"Corporate",Investments_Clean!$F$2:$F$150,"Accepted"))>0,1,0)) -> 0 | BQ43: =IF(BL43=0,"",IF((COUNTIFS(Investments_Clean!$A$2:$A$150,A43,Investments_Clean!$D$2:$D$150,"Government",Investments_Clean!$F$2:$F$150,"Accepted"))>0,1,0)) -> 0 | BR43: =IF(BL43=0,"",IF((COUNTIFS(Investments_Clean!$A$2:$A$150,A43,Investments_Clean!$D$2:$D$150,"Grant/Philanthropic",Investments_Clean!$F$2:$F$150,"Accepted")+COUNTIFS(Investments_Clean!$A$2:$A$150,A43,Investments_Clean!$D$2:$D$150,"DFI/Impact",Investments_Clean!$F$2:$F$150,"Accepted"))>0,1,0)) -> 1 | CA43: 0 | CC43: =IF(I43="","",IFERROR(IF(INDEX(Macro_Lookup!$B$2:$B$31,MATCH(I43,Macro_Lookup!$A$2:$A$31,0))="","",INDEX(Macro_Lookup!$B$2:$B$31,MATCH(I43,Macro_Lookup!$A$2:$A$31,0))),"")) | CD43: =IF(I43="","",IFERROR(IF(INDEX(Macro_Lookup!$C$2:$C$31,MATCH(I43,Macro_Lookup!$A$2:$A$31,0))="","",INDEX(Macro_Lookup!$C$2:$C$31,MATCH(I43,Macro_Lookup!$A$2:$A$31,0))),"")) | CE43: =IF(BJ43="","",IFERROR(IF(INDEX(Macro_Lookup!$B$2:$B$31,MATCH(BJ43,Macro_Lookup!$A$2:$A$31,0))="","",INDEX(Macro_Lookup!$B$2:$B$31,MATCH(BJ43,Macro_Lookup!$A$2:$A$31,0))),"")) | CF43: =IF(BJ43="","",IFERROR(IF(INDEX(Macro_Lookup!$C$2:$C$31,MATCH(BJ43,Macro_Lookup!$A$2:$A$31,0))="","",INDEX(Macro_Lookup!$C$2:$C$31,MATCH(BJ43,Macro_Lookup!$A$2:$A$31,0))),"")) | CG43: 6 | CH43: Original 100 (BD-ST-001..100); see Version_Log v1 (2026-10-06) | CI43: 2026-10-06
A44: BD-ST-043 | B44: EduHive | C44: Bangladesh | D44: Dhaka | E44: 0 | F44: Independent startup | I44: 2019 | K44: year | L44: 46295 | M44: =IF(I44="","",(YEAR(L44)-I44)*12+MONTH(L44)-IF(J44="",1,J44)) -> 92 | N44: =IF(M44="","",ROUND(M44/12,2)) -> 7.67 | O44: EdTech | P44: EdTech | Q44: B2C / Marketplace | R44: 0 | S44: 1 | T44: 1 | U44: 0 | V44: 0 | W44: 0 | X44: Live and Scaling | Y44: 3 | Z44: 1 | AA44: 1 | AB44: GP Accelerator (Cohort 5) | AF44: =IF(SUMIF(Founders_Clean!$A$2:$A$159,A44,Founders_Clean!$C$2:$C$159)=0,"",SUMIF(Founders_Clean!$A$2:$A$159,A44,Founders_Clean!$C$2:$C$159)) -> 1 | AG44: =IF(AF44="","",SUMIF(Founders_Clean!$A$2:$A$159,A44,Founders_Clean!$D$2:$D$159)) -> 1 | AH44: =IF(AF44="","",SUMIF(Founders_Clean!$A$2:$A$159,A44,Founders_Clean!$E$2:$E$159)) -> 0 | AI44: =IF(AF44="","",IF((AG44+AH44)=0,"",AH44/(AG44+AH44))) -> 0 | AJ44: =IF(AI44="","",IF(AH44>0,1,0)) -> 0 | AK44: =IF(AI44="","",ROUND(1-(AI44^2+(1-AI44)^2),3)) -> 0 | AL44: 15 | AX44: Active | AY44: High | BA44: 0 | BB44: 0 | BC44: 0 | BF44: =IF(OR(I44="",BC44=""),"",IF(BC44=1,(BD44-I44)*12+IF(BE44="",7,BE44)-IF(J44="",1,J44),M44)) -> 92 | BG44: 1 | BI44: unknown | BJ44: 2021 | BK44: 1 | BL44: =COUNTIFS(Investments_Clean!$A$2:$A$150,A44,Investments_Clean!$F$2:$F$150,"Accepted") -> 1 | BM44: =IF(BL44=0,"",IF((COUNTIFS(Investments_Clean!$A$2:$A$150,A44,Investments_Clean!$D$2:$D$150,"VC/PE",Investments_Clean!$F$2:$F$150,"Accepted"))>0,1,0)) -> 0 | BN44: =IF(BL44=0,"",IF((COUNTIFS(Investments_Clean!$A$2:$A$150,A44,Investments_Clean!$D$2:$D$150,"Angel",Investments_Clean!$F$2:$F$150,"Accepted"))>0,1,0)) -> 0 | BO44: =IF(BL44=0,"",IF((COUNTIFS(Investments_Clean!$A$2:$A$150,A44,Investments_Clean!$D$2:$D$150,"Accelerator",Investments_Clean!$F$2:$F$150,"Accepted"))>0,1,0)) -> 0 | BP44: =IF(BL44=0,"",IF((COUNTIFS(Investments_Clean!$A$2:$A$150,A44,Investments_Clean!$D$2:$D$150,"Corporate",Investments_Clean!$F$2:$F$150,"Accepted"))>0,1,0)) -> 0 | BQ44: =IF(BL44=0,"",IF((COUNTIFS(Investments_Clean!$A$2:$A$150,A44,Investments_Clean!$D$2:$D$150,"Government",Investments_Clean!$F$2:$F$150,"Accepted"))>0,1,0)) -> 1 | BR44: =IF(BL44=0,"",IF((COUNTIFS(Investments_Clean!$A$2:$A$150,A44,Investments_Clean!$D$2:$D$150,"Grant/Philanthropic",Investments_Clean!$F$2:$F$150,"Accepted")+COUNTIFS(Investments_Clean!$A$2:$A$150,A44,Investments_Clean!$D$2:$D$150,"DFI/Impact",Investments_Clean!$F$2:$F$150,"Accepted"))>0,1,0)) -> 0 | CA44: 0 | CC44: =IF(I44="","",IFERROR(IF(INDEX(Macro_Lookup!$B$2:$B$31,MATCH(I44,Macro_Lookup!$A$2:$A$31,0))="","",INDEX(Macro_Lookup!$B$2:$B$31,MATCH(I44,Macro_Lookup!$A$2:$A$31,0))),"")) | CD44: =IF(I44="","",IFERROR(IF(INDEX(Macro_Lookup!$C$2:$C$31,MATCH(I44,Macro_Lookup!$A$2:$A$31,0))="","",INDEX(Macro_Lookup!$C$2:$C$31,MATCH(I44,Macro_Lookup!$A$2:$A$31,0))),"")) | CE44: =IF(BJ44="","",IFERROR(IF(INDEX(Macro_Lookup!$B$2:$B$31,MATCH(BJ44,Macro_Lookup!$A$2:$A$31,0))="","",INDEX(Macro_Lookup!$B$2:$B$31,MATCH(BJ44,Macro_Lookup!$A$2:$A$31,0))),"")) | CF44: =IF(BJ44="","",IFERROR(IF(INDEX(Macro_Lookup!$C$2:$C$31,MATCH(BJ44,Macro_Lookup!$A$2:$A$31,0))="","",INDEX(Macro_Lookup!$C$2:$C$31,MATCH(BJ44,Macro_Lookup!$A$2:$A$31,0))),"")) | CG44: 7 | CH44: Original 100 (BD-ST-001..100); see Version_Log v1 (2026-10-06) | CI44: 2026-10-06
A45: BD-ST-044 | B45: Programming Hero | C45: Bangladesh | D45: Dhaka | E45: 0 | F45: Independent startup | I45: 2019 | K45: year | L45: 46295 | M45: =IF(I45="","",(YEAR(L45)-I45)*12+MONTH(L45)-IF(J45="",1,J45)) -> 92 | N45: =IF(M45="","",ROUND(M45/12,2)) -> 7.67 | O45: EdTech | P45: EdTech | Q45: B2C / Subscription | R45: 0 | S45: 1 | T45: 0 | U45: 1 | V45: 0 | W45: 0 | X45: Live and Scaling | Y45: 3 | Z45: 1 | AF45: =IF(SUMIF(Founders_Clean!$A$2:$A$159,A45,Founders_Clean!$C$2:$C$159)=0,"",SUMIF(Founders_Clean!$A$2:$A$159,A45,Founders_Clean!$C$2:$C$159)) -> 1 | AG45: =IF(AF45="","",SUMIF(Founders_Clean!$A$2:$A$159,A45,Founders_Clean!$D$2:$D$159)) -> 1 | AH45: =IF(AF45="","",SUMIF(Founders_Clean!$A$2:$A$159,A45,Founders_Clean!$E$2:$E$159)) -> 0 | AI45: =IF(AF45="","",IF((AG45+AH45)=0,"",AH45/(AG45+AH45))) -> 0 | AJ45: =IF(AI45="","",IF(AH45>0,1,0)) -> 0 | AK45: =IF(AI45="","",ROUND(1-(AI45^2+(1-AI45)^2),3)) -> 0 | AL45: 17.5 | AM45: 2 | AN45: Master's/MBA/professional | AO45: 1 | AP45: 1 | AQ45: 0 | AX45: Active | AY45: High | BA45: 0 | BB45: 0 | BC45: 0 | BF45: =IF(OR(I45="",BC45=""),"",IF(BC45=1,(BD45-I45)*12+IF(BE45="",7,BE45)-IF(J45="",1,J45),M45)) -> 92 | BL45: =COUNTIFS(Investments_Clean!$A$2:$A$150,A45,Investments_Clean!$F$2:$F$150,"Accepted") -> 0 | BM45: =IF(BL45=0,"",IF((COUNTIFS(Investments_Clean!$A$2:$A$150,A45,Investments_Clean!$D$2:$D$150,"VC/PE",Investments_Clean!$F$2:$F$150,"Accepted"))>0,1,0)) | BN45: =IF(BL45=0,"",IF((COUNTIFS(Investments_Clean!$A$2:$A$150,A45,Investments_Clean!$D$2:$D$150,"Angel",Investments_Clean!$F$2:$F$150,"Accepted"))>0,1,0)) | BO45: =IF(BL45=0,"",IF((COUNTIFS(Investments_Clean!$A$2:$A$150,A45,Investments_Clean!$D$2:$D$150,"Accelerator",Investments_Clean!$F$2:$F$150,"Accepted"))>0,1,0)) | BP45: =IF(BL45=0,"",IF((COUNTIFS(Investments_Clean!$A$2:$A$150,A45,Investments_Clean!$D$2:$D$150,"Corporate",Investments_Clean!$F$2:$F$150,"Accepted"))>0,1,0)) | BQ45: =IF(BL45=0,"",IF((COUNTIFS(Investments_Clean!$A$2:$A$150,A45,Investments_Clean!$D$2:$D$150,"Government",Investments_Clean!$F$2:$F$150,"Accepted"))>0,1,0)) | BR45: =IF(BL45=0,"",IF((COUNTIFS(Investments_Clean!$A$2:$A$150,A45,Investments_Clean!$D$2:$D$150,"Grant/Philanthropic",Investments_Clean!$F$2:$F$150,"Accepted")+COUNTIFS(Investments_Clean!$A$2:$A$150,A45,Investments_Clean!$D$2:$D$150,"DFI/Impact",Investments_Clean!$F$2:$F$150,"Accepted"))>0,1,0)) | CA45: 0 | CC45: =IF(I45="","",IFERROR(IF(INDEX(Macro_Lookup!$B$2:$B$31,MATCH(I45,Macro_Lookup!$A$2:$A$31,0))="","",INDEX(Macro_Lookup!$B$2:$B$31,MATCH(I45,Macro_Lookup!$A$2:$A$31,0))),"")) | CD45: =IF(I45="","",IFERROR(IF(INDEX(Macro_Lookup!$C$2:$C$31,MATCH(I45,Macro_Lookup!$A$2:$A$31,0))="","",INDEX(Macro_Lookup!$C$2:$C$31,MATCH(I45,Macro_Lookup!$A$2:$A$31,0))),"")) | CE45: =IF(BJ45="","",IFERROR(IF(INDEX(Macro_Lookup!$B$2:$B$31,MATCH(BJ45,Macro_Lookup!$A$2:$A$31,0))="","",INDEX(Macro_Lookup!$B$2:$B$31,MATCH(BJ45,Macro_Lookup!$A$2:$A$31,0))),"")) | CF45: =IF(BJ45="","",IFERROR(IF(INDEX(Macro_Lookup!$C$2:$C$31,MATCH(BJ45,Macro_Lookup!$A$2:$A$31,0))="","",INDEX(Macro_Lookup!$C$2:$C$31,MATCH(BJ45,Macro_Lookup!$A$2:$A$31,0))),"")) | CG45: 5 | CH45: Original 100 (BD-ST-001..100); see Version_Log v1 (2026-10-06) | CI45: 2026-10-06
A46: BD-ST-045 | B46: Sohopathi | C46: Bangladesh | D46: Dhaka | E46: 0 | F46: Independent startup | I46: 2018 | K46: year | L46: 46295 | M46: =IF(I46="","",(YEAR(L46)-I46)*12+MONTH(L46)-IF(J46="",1,J46)) -> 104 | N46: =IF(M46="","",ROUND(M46/12,2)) -> 8.67 | O46: EdTech | P46: EdTech | Q46: B2C / P2P | R46: 0 | S46: 1 | T46: 0 | U46: 0 | V46: 0 | W46: 0 | X46: Live and Scaling | Y46: 3 | Z46: 1 | AA46: 1 | AB46: GP Accelerator (Cohort 6), Student to Start-up | AC46: 1 | AE46: master (amount undisclosed) | AF46: =IF(SUMIF(Founders_Clean!$A$2:$A$159,A46,Founders_Clean!$C$2:$C$159)=0,"",SUMIF(Founders_Clean!$A$2:$A$159,A46,Founders_Clean!$C$2:$C$159)) -> 1 | AG46: =IF(AF46="","",SUMIF(Founders_Clean!$A$2:$A$159,A46,Founders_Clean!$D$2:$D$159)) -> 1 | AH46: =IF(AF46="","",SUMIF(Founders_Clean!$A$2:$A$159,A46,Founders_Clean!$E$2:$E$159)) -> 0 | AI46: =IF(AF46="","",IF((AG46+AH46)=0,"",AH46/(AG46+AH46))) -> 0 | AJ46: =IF(AI46="","",IF(AH46>0,1,0)) -> 0 | AK46: =IF(AI46="","",ROUND(1-(AI46^2+(1-AI46)^2),3)) -> 0 | AL46: 15 | AM46: 1 | AN46: Bachelor's | AO46: 1 | AP46: 1 | AQ46: 0 | AX46: Active | AY46: High | BA46: 0 | BB46: 0 | BC46: 0 | BF46: =IF(OR(I46="",BC46=""),"",IF(BC46=1,(BD46-I46)*12+IF(BE46="",7,BE46)-IF(J46="",1,J46),M46)) -> 104 | BG46: 1 | BI46: unknown | BJ46: 2020 | BK46: 1 | BL46: =COUNTIFS(Investments_Clean!$A$2:$A$150,A46,Investments_Clean!$F$2:$F$150,"Accepted") -> 3 | BM46: =IF(BL46=0,"",IF((COUNTIFS(Investments_Clean!$A$2:$A$150,A46,Investments_Clean!$D$2:$D$150,"VC/PE",Investments_Clean!$F$2:$F$150,"Accepted"))>0,1,0)) -> 0 | BN46: =IF(BL46=0,"",IF((COUNTIFS(Investments_Clean!$A$2:$A$150,A46,Investments_Clean!$D$2:$D$150,"Angel",Investments_Clean!$F$2:$F$150,"Accepted"))>0,1,0)) -> 0 | BO46: =IF(BL46=0,"",IF((COUNTIFS(Investments_Clean!$A$2:$A$150,A46,Investments_Clean!$D$2:$D$150,"Accelerator",Investments_Clean!$F$2:$F$150,"Accepted"))>0,1,0)) -> 1 | BP46: =IF(BL46=0,"",IF((COUNTIFS(Investments_Clean!$A$2:$A$150,A46,Investments_Clean!$D$2:$D$150,"Corporate",Investments_Clean!$F$2:$F$150,"Accepted"))>0,1,0)) -> 0 | BQ46: =IF(BL46=0,"",IF((COUNTIFS(Investments_Clean!$A$2:$A$150,A46,Investments_Clean!$D$2:$D$150,"Government",Investments_Clean!$F$2:$F$150,"Accepted"))>0,1,0)) -> 1 | BR46: =IF(BL46=0,"",IF((COUNTIFS(Investments_Clean!$A$2:$A$150,A46,Investments_Clean!$D$2:$D$150,"Grant/Philanthropic",Investments_Clean!$F$2:$F$150,"Accepted")+COUNTIFS(Investments_Clean!$A$2:$A$150,A46,Investments_Clean!$D$2:$D$150,"DFI/Impact",Investments_Clean!$F$2:$F$150,"Accepted"))>0,1,0)) -> 1 | CA46: 0 | CC46: =IF(I46="","",IFERROR(IF(INDEX(Macro_Lookup!$B$2:$B$31,MATCH(I46,Macro_Lookup!$A$2:$A$31,0))="","",INDEX(Macro_Lookup!$B$2:$B$31,MATCH(I46,Macro_Lookup!$A$2:$A$31,0))),"")) | CD46: =IF(I46="","",IFERROR(IF(INDEX(Macro_Lookup!$C$2:$C$31,MATCH(I46,Macro_Lookup!$A$2:$A$31,0))="","",INDEX(Macro_Lookup!$C$2:$C$31,MATCH(I46,Macro_Lookup!$A$2:$A$31,0))),"")) | CE46: =IF(BJ46="","",IFERROR(IF(INDEX(Macro_Lookup!$B$2:$B$31,MATCH(BJ46,Macro_Lookup!$A$2:$A$31,0))="","",INDEX(Macro_Lookup!$B$2:$B$31,MATCH(BJ46,Macro_Lookup!$A$2:$A$31,0))),"")) | CF46: =IF(BJ46="","",IFERROR(IF(INDEX(Macro_Lookup!$C$2:$C$31,MATCH(BJ46,Macro_Lookup!$A$2:$A$31,0))="","",INDEX(Macro_Lookup!$C$2:$C$31,MATCH(BJ46,Macro_Lookup!$A$2:$A$31,0))),"")) | CG46: 3 | CH46: Original 100 (BD-ST-001..100); see Version_Log v1 (2026-10-06) | CI46: 2026-10-06
A47: BD-ST-046 | B47: eShikhon | C47: Bangladesh | D47: Dhaka | E47: 0 | F47: Independent startup | I47: 2014 | K47: year | L47: 46295 | M47: =IF(I47="","",(YEAR(L47)-I47)*12+MONTH(L47)-IF(J47="",1,J47)) -> 152 | N47: =IF(M47="","",ROUND(M47/12,2)) -> 12.67 | O47: EdTech | P47: EdTech | Q47: B2C | R47: 0 | S47: 1 | T47: 0 | U47: 0 | V47: 0 | W47: 0 | X47: Live and Scaling | Y47: 3 | Z47: 1 | AF47: =IF(SUMIF(Founders_Clean!$A$2:$A$159,A47,Founders_Clean!$C$2:$C$159)=0,"",SUMIF(Founders_Clean!$A$2:$A$159,A47,Founders_Clean!$C$2:$C$159)) -> 1 | AG47: =IF(AF47="","",SUMIF(Founders_Clean!$A$2:$A$159,A47,Founders_Clean!$D$2:$D$159)) -> 1 | AH47: =IF(AF47="","",SUMIF(Founders_Clean!$A$2:$A$159,A47,Founders_Clean!$E$2:$E$159)) -> 0 | AI47: =IF(AF47="","",IF((AG47+AH47)=0,"",AH47/(AG47+AH47))) -> 0 | AJ47: =IF(AI47="","",IF(AH47>0,1,0)) -> 0 | AK47: =IF(AI47="","",ROUND(1-(AI47^2+(1-AI47)^2),3)) -> 0 | AL47: 12.5 | AX47: Active | AY47: High | BA47: 0 | BB47: 0 | BC47: 0 | BF47: =IF(OR(I47="",BC47=""),"",IF(BC47=1,(BD47-I47)*12+IF(BE47="",7,BE47)-IF(J47="",1,J47),M47)) -> 152 | BL47: =COUNTIFS(Investments_Clean!$A$2:$A$150,A47,Investments_Clean!$F$2:$F$150,"Accepted") -> 0 | BM47: =IF(BL47=0,"",IF((COUNTIFS(Investments_Clean!$A$2:$A$150,A47,Investments_Clean!$D$2:$D$150,"VC/PE",Investments_Clean!$F$2:$F$150,"Accepted"))>0,1,0)) | BN47: =IF(BL47=0,"",IF((COUNTIFS(Investments_Clean!$A$2:$A$150,A47,Investments_Clean!$D$2:$D$150,"Angel",Investments_Clean!$F$2:$F$150,"Accepted"))>0,1,0)) | BO47: =IF(BL47=0,"",IF((COUNTIFS(Investments_Clean!$A$2:$A$150,A47,Investments_Clean!$D$2:$D$150,"Accelerator",Investments_Clean!$F$2:$F$150,"Accepted"))>0,1,0)) | BP47: =IF(BL47=0,"",IF((COUNTIFS(Investments_Clean!$A$2:$A$150,A47,Investments_Clean!$D$2:$D$150,"Corporate",Investments_Clean!$F$2:$F$150,"Accepted"))>0,1,0)) | BQ47: =IF(BL47=0,"",IF((COUNTIFS(Investments_Clean!$A$2:$A$150,A47,Investments_Clean!$D$2:$D$150,"Government",Investments_Clean!$F$2:$F$150,"Accepted"))>0,1,0)) | BR47: =IF(BL47=0,"",IF((COUNTIFS(Investments_Clean!$A$2:$A$150,A47,Investments_Clean!$D$2:$D$150,"Grant/Philanthropic",Investments_Clean!$F$2:$F$150,"Accepted")+COUNTIFS(Investments_Clean!$A$2:$A$150,A47,Investments_Clean!$D$2:$D$150,"DFI/Impact",Investments_Clean!$F$2:$F$150,"Accepted"))>0,1,0)) | BV47: 65000 | CA47: 1 | CC47: =IF(I47="","",IFERROR(IF(INDEX(Macro_Lookup!$B$2:$B$31,MATCH(I47,Macro_Lookup!$A$2:$A$31,0))="","",INDEX(Macro_Lookup!$B$2:$B$31,MATCH(I47,Macro_Lookup!$A$2:$A$31,0))),"")) | CD47: =IF(I47="","",IFERROR(IF(INDEX(Macro_Lookup!$C$2:$C$31,MATCH(I47,Macro_Lookup!$A$2:$A$31,0))="","",INDEX(Macro_Lookup!$C$2:$C$31,MATCH(I47,Macro_Lookup!$A$2:$A$31,0))),"")) | CE47: =IF(BJ47="","",IFERROR(IF(INDEX(Macro_Lookup!$B$2:$B$31,MATCH(BJ47,Macro_Lookup!$A$2:$A$31,0))="","",INDEX(Macro_Lookup!$B$2:$B$31,MATCH(BJ47,Macro_Lookup!$A$2:$A$31,0))),"")) | CF47: =IF(BJ47="","",IFERROR(IF(INDEX(Macro_Lookup!$C$2:$C$31,MATCH(BJ47,Macro_Lookup!$A$2:$A$31,0))="","",INDEX(Macro_Lookup!$C$2:$C$31,MATCH(BJ47,Macro_Lookup!$A$2:$A$31,0))),"")) | CG47: 8 | CH47: Original 100 (BD-ST-001..100); see Version_Log v1 (2026-10-06) | CI47: 2026-10-06
A48: BD-ST-047 | B48: Repto | C48: Bangladesh | D48: Dhaka | E48: 0 | F48: Independent startup | I48: 2015 | K48: year | L48: 46295 | M48: =IF(I48="","",(YEAR(L48)-I48)*12+MONTH(L48)-IF(J48="",1,J48)) -> 140 | N48: =IF(M48="","",ROUND(M48/12,2)) -> 11.67 | O48: EdTech | P48: EdTech | Q48: Marketplace / B2C | R48: 0 | S48: 1 | T48: 1 | U48: 0 | V48: 0 | W48: 0 | X48: Live and Scaling | Y48: 3 | Z48: 1 | AA48: 1 | AB48: GP Accelerator (Cohort 1) | AF48: =IF(SUMIF(Founders_Clean!$A$2:$A$159,A48,Founders_Clean!$C$2:$C$159)=0,"",SUMIF(Founders_Clean!$A$2:$A$159,A48,Founders_Clean!$C$2:$C$159)) -> 1 | AG48: =IF(AF48="","",SUMIF(Founders_Clean!$A$2:$A$159,A48,Founders_Clean!$D$2:$D$159)) -> 1 | AH48: =IF(AF48="","",SUMIF(Founders_Clean!$A$2:$A$159,A48,Founders_Clean!$E$2:$E$159)) -> 0 | AI48: =IF(AF48="","",IF((AG48+AH48)=0,"",AH48/(AG48+AH48))) -> 0 | AJ48: =IF(AI48="","",IF(AH48>0,1,0)) -> 0 | AK48: =IF(AI48="","",ROUND(1-(AI48^2+(1-AI48)^2),3)) -> 0 | AL48: 12.5 | AM48: 0 | AN48: Below bachelor | AO48: 1 | AP48: 1 | AQ48: 0 | AX48: Active | AY48: High | BA48: 0 | BB48: 0 | BC48: 0 | BF48: =IF(OR(I48="",BC48=""),"",IF(BC48=1,(BD48-I48)*12+IF(BE48="",7,BE48)-IF(J48="",1,J48),M48)) -> 140 | BK48: 1 | BL48: =COUNTIFS(Investments_Clean!$A$2:$A$150,A48,Investments_Clean!$F$2:$F$150,"Accepted") -> 1 | BM48: =IF(BL48=0,"",IF((COUNTIFS(Investments_Clean!$A$2:$A$150,A48,Investments_Clean!$D$2:$D$150,"VC/PE",Investments_Clean!$F$2:$F$150,"Accepted"))>0,1,0)) -> 0 | BN48: =IF(BL48=0,"",IF((COUNTIFS(Investments_Clean!$A$2:$A$150,A48,Investments_Clean!$D$2:$D$150,"Angel",Investments_Clean!$F$2:$F$150,"Accepted"))>0,1,0)) -> 0 | BO48: =IF(BL48=0,"",IF((COUNTIFS(Investments_Clean!$A$2:$A$150,A48,Investments_Clean!$D$2:$D$150,"Accelerator",Investments_Clean!$F$2:$F$150,"Accepted"))>0,1,0)) -> 1 | BP48: =IF(BL48=0,"",IF((COUNTIFS(Investments_Clean!$A$2:$A$150,A48,Investments_Clean!$D$2:$D$150,"Corporate",Investments_Clean!$F$2:$F$150,"Accepted"))>0,1,0)) -> 0 | BQ48: =IF(BL48=0,"",IF((COUNTIFS(Investments_Clean!$A$2:$A$150,A48,Investments_Clean!$D$2:$D$150,"Government",Investments_Clean!$F$2:$F$150,"Accepted"))>0,1,0)) -> 0 | BR48: =IF(BL48=0,"",IF((COUNTIFS(Investments_Clean!$A$2:$A$150,A48,Investments_Clean!$D$2:$D$150,"Grant/Philanthropic",Investments_Clean!$F$2:$F$150,"Accepted")+COUNTIFS(Investments_Clean!$A$2:$A$150,A48,Investments_Clean!$D$2:$D$150,"DFI/Impact",Investments_Clean!$F$2:$F$150,"Accepted"))>0,1,0)) -> 0 | CA48: 0 | CC48: =IF(I48="","",IFERROR(IF(INDEX(Macro_Lookup!$B$2:$B$31,MATCH(I48,Macro_Lookup!$A$2:$A$31,0))="","",INDEX(Macro_Lookup!$B$2:$B$31,MATCH(I48,Macro_Lookup!$A$2:$A$31,0))),"")) | CD48: =IF(I48="","",IFERROR(IF(INDEX(Macro_Lookup!$C$2:$C$31,MATCH(I48,Macro_Lookup!$A$2:$A$31,0))="","",INDEX(Macro_Lookup!$C$2:$C$31,MATCH(I48,Macro_Lookup!$A$2:$A$31,0))),"")) | CE48: =IF(BJ48="","",IFERROR(IF(INDEX(Macro_Lookup!$B$2:$B$31,MATCH(BJ48,Macro_Lookup!$A$2:$A$31,0))="","",INDEX(Macro_Lookup!$B$2:$B$31,MATCH(BJ48,Macro_Lookup!$A$2:$A$31,0))),"")) | CF48: =IF(BJ48="","",IFERROR(IF(INDEX(Macro_Lookup!$C$2:$C$31,MATCH(BJ48,Macro_Lookup!$A$2:$A$31,0))="","",INDEX(Macro_Lookup!$C$2:$C$31,MATCH(BJ48,Macro_Lookup!$A$2:$A$31,0))),"")) | CG48: 4 | CH48: Original 100 (BD-ST-001..100); see Version_Log v1 (2026-10-06) | CI48: 2026-10-06
A49: BD-ST-048 | B49: Ostad | C49: Bangladesh | D49: Dhaka | E49: 0 | F49: Independent startup | I49: 2020 | K49: year | L49: 46295 | M49: =IF(I49="","",(YEAR(L49)-I49)*12+MONTH(L49)-IF(J49="",1,J49)) -> 80 | N49: =IF(M49="","",ROUND(M49/12,2)) -> 6.67 | O49: EdTech | P49: EdTech | Q49: B2C / Live Learning | R49: 0 | S49: 1 | T49: 0 | U49: 0 | V49: 0 | W49: 0 | X49: Live and Scaling | Y49: 3 | Z49: 1 | AA49: 1 | AB49: Accelerating Asia (Cohort 6) | AF49: =IF(SUMIF(Founders_Clean!$A$2:$A$159,A49,Founders_Clean!$C$2:$C$159)=0,"",SUMIF(Founders_Clean!$A$2:$A$159,A49,Founders_Clean!$C$2:$C$159)) -> 3 | AG49: =IF(AF49="","",SUMIF(Founders_Clean!$A$2:$A$159,A49,Founders_Clean!$D$2:$D$159)) -> 3 | AH49: =IF(AF49="","",SUMIF(Founders_Clean!$A$2:$A$159,A49,Founders_Clean!$E$2:$E$159)) -> 0 | AI49: =IF(AF49="","",IF((AG49+AH49)=0,"",AH49/(AG49+AH49))) -> 0 | AJ49: =IF(AI49="","",IF(AH49>0,1,0)) -> 0 | AK49: =IF(AI49="","",ROUND(1-(AI49^2+(1-AI49)^2),3)) -> 0 | AL49: 17.5 | AM49: 1 | AN49: Bachelor's | AO49: 1 | AP49: 1 | AQ49: 0 | AX49: Active | AY49: High | BA49: 0 | BB49: 0 | BC49: 0 | BF49: =IF(OR(I49="",BC49=""),"",IF(BC49=1,(BD49-I49)*12+IF(BE49="",7,BE49)-IF(J49="",1,J49),M49)) -> 80 | BG49: 1 | BH49: 170000 | BI49: round | BJ49: 2022 | BK49: 1 | BL49: =COUNTIFS(Investments_Clean!$A$2:$A$150,A49,Investments_Clean!$F$2:$F$150,"Accepted") -> 3 | BM49: =IF(BL49=0,"",IF((COUNTIFS(Investments_Clean!$A$2:$A$150,A49,Investments_Clean!$D$2:$D$150,"VC/PE",Investments_Clean!$F$2:$F$150,"Accepted"))>0,1,0)) -> 1 | BN49: =IF(BL49=0,"",IF((COUNTIFS(Investments_Clean!$A$2:$A$150,A49,Investments_Clean!$D$2:$D$150,"Angel",Investments_Clean!$F$2:$F$150,"Accepted"))>0,1,0)) -> 0 | BO49: =IF(BL49=0,"",IF((COUNTIFS(Investments_Clean!$A$2:$A$150,A49,Investments_Clean!$D$2:$D$150,"Accelerator",Investments_Clean!$F$2:$F$150,"Accepted"))>0,1,0)) -> 1 | BP49: =IF(BL49=0,"",IF((COUNTIFS(Investments_Clean!$A$2:$A$150,A49,Investments_Clean!$D$2:$D$150,"Corporate",Investments_Clean!$F$2:$F$150,"Accepted"))>0,1,0)) -> 0 | BQ49: =IF(BL49=0,"",IF((COUNTIFS(Investments_Clean!$A$2:$A$150,A49,Investments_Clean!$D$2:$D$150,"Government",Investments_Clean!$F$2:$F$150,"Accepted"))>0,1,0)) -> 0 | BR49: =IF(BL49=0,"",IF((COUNTIFS(Investments_Clean!$A$2:$A$150,A49,Investments_Clean!$D$2:$D$150,"Grant/Philanthropic",Investments_Clean!$F$2:$F$150,"Accepted")+COUNTIFS(Investments_Clean!$A$2:$A$150,A49,Investments_Clean!$D$2:$D$150,"DFI/Impact",Investments_Clean!$F$2:$F$150,"Accepted"))>0,1,0)) -> 0 | CA49: 0 | CC49: =IF(I49="","",IFERROR(IF(INDEX(Macro_Lookup!$B$2:$B$31,MATCH(I49,Macro_Lookup!$A$2:$A$31,0))="","",INDEX(Macro_Lookup!$B$2:$B$31,MATCH(I49,Macro_Lookup!$A$2:$A$31,0))),"")) | CD49: =IF(I49="","",IFERROR(IF(INDEX(Macro_Lookup!$C$2:$C$31,MATCH(I49,Macro_Lookup!$A$2:$A$31,0))="","",INDEX(Macro_Lookup!$C$2:$C$31,MATCH(I49,Macro_Lookup!$A$2:$A$31,0))),"")) | CE49: =IF(BJ49="","",IFERROR(IF(INDEX(Macro_Lookup!$B$2:$B$31,MATCH(BJ49,Macro_Lookup!$A$2:$A$31,0))="","",INDEX(Macro_Lookup!$B$2:$B$31,MATCH(BJ49,Macro_Lookup!$A$2:$A$31,0))),"")) | CF49: =IF(BJ49="","",IFERROR(IF(INDEX(Macro_Lookup!$C$2:$C$31,MATCH(BJ49,Macro_Lookup!$A$2:$A$31,0))="","",INDEX(Macro_Lookup!$C$2:$C$31,MATCH(BJ49,Macro_Lookup!$A$2:$A$31,0))),"")) | CG49: 4 | CH49: Original 100 (BD-ST-001..100); see Version_Log v1 (2026-10-06) | CI49: 2026-10-06
A50: BD-ST-049 | B50: Onnorokom Pathshala | C50: Bangladesh | D50: Dhaka | E50: 0 | F50: Independent startup | I50: 2012 | K50: year | L50: 46295 | M50: =IF(I50="","",(YEAR(L50)-I50)*12+MONTH(L50)-IF(J50="",1,J50)) -> 176 | N50: =IF(M50="","",ROUND(M50/12,2)) -> 14.67 | O50: EdTech | P50: EdTech | Q50: Non-profit / B2C (Freemium & Social Enterprise) | R50: 0 | S50: 1 | T50: 0 | U50: 0 | V50: 0 | W50: 0 | X50: Live and Scaling | Y50: 3 | Z50: 1 | AF50: =IF(SUMIF(Founders_Clean!$A$2:$A$159,A50,Founders_Clean!$C$2:$C$159)=0,"",SUMIF(Founders_Clean!$A$2:$A$159,A50,Founders_Clean!$C$2:$C$159)) -> 1 | AG50: =IF(AF50="","",SUMIF(Founders_Clean!$A$2:$A$159,A50,Founders_Clean!$D$2:$D$159)) -> 1 | AH50: =IF(AF50="","",SUMIF(Founders_Clean!$A$2:$A$159,A50,Founders_Clean!$E$2:$E$159)) -> 0 | AI50: =IF(AF50="","",IF((AG50+AH50)=0,"",AH50/(AG50+AH50))) -> 0 | AJ50: =IF(AI50="","",IF(AH50>0,1,0)) -> 0 | AK50: =IF(AI50="","",ROUND(1-(AI50^2+(1-AI50)^2),3)) -> 0 | AL50: 15 | AQ50: 1 | AX50: Active | AY50: High | BA50: 0 | BB50: 0 | BC50: 0 | BF50: =IF(OR(I50="",BC50=""),"",IF(BC50=1,(BD50-I50)*12+IF(BE50="",7,BE50)-IF(J50="",1,J50),M50)) -> 176 | BL50: =COUNTIFS(Investments_Clean!$A$2:$A$150,A50,Investments_Clean!$F$2:$F$150,"Accepted") -> 0 | BM50: =IF(BL50=0,"",IF((COUNTIFS(Investments_Clean!$A$2:$A$150,A50,Investments_Clean!$D$2:$D$150,"VC/PE",Investments_Clean!$F$2:$F$150,"Accepted"))>0,1,0)) | BN50: =IF(BL50=0,"",IF((COUNTIFS(Investments_Clean!$A$2:$A$150,A50,Investments_Clean!$D$2:$D$150,"Angel",Investments_Clean!$F$2:$F$150,"Accepted"))>0,1,0)) | BO50: =IF(BL50=0,"",IF((COUNTIFS(Investments_Clean!$A$2:$A$150,A50,Investments_Clean!$D$2:$D$150,"Accelerator",Investments_Clean!$F$2:$F$150,"Accepted"))>0,1,0)) | BP50: =IF(BL50=0,"",IF((COUNTIFS(Investments_Clean!$A$2:$A$150,A50,Investments_Clean!$D$2:$D$150,"Corporate",Investments_Clean!$F$2:$F$150,"Accepted"))>0,1,0)) | BQ50: =IF(BL50=0,"",IF((COUNTIFS(Investments_Clean!$A$2:$A$150,A50,Investments_Clean!$D$2:$D$150,"Government",Investments_Clean!$F$2:$F$150,"Accepted"))>0,1,0)) | BR50: =IF(BL50=0,"",IF((COUNTIFS(Investments_Clean!$A$2:$A$150,A50,Investments_Clean!$D$2:$D$150,"Grant/Philanthropic",Investments_Clean!$F$2:$F$150,"Accepted")+COUNTIFS(Investments_Clean!$A$2:$A$150,A50,Investments_Clean!$D$2:$D$150,"DFI/Impact",Investments_Clean!$F$2:$F$150,"Accepted"))>0,1,0)) | CA50: 0 | CC50: =IF(I50="","",IFERROR(IF(INDEX(Macro_Lookup!$B$2:$B$31,MATCH(I50,Macro_Lookup!$A$2:$A$31,0))="","",INDEX(Macro_Lookup!$B$2:$B$31,MATCH(I50,Macro_Lookup!$A$2:$A$31,0))),"")) | CD50: =IF(I50="","",IFERROR(IF(INDEX(Macro_Lookup!$C$2:$C$31,MATCH(I50,Macro_Lookup!$A$2:$A$31,0))="","",INDEX(Macro_Lookup!$C$2:$C$31,MATCH(I50,Macro_Lookup!$A$2:$A$31,0))),"")) | CE50: =IF(BJ50="","",IFERROR(IF(INDEX(Macro_Lookup!$B$2:$B$31,MATCH(BJ50,Macro_Lookup!$A$2:$A$31,0))="","",INDEX(Macro_Lookup!$B$2:$B$31,MATCH(BJ50,Macro_Lookup!$A$2:$A$31,0))),"")) | CF50: =IF(BJ50="","",IFERROR(IF(INDEX(Macro_Lookup!$C$2:$C$31,MATCH(BJ50,Macro_Lookup!$A$2:$A$31,0))="","",INDEX(Macro_Lookup!$C$2:$C$31,MATCH(BJ50,Macro_Lookup!$A$2:$A$31,0))),"")) | CG50: 7 | CH50: Original 100 (BD-ST-001..100); see Version_Log v1 (2026-10-06) | CI50: 2026-10-06
A51: BD-ST-050 | B51: Bissoy | C51: Bangladesh | D51: Dhaka | E51: 0 | F51: Independent startup | I51: 2014 | K51: year | L51: 46295 | M51: =IF(I51="","",(YEAR(L51)-I51)*12+MONTH(L51)-IF(J51="",1,J51)) -> 152 | N51: =IF(M51="","",ROUND(M51/12,2)) -> 12.67 | O51: EdTech / Q&A Platform | P51: EdTech | Q51: Q&A Platform / Ad-supported / B2C | R51: 0 | S51: 1 | T51: 0 | U51: 0 | V51: 0 | W51: 0 | X51: Live and Scaling | Y51: 3 | Z51: 1 | AF51: =IF(SUMIF(Founders_Clean!$A$2:$A$159,A51,Founders_Clean!$C$2:$C$159)=0,"",SUMIF(Founders_Clean!$A$2:$A$159,A51,Founders_Clean!$C$2:$C$159)) | AG51: =IF(AF51="","",SUMIF(Founders_Clean!$A$2:$A$159,A51,Founders_Clean!$D$2:$D$159)) | AH51: =IF(AF51="","",SUMIF(Founders_Clean!$A$2:$A$159,A51,Founders_Clean!$E$2:$E$159)) | AI51: =IF(AF51="","",IF((AG51+AH51)=0,"",AH51/(AG51+AH51))) | AJ51: =IF(AI51="","",IF(AH51>0,1,0)) | AK51: =IF(AI51="","",ROUND(1-(AI51^2+(1-AI51)^2),3)) | AL51: 10 | AX51: Active | AY51: High | BA51: 0 | BB51: 0 | BC51: 0 | BF51: =IF(OR(I51="",BC51=""),"",IF(BC51=1,(BD51-I51)*12+IF(BE51="",7,BE51)-IF(J51="",1,J51),M51)) -> 152 | BL51: =COUNTIFS(Investments_Clean!$A$2:$A$150,A51,Investments_Clean!$F$2:$F$150,"Accepted") -> 0 | BM51: =IF(BL51=0,"",IF((COUNTIFS(Investments_Clean!$A$2:$A$150,A51,Investments_Clean!$D$2:$D$150,"VC/PE",Investments_Clean!$F$2:$F$150,"Accepted"))>0,1,0)) | BN51: =IF(BL51=0,"",IF((COUNTIFS(Investments_Clean!$A$2:$A$150,A51,Investments_Clean!$D$2:$D$150,"Angel",Investments_Clean!$F$2:$F$150,"Accepted"))>0,1,0)) | BO51: =IF(BL51=0,"",IF((COUNTIFS(Investments_Clean!$A$2:$A$150,A51,Investments_Clean!$D$2:$D$150,"Accelerator",Investments_Clean!$F$2:$F$150,"Accepted"))>0,1,0)) | BP51: =IF(BL51=0,"",IF((COUNTIFS(Investments_Clean!$A$2:$A$150,A51,Investments_Clean!$D$2:$D$150,"Corporate",Investments_Clean!$F$2:$F$150,"Accepted"))>0,1,0)) | BQ51: =IF(BL51=0,"",IF((COUNTIFS(Investments_Clean!$A$2:$A$150,A51,Investments_Clean!$D$2:$D$150,"Government",Investments_Clean!$F$2:$F$150,"Accepted"))>0,1,0)) | BR51: =IF(BL51=0,"",IF((COUNTIFS(Investments_Clean!$A$2:$A$150,A51,Investments_Clean!$D$2:$D$150,"Grant/Philanthropic",Investments_Clean!$F$2:$F$150,"Accepted")+COUNTIFS(Investments_Clean!$A$2:$A$150,A51,Investments_Clean!$D$2:$D$150,"DFI/Impact",Investments_Clean!$F$2:$F$150,"Accepted"))>0,1,0)) | CA51: 0 | CC51: =IF(I51="","",IFERROR(IF(INDEX(Macro_Lookup!$B$2:$B$31,MATCH(I51,Macro_Lookup!$A$2:$A$31,0))="","",INDEX(Macro_Lookup!$B$2:$B$31,MATCH(I51,Macro_Lookup!$A$2:$A$31,0))),"")) | CD51: =IF(I51="","",IFERROR(IF(INDEX(Macro_Lookup!$C$2:$C$31,MATCH(I51,Macro_Lookup!$A$2:$A$31,0))="","",INDEX(Macro_Lookup!$C$2:$C$31,MATCH(I51,Macro_Lookup!$A$2:$A$31,0))),"")) | CE51: =IF(BJ51="","",IFERROR(IF(INDEX(Macro_Lookup!$B$2:$B$31,MATCH(BJ51,Macro_Lookup!$A$2:$A$31,0))="","",INDEX(Macro_Lookup!$B$2:$B$31,MATCH(BJ51,Macro_Lookup!$A$2:$A$31,0))),"")) | CF51: =IF(BJ51="","",IFERROR(IF(INDEX(Macro_Lookup!$C$2:$C$31,MATCH(BJ51,Macro_Lookup!$A$2:$A$31,0))="","",INDEX(Macro_Lookup!$C$2:$C$31,MATCH(BJ51,Macro_Lookup!$A$2:$A$31,0))),"")) | CG51: 8 | CH51: Original 100 (BD-ST-001..100); see Version_Log v1 (2026-10-06) | CI51: 2026-10-06
A52: BD-ST-051 | B52: Praava Health | C52: Bangladesh | D52: Dhaka | E52: 0 | F52: Independent startup | I52: 2018 | K52: year | L52: 46295 | M52: =IF(I52="","",(YEAR(L52)-I52)*12+MONTH(L52)-IF(J52="",1,J52)) -> 104 | N52: =IF(M52="","",ROUND(M52/12,2)) -> 8.67 | O52: HealthTech | P52: HealthTech | Q52: Hybrid (B2C Clinics & Digital Telehealth / Diagnostics) | R52: 0 | S52: 1 | T52: 0 | U52: 0 | V52: 0 | W52: 0 | X52: Live and Scaling | Y52: 3 | Z52: 1 | AA52: 0 | AB52: Fast Company World Changing Ideas, Harvard Business School Case Study | AF52: =IF(SUMIF(Founders_Clean!$A$2:$A$159,A52,Founders_Clean!$C$2:$C$159)=0,"",SUMIF(Founders_Clean!$A$2:$A$159,A52,Founders_Clean!$C$2:$C$159)) -> 1 | AG52: =IF(AF52="","",SUMIF(Founders_Clean!$A$2:$A$159,A52,Founders_Clean!$D$2:$D$159)) -> 0 | AH52: =IF(AF52="","",SUMIF(Founders_Clean!$A$2:$A$159,A52,Founders_Clean!$E$2:$E$159)) -> 1 | AI52: =IF(AF52="","",IF((AG52+AH52)=0,"",AH52/(AG52+AH52))) -> 1 | AJ52: =IF(AI52="","",IF(AH52>0,1,0)) -> 1 | AK52: =IF(AI52="","",ROUND(1-(AI52^2+(1-AI52)^2),3)) -> 0 | AL52: 47.5 | AM52: 2 | AN52: Master's/MBA/professional | AO52: 0 | AP52: 0 | AQ52: 0 | AR52: 20 | AS52: 20 | AX52: Active | AY52: High | BA52: 0 | BB52: 0 | BC52: 0 | BF52: =IF(OR(I52="",BC52=""),"",IF(BC52=1,(BD52-I52)*12+IF(BE52="",7,BE52)-IF(J52="",1,J52),M52)) -> 104 | BG52: 1 | BH52: 10600000 | BI52: cumulative | BJ52: 2021 | BK52: 1 | BL52: =COUNTIFS(Investments_Clean!$A$2:$A$150,A52,Investments_Clean!$F$2:$F$150,"Accepted") -> 1 | BM52: =IF(BL52=0,"",IF((COUNTIFS(Investments_Clean!$A$2:$A$150,A52,Investments_Clean!$D$2:$D$150,"VC/PE",Investments_Clean!$F$2:$F$150,"Accepted"))>0,1,0)) -> 1 | BN52: =IF(BL52=0,"",IF((COUNTIFS(Investments_Clean!$A$2:$A$150,A52,Investments_Clean!$D$2:$D$150,"Angel",Investments_Clean!$F$2:$F$150,"Accepted"))>0,1,0)) -> 0 | BO52: =IF(BL52=0,"",IF((COUNTIFS(Investments_Clean!$A$2:$A$150,A52,Investments_Clean!$D$2:$D$150,"Accelerator",Investments_Clean!$F$2:$F$150,"Accepted"))>0,1,0)) -> 0 | BP52: =IF(BL52=0,"",IF((COUNTIFS(Investments_Clean!$A$2:$A$150,A52,Investments_Clean!$D$2:$D$150,"Corporate",Investments_Clean!$F$2:$F$150,"Accepted"))>0,1,0)) -> 0 | BQ52: =IF(BL52=0,"",IF((COUNTIFS(Investments_Clean!$A$2:$A$150,A52,Investments_Clean!$D$2:$D$150,"Government",Investments_Clean!$F$2:$F$150,"Accepted"))>0,1,0)) -> 0 | BR52: =IF(BL52=0,"",IF((COUNTIFS(Investments_Clean!$A$2:$A$150,A52,Investments_Clean!$D$2:$D$150,"Grant/Philanthropic",Investments_Clean!$F$2:$F$150,"Accepted")+COUNTIFS(Investments_Clean!$A$2:$A$150,A52,Investments_Clean!$D$2:$D$150,"DFI/Impact",Investments_Clean!$F$2:$F$150,"Accepted"))>0,1,0)) -> 0 | CA52: 0 | CC52: =IF(I52="","",IFERROR(IF(INDEX(Macro_Lookup!$B$2:$B$31,MATCH(I52,Macro_Lookup!$A$2:$A$31,0))="","",INDEX(Macro_Lookup!$B$2:$B$31,MATCH(I52,Macro_Lookup!$A$2:$A$31,0))),"")) | CD52: =IF(I52="","",IFERROR(IF(INDEX(Macro_Lookup!$C$2:$C$31,MATCH(I52,Macro_Lookup!$A$2:$A$31,0))="","",INDEX(Macro_Lookup!$C$2:$C$31,MATCH(I52,Macro_Lookup!$A$2:$A$31,0))),"")) | CE52: =IF(BJ52="","",IFERROR(IF(INDEX(Macro_Lookup!$B$2:$B$31,MATCH(BJ52,Macro_Lookup!$A$2:$A$31,0))="","",INDEX(Macro_Lookup!$B$2:$B$31,MATCH(BJ52,Macro_Lookup!$A$2:$A$31,0))),"")) | CF52: =IF(BJ52="","",IFERROR(IF(INDEX(Macro_Lookup!$C$2:$C$31,MATCH(BJ52,Macro_Lookup!$A$2:$A$31,0))="","",INDEX(Macro_Lookup!$C$2:$C$31,MATCH(BJ52,Macro_Lookup!$A$2:$A$31,0))),"")) | CG52: 3 | CH52: Original 100 (BD-ST-001..100); see Version_Log v1 (2026-10-06) | CI52: 2026-10-06
A53: BD-ST-052 | B53: DocTime | C53: Bangladesh | D53: Dhaka | E53: 0 | F53: Independent startup | I53: 2020 | K53: year | L53: 46295 | M53: =IF(I53="","",(YEAR(L53)-I53)*12+MONTH(L53)-IF(J53="",1,J53)) -> 80 | N53: =IF(M53="","",ROUND(M53/12,2)) -> 6.67 | O53: HealthTech / Telemedicine | P53: HealthTech | Q53: B2C / B2B (Corporate Health Packages) | R53: 1 | S53: 1 | T53: 0 | U53: 0 | V53: 0 | W53: 0 | X53: Live and Scaling | Y53: 3 | Z53: 1 | AA53: 1 | AB53: GP Accelerator | AF53: =IF(SUMIF(Founders_Clean!$A$2:$A$159,A53,Founders_Clean!$C$2:$C$159)=0,"",SUMIF(Founders_Clean!$A$2:$A$159,A53,Founders_Clean!$C$2:$C$159)) -> 2 | AG53: =IF(AF53="","",SUMIF(Founders_Clean!$A$2:$A$159,A53,Founders_Clean!$D$2:$D$159)) -> 2 | AH53: =IF(AF53="","",SUMIF(Founders_Clean!$A$2:$A$159,A53,Founders_Clean!$E$2:$E$159)) -> 0 | AI53: =IF(AF53="","",IF((AG53+AH53)=0,"",AH53/(AG53+AH53))) -> 0 | AJ53: =IF(AI53="","",IF(AH53>0,1,0)) -> 0 | AK53: =IF(AI53="","",ROUND(1-(AI53^2+(1-AI53)^2),3)) -> 0 | AL53: 27.5 | AQ53: 1 | AT53: 6 | AU53: 1-10 | AV53: LinkedIn (Public_Macro_Data) | AX53: Active | AY53: High | BA53: 0 | BB53: 0 | BC53: 0 | BF53: =IF(OR(I53="",BC53=""),"",IF(BC53=1,(BD53-I53)*12+IF(BE53="",7,BE53)-IF(J53="",1,J53),M53)) -> 80 | BK53: 1 | BL53: =COUNTIFS(Investments_Clean!$A$2:$A$150,A53,Investments_Clean!$F$2:$F$150,"Accepted") -> 1 | BM53: =IF(BL53=0,"",IF((COUNTIFS(Investments_Clean!$A$2:$A$150,A53,Investments_Clean!$D$2:$D$150,"VC/PE",Investments_Clean!$F$2:$F$150,"Accepted"))>0,1,0)) -> 0 | BN53: =IF(BL53=0,"",IF((COUNTIFS(Investments_Clean!$A$2:$A$150,A53,Investments_Clean!$D$2:$D$150,"Angel",Investments_Clean!$F$2:$F$150,"Accepted"))>0,1,0)) -> 0 | BO53: =IF(BL53=0,"",IF((COUNTIFS(Investments_Clean!$A$2:$A$150,A53,Investments_Clean!$D$2:$D$150,"Accelerator",Investments_Clean!$F$2:$F$150,"Accepted"))>0,1,0)) -> 1 | BP53: =IF(BL53=0,"",IF((COUNTIFS(Investments_Clean!$A$2:$A$150,A53,Investments_Clean!$D$2:$D$150,"Corporate",Investments_Clean!$F$2:$F$150,"Accepted"))>0,1,0)) -> 0 | BQ53: =IF(BL53=0,"",IF((COUNTIFS(Investments_Clean!$A$2:$A$150,A53,Investments_Clean!$D$2:$D$150,"Government",Investments_Clean!$F$2:$F$150,"Accepted"))>0,1,0)) -> 0 | BR53: =IF(BL53=0,"",IF((COUNTIFS(Investments_Clean!$A$2:$A$150,A53,Investments_Clean!$D$2:$D$150,"Grant/Philanthropic",Investments_Clean!$F$2:$F$150,"Accepted")+COUNTIFS(Investments_Clean!$A$2:$A$150,A53,Investments_Clean!$D$2:$D$150,"DFI/Impact",Investments_Clean!$F$2:$F$150,"Accepted"))>0,1,0)) -> 0 | BY53: 1000000 | BZ53: 4.7 | CA53: 1 | CC53: =IF(I53="","",IFERROR(IF(INDEX(Macro_Lookup!$B$2:$B$31,MATCH(I53,Macro_Lookup!$A$2:$A$31,0))="","",INDEX(Macro_Lookup!$B$2:$B$31,MATCH(I53,Macro_Lookup!$A$2:$A$31,0))),"")) | CD53: =IF(I53="","",IFERROR(IF(INDEX(Macro_Lookup!$C$2:$C$31,MATCH(I53,Macro_Lookup!$A$2:$A$31,0))="","",INDEX(Macro_Lookup!$C$2:$C$31,MATCH(I53,Macro_Lookup!$A$2:$A$31,0))),"")) | CE53: =IF(BJ53="","",IFERROR(IF(INDEX(Macro_Lookup!$B$2:$B$31,MATCH(BJ53,Macro_Lookup!$A$2:$A$31,0))="","",INDEX(Macro_Lookup!$B$2:$B$31,MATCH(BJ53,Macro_Lookup!$A$2:$A$31,0))),"")) | CF53: =IF(BJ53="","",IFERROR(IF(INDEX(Macro_Lookup!$C$2:$C$31,MATCH(BJ53,Macro_Lookup!$A$2:$A$31,0))="","",INDEX(Macro_Lookup!$C$2:$C$31,MATCH(BJ53,Macro_Lookup!$A$2:$A$31,0))),"")) | CG53: 5 | CH53: Original 100 (BD-ST-001..100); see Version_Log v1 (2026-10-06) | CI53: 2026-10-06
A54: BD-ST-053 | B54: Arogga | C54: Bangladesh | D54: Dhaka | E54: 0 | F54: Independent startup | I54: 2020 | K54: year | L54: 46295 | M54: =IF(I54="","",(YEAR(L54)-I54)*12+MONTH(L54)-IF(J54="",1,J54)) -> 80 | N54: =IF(M54="","",ROUND(M54/12,2)) -> 6.67 | O54: HealthTech / E-pharmacy | P54: HealthTech | Q54: B2C / E-commerce | R54: 0 | S54: 1 | T54: 0 | U54: 0 | V54: 0 | W54: 0 | X54: Live and Scaling | Y54: 3 | Z54: 1 | AA54: 1 | AB54: Y Combinator (YC W21), Surge (Peak XV Partners) | AF54: =IF(SUMIF(Founders_Clean!$A$2:$A$159,A54,Founders_Clean!$C$2:$C$159)=0,"",SUMIF(Founders_Clean!$A$2:$A$159,A54,Founders_Clean!$C$2:$C$159)) -> 4 | AG54: =IF(AF54="","",SUMIF(Founders_Clean!$A$2:$A$159,A54,Founders_Clean!$D$2:$D$159)) -> 3 | AH54: =IF(AF54="","",SUMIF(Founders_Clean!$A$2:$A$159,A54,Founders_Clean!$E$2:$E$159)) -> 1 | AI54: =IF(AF54="","",IF((AG54+AH54)=0,"",AH54/(AG54+AH54))) -> 0.25 | AJ54: =IF(AI54="","",IF(AH54>0,1,0)) -> 1 | AK54: =IF(AI54="","",ROUND(1-(AI54^2+(1-AI54)^2),3)) -> 0.375 | AL54: 27.5 | AO54: 0 | AP54: 0 | AQ54: 1 | AR54: 10 | AS54: 10 | AX54: Active | AY54: High | BA54: 0 | BB54: 0 | BC54: 0 | BF54: =IF(OR(I54="",BC54=""),"",IF(BC54=1,(BD54-I54)*12+IF(BE54="",7,BE54)-IF(J54="",1,J54),M54)) -> 80 | BG54: 1 | BH54: 5500000 | BI54: cumulative | BJ54: 2023 | BK54: 1 | BL54: =COUNTIFS(Investments_Clean!$A$2:$A$150,A54,Investments_Clean!$F$2:$F$150,"Accepted") -> 5 | BM54: =IF(BL54=0,"",IF((COUNTIFS(Investments_Clean!$A$2:$A$150,A54,Investments_Clean!$D$2:$D$150,"VC/PE",Investments_Clean!$F$2:$F$150,"Accepted"))>0,1,0)) -> 1 | BN54: =IF(BL54=0,"",IF((COUNTIFS(Investments_Clean!$A$2:$A$150,A54,Investments_Clean!$D$2:$D$150,"Angel",Investments_Clean!$F$2:$F$150,"Accepted"))>0,1,0)) -> 1 | BO54: =IF(BL54=0,"",IF((COUNTIFS(Investments_Clean!$A$2:$A$150,A54,Investments_Clean!$D$2:$D$150,"Accelerator",Investments_Clean!$F$2:$F$150,"Accepted"))>0,1,0)) -> 1 | BP54: =IF(BL54=0,"",IF((COUNTIFS(Investments_Clean!$A$2:$A$150,A54,Investments_Clean!$D$2:$D$150,"Corporate",Investments_Clean!$F$2:$F$150,"Accepted"))>0,1,0)) -> 0 | BQ54: =IF(BL54=0,"",IF((COUNTIFS(Investments_Clean!$A$2:$A$150,A54,Investments_Clean!$D$2:$D$150,"Government",Investments_Clean!$F$2:$F$150,"Accepted"))>0,1,0)) -> 0 | BR54: =IF(BL54=0,"",IF((COUNTIFS(Investments_Clean!$A$2:$A$150,A54,Investments_Clean!$D$2:$D$150,"Grant/Philanthropic",Investments_Clean!$F$2:$F$150,"Accepted")+COUNTIFS(Investments_Clean!$A$2:$A$150,A54,Investments_Clean!$D$2:$D$150,"DFI/Impact",Investments_Clean!$F$2:$F$150,"Accepted"))>0,1,0)) -> 0 | CA54: 0 | CC54: =IF(I54="","",IFERROR(IF(INDEX(Macro_Lookup!$B$2:$B$31,MATCH(I54,Macro_Lookup!$A$2:$A$31,0))="","",INDEX(Macro_Lookup!$B$2:$B$31,MATCH(I54,Macro_Lookup!$A$2:$A$31,0))),"")) | CD54: =IF(I54="","",IFERROR(IF(INDEX(Macro_Lookup!$C$2:$C$31,MATCH(I54,Macro_Lookup!$A$2:$A$31,0))="","",INDEX(Macro_Lookup!$C$2:$C$31,MATCH(I54,Macro_Lookup!$A$2:$A$31,0))),"")) | CE54: =IF(BJ54="","",IFERROR(IF(INDEX(Macro_Lookup!$B$2:$B$31,MATCH(BJ54,Macro_Lookup!$A$2:$A$31,0))="","",INDEX(Macro_Lookup!$B$2:$B$31,MATCH(BJ54,Macro_Lookup!$A$2:$A$31,0))),"")) | CF54: =IF(BJ54="","",IFERROR(IF(INDEX(Macro_Lookup!$C$2:$C$31,MATCH(BJ54,Macro_Lookup!$A$2:$A$31,0))="","",INDEX(Macro_Lookup!$C$2:$C$31,MATCH(BJ54,Macro_Lookup!$A$2:$A$31,0))),"")) | CG54: 4 | CH54: Original 100 (BD-ST-001..100); see Version_Log v1 (2026-10-06) | CI54: 2026-10-06
A55: BD-ST-054 | B55: Moner Bondhu | C55: Bangladesh | D55: Dhaka | E55: 0 | F55: Independent startup | I55: 2016 | K55: year | L55: 46295 | M55: =IF(I55="","",(YEAR(L55)-I55)*12+MONTH(L55)-IF(J55="",1,J55)) -> 128 | N55: =IF(M55="","",ROUND(M55/12,2)) -> 10.67 | O55: HealthTech / Mental Health | P55: HealthTech | Q55: B2C / B2B (Corporate Wellness Programs) | R55: 1 | S55: 1 | T55: 0 | U55: 0 | V55: 0 | W55: 0 | X55: Live and Scaling | Y55: 3 | Z55: 1 | AA55: 1 | AB55: Accelerating Asia, Tommy Hilfiger Fashion Frontier Challenge | AC55: 1 | AD55: 108000 | AE55: Investment_Decisions | AF55: =IF(SUMIF(Founders_Clean!$A$2:$A$159,A55,Founders_Clean!$C$2:$C$159)=0,"",SUMIF(Founders_Clean!$A$2:$A$159,A55,Founders_Clean!$C$2:$C$159)) -> 1 | AG55: =IF(AF55="","",SUMIF(Founders_Clean!$A$2:$A$159,A55,Founders_Clean!$D$2:$D$159)) -> 0 | AH55: =IF(AF55="","",SUMIF(Founders_Clean!$A$2:$A$159,A55,Founders_Clean!$E$2:$E$159)) -> 1 | AI55: =IF(AF55="","",IF((AG55+AH55)=0,"",AH55/(AG55+AH55))) -> 1 | AJ55: =IF(AI55="","",IF(AH55>0,1,0)) -> 1 | AK55: =IF(AI55="","",ROUND(1-(AI55^2+(1-AI55)^2),3)) -> 0 | AL55: 50 | AM55: 2 | AN55: Master's/MBA/professional | AO55: 0 | AP55: 0 | AQ55: 0 | AR55: 13 | AS55: 13 | AT55: 30.5 | AU55: 11-50 | AV55: Founders_Team | AX55: Active | AY55: High | BA55: 0 | BB55: 0 | BC55: 0 | BF55: =IF(OR(I55="",BC55=""),"",IF(BC55=1,(BD55-I55)*12+IF(BE55="",7,BE55)-IF(J55="",1,J55),M55)) -> 128 | BG55: 1 | BH55: 108000 | BI55: round | BJ55: 2023 | BK55: 1 | BL55: =COUNTIFS(Investments_Clean!$A$2:$A$150,A55,Investments_Clean!$F$2:$F$150,"Accepted") -> 3 | BM55: =IF(BL55=0,"",IF((COUNTIFS(Investments_Clean!$A$2:$A$150,A55,Investments_Clean!$D$2:$D$150,"VC/PE",Investments_Clean!$F$2:$F$150,"Accepted"))>0,1,0)) -> 0 | BN55: =IF(BL55=0,"",IF((COUNTIFS(Investments_Clean!$A$2:$A$150,A55,Investments_Clean!$D$2:$D$150,"Angel",Investments_Clean!$F$2:$F$150,"Accepted"))>0,1,0)) -> 0 | BO55: =IF(BL55=0,"",IF((COUNTIFS(Investments_Clean!$A$2:$A$150,A55,Investments_Clean!$D$2:$D$150,"Accelerator",Investments_Clean!$F$2:$F$150,"Accepted"))>0,1,0)) -> 1 | BP55: =IF(BL55=0,"",IF((COUNTIFS(Investments_Clean!$A$2:$A$150,A55,Investments_Clean!$D$2:$D$150,"Corporate",Investments_Clean!$F$2:$F$150,"Accepted"))>0,1,0)) -> 0 | BQ55: =IF(BL55=0,"",IF((COUNTIFS(Investments_Clean!$A$2:$A$150,A55,Investments_Clean!$D$2:$D$150,"Government",Investments_Clean!$F$2:$F$150,"Accepted"))>0,1,0)) -> 0 | BR55: =IF(BL55=0,"",IF((COUNTIFS(Investments_Clean!$A$2:$A$150,A55,Investments_Clean!$D$2:$D$150,"Grant/Philanthropic",Investments_Clean!$F$2:$F$150,"Accepted")+COUNTIFS(Investments_Clean!$A$2:$A$150,A55,Investments_Clean!$D$2:$D$150,"DFI/Impact",Investments_Clean!$F$2:$F$150,"Accepted"))>0,1,0)) -> 1 | CA55: 0 | CC55: =IF(I55="","",IFERROR(IF(INDEX(Macro_Lookup!$B$2:$B$31,MATCH(I55,Macro_Lookup!$A$2:$A$31,0))="","",INDEX(Macro_Lookup!$B$2:$B$31,MATCH(I55,Macro_Lookup!$A$2:$A$31,0))),"")) | CD55: =IF(I55="","",IFERROR(IF(INDEX(Macro_Lookup!$C$2:$C$31,MATCH(I55,Macro_Lookup!$A$2:$A$31,0))="","",INDEX(Macro_Lookup!$C$2:$C$31,MATCH(I55,Macro_Lookup!$A$2:$A$31,0))),"")) | CE55: =IF(BJ55="","",IFERROR(IF(INDEX(Macro_Lookup!$B$2:$B$31,MATCH(BJ55,Macro_Lookup!$A$2:$A$31,0))="","",INDEX(Macro_Lookup!$B$2:$B$31,MATCH(BJ55,Macro_Lookup!$A$2:$A$31,0))),"")) | CF55: =IF(BJ55="","",IFERROR(IF(INDEX(Macro_Lookup!$C$2:$C$31,MATCH(BJ55,Macro_Lookup!$A$2:$A$31,0))="","",INDEX(Macro_Lookup!$C$2:$C$31,MATCH(BJ55,Macro_Lookup!$A$2:$A$31,0))),"")) | CG55: 1 | CH55: Original 100 (BD-ST-001..100); see Version_Log v1 (2026-10-06) | CI55: 2026-10-06
A56: BD-ST-055 | B56: Maya (Myalogy) | C56: Bangladesh | D56: Dhaka | E56: 0 | F56: Independent startup | I56: 2015 | K56: year | L56: 46295 | M56: =IF(I56="","",(YEAR(L56)-I56)*12+MONTH(L56)-IF(J56="",1,J56)) -> 140 | N56: =IF(M56="","",ROUND(M56/12,2)) -> 11.67 | O56: HealthTech / Telehealth | P56: HealthTech | Q56: B2C / B2B (Corporate Healthcare Solutions) | R56: 1 | S56: 1 | T56: 0 | U56: 0 | V56: 0 | W56: 0 | X56: Live and Scaling | Y56: 3 | Z56: 1 | AA56: 1 | AB56: Google for Startups Accelerator, Spring Accelerator | AC56: 1 | AE56: master (amount undisclosed) | AF56: =IF(SUMIF(Founders_Clean!$A$2:$A$159,A56,Founders_Clean!$C$2:$C$159)=0,"",SUMIF(Founders_Clean!$A$2:$A$159,A56,Founders_Clean!$C$2:$C$159)) -> 1 | AG56: =IF(AF56="","",SUMIF(Founders_Clean!$A$2:$A$159,A56,Founders_Clean!$D$2:$D$159)) -> 0 | AH56: =IF(AF56="","",SUMIF(Founders_Clean!$A$2:$A$159,A56,Founders_Clean!$E$2:$E$159)) -> 1 | AI56: =IF(AF56="","",IF((AG56+AH56)=0,"",AH56/(AG56+AH56))) -> 1 | AJ56: =IF(AI56="","",IF(AH56>0,1,0)) -> 1 | AK56: =IF(AI56="","",ROUND(1-(AI56^2+(1-AI56)^2),3)) -> 0 | AL56: 50 | AM56: 1 | AN56: Bachelor's | AO56: 0 | AP56: 0 | AQ56: 0 | AX56: Active | AY56: High | BA56: 0 | BB56: 0 | BC56: 0 | BF56: =IF(OR(I56="",BC56=""),"",IF(BC56=1,(BD56-I56)*12+IF(BE56="",7,BE56)-IF(J56="",1,J56),M56)) -> 140 | BG56: 1 | BH56: 2200000 | BI56: round | BJ56: 2021 | BK56: 1 | BL56: =COUNTIFS(Investments_Clean!$A$2:$A$150,A56,Investments_Clean!$F$2:$F$150,"Accepted") -> 5 | BM56: =IF(BL56=0,"",IF((COUNTIFS(Investments_Clean!$A$2:$A$150,A56,Investments_Clean!$D$2:$D$150,"VC/PE",Investments_Clean!$F$2:$F$150,"Accepted"))>0,1,0)) -> 1 | BN56: =IF(BL56=0,"",IF((COUNTIFS(Investments_Clean!$A$2:$A$150,A56,Investments_Clean!$D$2:$D$150,"Angel",Investments_Clean!$F$2:$F$150,"Accepted"))>0,1,0)) -> 0 | BO56: =IF(BL56=0,"",IF((COUNTIFS(Investments_Clean!$A$2:$A$150,A56,Investments_Clean!$D$2:$D$150,"Accelerator",Investments_Clean!$F$2:$F$150,"Accepted"))>0,1,0)) -> 1 | BP56: =IF(BL56=0,"",IF((COUNTIFS(Investments_Clean!$A$2:$A$150,A56,Investments_Clean!$D$2:$D$150,"Corporate",Investments_Clean!$F$2:$F$150,"Accepted"))>0,1,0)) -> 0 | BQ56: =IF(BL56=0,"",IF((COUNTIFS(Investments_Clean!$A$2:$A$150,A56,Investments_Clean!$D$2:$D$150,"Government",Investments_Clean!$F$2:$F$150,"Accepted"))>0,1,0)) -> 0 | BR56: =IF(BL56=0,"",IF((COUNTIFS(Investments_Clean!$A$2:$A$150,A56,Investments_Clean!$D$2:$D$150,"Grant/Philanthropic",Investments_Clean!$F$2:$F$150,"Accepted")+COUNTIFS(Investments_Clean!$A$2:$A$150,A56,Investments_Clean!$D$2:$D$150,"DFI/Impact",Investments_Clean!$F$2:$F$150,"Accepted"))>0,1,0)) -> 1 | BY56: 10000000 | CA56: 1 | CC56: =IF(I56="","",IFERROR(IF(INDEX(Macro_Lookup!$B$2:$B$31,MATCH(I56,Macro_Lookup!$A$2:$A$31,0))="","",INDEX(Macro_Lookup!$B$2:$B$31,MATCH(I56,Macro_Lookup!$A$2:$A$31,0))),"")) | CD56: =IF(I56="","",IFERROR(IF(INDEX(Macro_Lookup!$C$2:$C$31,MATCH(I56,Macro_Lookup!$A$2:$A$31,0))="","",INDEX(Macro_Lookup!$C$2:$C$31,MATCH(I56,Macro_Lookup!$A$2:$A$31,0))),"")) | CE56: =IF(BJ56="","",IFERROR(IF(INDEX(Macro_Lookup!$B$2:$B$31,MATCH(BJ56,Macro_Lookup!$A$2:$A$31,0))="","",INDEX(Macro_Lookup!$B$2:$B$31,MATCH(BJ56,Macro_Lookup!$A$2:$A$31,0))),"")) | CF56: =IF(BJ56="","",IFERROR(IF(INDEX(Macro_Lookup!$C$2:$C$31,MATCH(BJ56,Macro_Lookup!$A$2:$A$31,0))="","",INDEX(Macro_Lookup!$C$2:$C$31,MATCH(BJ56,Macro_Lookup!$A$2:$A$31,0))),"")) | CG56: 3 | CH56: Original 100 (BD-ST-001..100); see Version_Log v1 (2026-10-06) | CI56: 2026-10-06
A57: BD-ST-056 | B57: Jeeon | C57: Bangladesh | D57: Dhaka | E57: 0 | F57: Independent startup | I57: 2014 | K57: year | L57: 46295 | M57: =IF(I57="","",(YEAR(L57)-I57)*12+MONTH(L57)-IF(J57="",1,J57)) -> 152 | N57: =IF(M57="","",ROUND(M57/12,2)) -> 12.67 | O57: HealthTech / Rural Health | P57: HealthTech | Q57: B2B / Marketplace | R57: 1 | S57: 0 | T57: 1 | U57: 0 | V57: 0 | W57: 0 | X57: Live and Scaling | Y57: 3 | Z57: 1 | AA57: 1 | AB57: Transform Health Challenge, Echoing Green | AC57: 1 | AE57: master (amount undisclosed) | AF57: =IF(SUMIF(Founders_Clean!$A$2:$A$159,A57,Founders_Clean!$C$2:$C$159)=0,"",SUMIF(Founders_Clean!$A$2:$A$159,A57,Founders_Clean!$C$2:$C$159)) -> 1 | AG57: =IF(AF57="","",SUMIF(Founders_Clean!$A$2:$A$159,A57,Founders_Clean!$D$2:$D$159)) -> 1 | AH57: =IF(AF57="","",SUMIF(Founders_Clean!$A$2:$A$159,A57,Founders_Clean!$E$2:$E$159)) -> 0 | AI57: =IF(AF57="","",IF((AG57+AH57)=0,"",AH57/(AG57+AH57))) -> 0 | AJ57: =IF(AI57="","",IF(AH57>0,1,0)) -> 0 | AK57: =IF(AI57="","",ROUND(1-(AI57^2+(1-AI57)^2),3)) -> 0 | AL57: 25 | AM57: 2 | AN57: Master's/MBA/professional | AO57: 1 | AP57: 1 | AQ57: 1 | AR57: 6.5 | AS57: 6.5 | AT57: 6 | AU57: 1-10 | AV57: Founders_Team | AX57: Active | AY57: High | BA57: 0 | BB57: 0 | BC57: 0 | BF57: =IF(OR(I57="",BC57=""),"",IF(BC57=1,(BD57-I57)*12+IF(BE57="",7,BE57)-IF(J57="",1,J57),M57)) -> 152 | BG57: 1 | BI57: unknown | BK57: 1 | BL57: =COUNTIFS(Investments_Clean!$A$2:$A$150,A57,Investments_Clean!$F$2:$F$150,"Accepted") -> 4 | BM57: =IF(BL57=0,"",IF((COUNTIFS(Investments_Clean!$A$2:$A$150,A57,Investments_Clean!$D$2:$D$150,"VC/PE",Investments_Clean!$F$2:$F$150,"Accepted"))>0,1,0)) -> 0 | BN57: =IF(BL57=0,"",IF((COUNTIFS(Investments_Clean!$A$2:$A$150,A57,Investments_Clean!$D$2:$D$150,"Angel",Investments_Clean!$F$2:$F$150,"Accepted"))>0,1,0)) -> 0 | BO57: =IF(BL57=0,"",IF((COUNTIFS(Investments_Clean!$A$2:$A$150,A57,Investments_Clean!$D$2:$D$150,"Accelerator",Investments_Clean!$F$2:$F$150,"Accepted"))>0,1,0)) -> 0 | BP57: =IF(BL57=0,"",IF((COUNTIFS(Investments_Clean!$A$2:$A$150,A57,Investments_Clean!$D$2:$D$150,"Corporate",Investments_Clean!$F$2:$F$150,"Accepted"))>0,1,0)) -> 0 | BQ57: =IF(BL57=0,"",IF((COUNTIFS(Investments_Clean!$A$2:$A$150,A57,Investments_Clean!$D$2:$D$150,"Government",Investments_Clean!$F$2:$F$150,"Accepted"))>0,1,0)) -> 0 | BR57: =IF(BL57=0,"",IF((COUNTIFS(Investments_Clean!$A$2:$A$150,A57,Investments_Clean!$D$2:$D$150,"Grant/Philanthropic",Investments_Clean!$F$2:$F$150,"Accepted")+COUNTIFS(Investments_Clean!$A$2:$A$150,A57,Investments_Clean!$D$2:$D$150,"DFI/Impact",Investments_Clean!$F$2:$F$150,"Accepted"))>0,1,0)) -> 1 | CA57: 0 | CC57: =IF(I57="","",IFERROR(IF(INDEX(Macro_Lookup!$B$2:$B$31,MATCH(I57,Macro_Lookup!$A$2:$A$31,0))="","",INDEX(Macro_Lookup!$B$2:$B$31,MATCH(I57,Macro_Lookup!$A$2:$A$31,0))),"")) | CD57: =IF(I57="","",IFERROR(IF(INDEX(Macro_Lookup!$C$2:$C$31,MATCH(I57,Macro_Lookup!$A$2:$A$31,0))="","",INDEX(Macro_Lookup!$C$2:$C$31,MATCH(I57,Macro_Lookup!$A$2:$A$31,0))),"")) | CE57: =IF(BJ57="","",IFERROR(IF(INDEX(Macro_Lookup!$B$2:$B$31,MATCH(BJ57,Macro_Lookup!$A$2:$A$31,0))="","",INDEX(Macro_Lookup!$B$2:$B$31,MATCH(BJ57,Macro_Lookup!$A$2:$A$31,0))),"")) | CF57: =IF(BJ57="","",IFERROR(IF(INDEX(Macro_Lookup!$C$2:$C$31,MATCH(BJ57,Macro_Lookup!$A$2:$A$31,0))="","",INDEX(Macro_Lookup!$C$2:$C$31,MATCH(BJ57,Macro_Lookup!$A$2:$A$31,0))),"")) | CG57: 1 | CH57: Original 100 (BD-ST-001..100); see Version_Log v1 (2026-10-06) | CI57: 2026-10-06
A58: BD-ST-057 | B58: MedEasy | C58: Bangladesh | D58: Dhaka | E58: 0 | F58: Independent startup | I58: 2020 | K58: year | L58: 46295 | M58: =IF(I58="","",(YEAR(L58)-I58)*12+MONTH(L58)-IF(J58="",1,J58)) -> 80 | N58: =IF(M58="","",ROUND(M58/12,2)) -> 6.67 | O58: HealthTech / E-pharmacy | P58: HealthTech | Q58: B2C / Health Services | R58: 0 | S58: 1 | T58: 0 | U58: 0 | V58: 0 | W58: 0 | X58: Live and Scaling | Y58: 3 | Z58: 1 | AA58: 1 | AB58: Accelerating Asia (Cohort 8), GP Accelerator | AC58: 1 | AE58: master (amount undisclosed) | AF58: =IF(SUMIF(Founders_Clean!$A$2:$A$159,A58,Founders_Clean!$C$2:$C$159)=0,"",SUMIF(Founders_Clean!$A$2:$A$159,A58,Founders_Clean!$C$2:$C$159)) -> 1 | AG58: =IF(AF58="","",SUMIF(Founders_Clean!$A$2:$A$159,A58,Founders_Clean!$D$2:$D$159)) -> 1 | AH58: =IF(AF58="","",SUMIF(Founders_Clean!$A$2:$A$159,A58,Founders_Clean!$E$2:$E$159)) -> 0 | AI58: =IF(AF58="","",IF((AG58+AH58)=0,"",AH58/(AG58+AH58))) -> 0 | AJ58: =IF(AI58="","",IF(AH58>0,1,0)) -> 0 | AK58: =IF(AI58="","",ROUND(1-(AI58^2+(1-AI58)^2),3)) -> 0 | AL58: 17.5 | AX58: Active | AY58: High | AZ58: MedEasy is the ACQUIRER (bought Alchemy, 2023), not acquired | BA58: 0 | BB58: 1 | BC58: 0 | BF58: =IF(OR(I58="",BC58=""),"",IF(BC58=1,(BD58-I58)*12+IF(BE58="",7,BE58)-IF(J58="",1,J58),M58)) -> 80 | BG58: 1 | BH58: 750000 | BI58: round | BJ58: 2023 | BK58: 1 | BL58: =COUNTIFS(Investments_Clean!$A$2:$A$150,A58,Investments_Clean!$F$2:$F$150,"Accepted") -> 6 | BM58: =IF(BL58=0,"",IF((COUNTIFS(Investments_Clean!$A$2:$A$150,A58,Investments_Clean!$D$2:$D$150,"VC/PE",Investments_Clean!$F$2:$F$150,"Accepted"))>0,1,0)) -> 1 | BN58: =IF(BL58=0,"",IF((COUNTIFS(Investments_Clean!$A$2:$A$150,A58,Investments_Clean!$D$2:$D$150,"Angel",Investments_Clean!$F$2:$F$150,"Accepted"))>0,1,0)) -> 1 | BO58: =IF(BL58=0,"",IF((COUNTIFS(Investments_Clean!$A$2:$A$150,A58,Investments_Clean!$D$2:$D$150,"Accelerator",Investments_Clean!$F$2:$F$150,"Accepted"))>0,1,0)) -> 1 | BP58: =IF(BL58=0,"",IF((COUNTIFS(Investments_Clean!$A$2:$A$150,A58,Investments_Clean!$D$2:$D$150,"Corporate",Investments_Clean!$F$2:$F$150,"Accepted"))>0,1,0)) -> 0 | BQ58: =IF(BL58=0,"",IF((COUNTIFS(Investments_Clean!$A$2:$A$150,A58,Investments_Clean!$D$2:$D$150,"Government",Investments_Clean!$F$2:$F$150,"Accepted"))>0,1,0)) -> 1 | BR58: =IF(BL58=0,"",IF((COUNTIFS(Investments_Clean!$A$2:$A$150,A58,Investments_Clean!$D$2:$D$150,"Grant/Philanthropic",Investments_Clean!$F$2:$F$150,"Accepted")+COUNTIFS(Investments_Clean!$A$2:$A$150,A58,Investments_Clean!$D$2:$D$150,"DFI/Impact",Investments_Clean!$F$2:$F$150,"Accepted"))>0,1,0)) -> 1 | CA58: 0 | CC58: =IF(I58="","",IFERROR(IF(INDEX(Macro_Lookup!$B$2:$B$31,MATCH(I58,Macro_Lookup!$A$2:$A$31,0))="","",INDEX(Macro_Lookup!$B$2:$B$31,MATCH(I58,Macro_Lookup!$A$2:$A$31,0))),"")) | CD58: =IF(I58="","",IFERROR(IF(INDEX(Macro_Lookup!$C$2:$C$31,MATCH(I58,Macro_Lookup!$A$2:$A$31,0))="","",INDEX(Macro_Lookup!$C$2:$C$31,MATCH(I58,Macro_Lookup!$A$2:$A$31,0))),"")) | CE58: =IF(BJ58="","",IFERROR(IF(INDEX(Macro_Lookup!$B$2:$B$31,MATCH(BJ58,Macro_Lookup!$A$2:$A$31,0))="","",INDEX(Macro_Lookup!$B$2:$B$31,MATCH(BJ58,Macro_Lookup!$A$2:$A$31,0))),"")) | CF58: =IF(BJ58="","",IFERROR(IF(INDEX(Macro_Lookup!$C$2:$C$31,MATCH(BJ58,Macro_Lookup!$A$2:$A$31,0))="","",INDEX(Macro_Lookup!$C$2:$C$31,MATCH(BJ58,Macro_Lookup!$A$2:$A$31,0))),"")) | CG58: 6 | CH58: Original 100 (BD-ST-001..100); see Version_Log v1 (2026-10-06) | CI58: 2026-10-06
A59: BD-ST-058 | B59: Doctorola | C59: Bangladesh | D59: Dhaka | E59: 0 | F59: Independent startup | I59: 2015 | K59: year | L59: 46295 | M59: =IF(I59="","",(YEAR(L59)-I59)*12+MONTH(L59)-IF(J59="",1,J59)) -> 140 | N59: =IF(M59="","",ROUND(M59/12,2)) -> 11.67 | O59: HealthTech / Telemedicine | P59: HealthTech | Q59: B2C / Marketplace | R59: 0 | S59: 1 | T59: 1 | U59: 0 | V59: 0 | W59: 0 | X59: Live and Scaling | Y59: 3 | Z59: 1 | AF59: =IF(SUMIF(Founders_Clean!$A$2:$A$159,A59,Founders_Clean!$C$2:$C$159)=0,"",SUMIF(Founders_Clean!$A$2:$A$159,A59,Founders_Clean!$C$2:$C$159)) -> 1 | AG59: =IF(AF59="","",SUMIF(Founders_Clean!$A$2:$A$159,A59,Founders_Clean!$D$2:$D$159)) -> 1 | AH59: =IF(AF59="","",SUMIF(Founders_Clean!$A$2:$A$159,A59,Founders_Clean!$E$2:$E$159)) -> 0 | AI59: =IF(AF59="","",IF((AG59+AH59)=0,"",AH59/(AG59+AH59))) -> 0 | AJ59: =IF(AI59="","",IF(AH59>0,1,0)) -> 0 | AK59: =IF(AI59="","",ROUND(1-(AI59^2+(1-AI59)^2),3)) -> 0 | AL59: 15 | AO59: 1 | AP59: 1 | AQ59: 1 | AX59: Active | AY59: High | AZ59: Founder moved to lead Pulse Healthcare Services; Doctorola status as per source = Active | BA59: 0 | BB59: 0 | BC59: 0 | BF59: =IF(OR(I59="",BC59=""),"",IF(BC59=1,(BD59-I59)*12+IF(BE59="",7,BE59)-IF(J59="",1,J59),M59)) -> 140 | BG59: 1 | BH59: 250000 | BI59: round | BJ59: 2015 | BK59: 1 | BL59: =COUNTIFS(Investments_Clean!$A$2:$A$150,A59,Investments_Clean!$F$2:$F$150,"Accepted") -> 1 | BM59: =IF(BL59=0,"",IF((COUNTIFS(Investments_Clean!$A$2:$A$150,A59,Investments_Clean!$D$2:$D$150,"VC/PE",Investments_Clean!$F$2:$F$150,"Accepted"))>0,1,0)) -> 1 | BN59: =IF(BL59=0,"",IF((COUNTIFS(Investments_Clean!$A$2:$A$150,A59,Investments_Clean!$D$2:$D$150,"Angel",Investments_Clean!$F$2:$F$150,"Accepted"))>0,1,0)) -> 0 | BO59: =IF(BL59=0,"",IF((COUNTIFS(Investments_Clean!$A$2:$A$150,A59,Investments_Clean!$D$2:$D$150,"Accelerator",Investments_Clean!$F$2:$F$150,"Accepted"))>0,1,0)) -> 0 | BP59: =IF(BL59=0,"",IF((COUNTIFS(Investments_Clean!$A$2:$A$150,A59,Investments_Clean!$D$2:$D$150,"Corporate",Investments_Clean!$F$2:$F$150,"Accepted"))>0,1,0)) -> 0 | BQ59: =IF(BL59=0,"",IF((COUNTIFS(Investments_Clean!$A$2:$A$150,A59,Investments_Clean!$D$2:$D$150,"Government",Investments_Clean!$F$2:$F$150,"Accepted"))>0,1,0)) -> 0 | BR59: =IF(BL59=0,"",IF((COUNTIFS(Investments_Clean!$A$2:$A$150,A59,Investments_Clean!$D$2:$D$150,"Grant/Philanthropic",Investments_Clean!$F$2:$F$150,"Accepted")+COUNTIFS(Investments_Clean!$A$2:$A$150,A59,Investments_Clean!$D$2:$D$150,"DFI/Impact",Investments_Clean!$F$2:$F$150,"Accepted"))>0,1,0)) -> 0 | CA59: 0 | CC59: =IF(I59="","",IFERROR(IF(INDEX(Macro_Lookup!$B$2:$B$31,MATCH(I59,Macro_Lookup!$A$2:$A$31,0))="","",INDEX(Macro_Lookup!$B$2:$B$31,MATCH(I59,Macro_Lookup!$A$2:$A$31,0))),"")) | CD59: =IF(I59="","",IFERROR(IF(INDEX(Macro_Lookup!$C$2:$C$31,MATCH(I59,Macro_Lookup!$A$2:$A$31,0))="","",INDEX(Macro_Lookup!$C$2:$C$31,MATCH(I59,Macro_Lookup!$A$2:$A$31,0))),"")) | CE59: =IF(BJ59="","",IFERROR(IF(INDEX(Macro_Lookup!$B$2:$B$31,MATCH(BJ59,Macro_Lookup!$A$2:$A$31,0))="","",INDEX(Macro_Lookup!$B$2:$B$31,MATCH(BJ59,Macro_Lookup!$A$2:$A$31,0))),"")) | CF59: =IF(BJ59="","",IFERROR(IF(INDEX(Macro_Lookup!$C$2:$C$31,MATCH(BJ59,Macro_Lookup!$A$2:$A$31,0))="","",INDEX(Macro_Lookup!$C$2:$C$31,MATCH(BJ59,Macro_Lookup!$A$2:$A$31,0))),"")) | CG59: 6 | CH59: Original 100 (BD-ST-001..100); see Version_Log v1 (2026-10-06) | CI59: 2026-10-06
A60: BD-ST-059 | B60: Doctor Koi | C60: Bangladesh | D60: Dhaka | E60: 0 | F60: Independent startup | I60: 2017 | K60: year | L60: 46295 | M60: =IF(I60="","",(YEAR(L60)-I60)*12+MONTH(L60)-IF(J60="",1,J60)) -> 116 | N60: =IF(M60="","",ROUND(M60/12,2)) -> 9.67 | O60: HealthTech / Telemedicine | P60: HealthTech | Q60: B2B / B2C | R60: 1 | S60: 1 | T60: 0 | U60: 0 | V60: 0 | W60: 0 | X60: Live and Scaling | Y60: 3 | Z60: 1 | AA60: 1 | AB60: GP Accelerator (Cohort 4) | AF60: =IF(SUMIF(Founders_Clean!$A$2:$A$159,A60,Founders_Clean!$C$2:$C$159)=0,"",SUMIF(Founders_Clean!$A$2:$A$159,A60,Founders_Clean!$C$2:$C$159)) -> 2 | AG60: =IF(AF60="","",SUMIF(Founders_Clean!$A$2:$A$159,A60,Founders_Clean!$D$2:$D$159)) -> 2 | AH60: =IF(AF60="","",SUMIF(Founders_Clean!$A$2:$A$159,A60,Founders_Clean!$E$2:$E$159)) -> 0 | AI60: =IF(AF60="","",IF((AG60+AH60)=0,"",AH60/(AG60+AH60))) -> 0 | AJ60: =IF(AI60="","",IF(AH60>0,1,0)) -> 0 | AK60: =IF(AI60="","",ROUND(1-(AI60^2+(1-AI60)^2),3)) -> 0 | AL60: 15 | AX60: Active | AY60: High | BA60: 0 | BB60: 0 | BC60: 0 | BF60: =IF(OR(I60="",BC60=""),"",IF(BC60=1,(BD60-I60)*12+IF(BE60="",7,BE60)-IF(J60="",1,J60),M60)) -> 116 | BG60: 1 | BH60: 500000 | BI60: round | BJ60: 2022 | BK60: 1 | BL60: =COUNTIFS(Investments_Clean!$A$2:$A$150,A60,Investments_Clean!$F$2:$F$150,"Accepted") -> 4 | BM60: =IF(BL60=0,"",IF((COUNTIFS(Investments_Clean!$A$2:$A$150,A60,Investments_Clean!$D$2:$D$150,"VC/PE",Investments_Clean!$F$2:$F$150,"Accepted"))>0,1,0)) -> 1 | BN60: =IF(BL60=0,"",IF((COUNTIFS(Investments_Clean!$A$2:$A$150,A60,Investments_Clean!$D$2:$D$150,"Angel",Investments_Clean!$F$2:$F$150,"Accepted"))>0,1,0)) -> 1 | BO60: =IF(BL60=0,"",IF((COUNTIFS(Investments_Clean!$A$2:$A$150,A60,Investments_Clean!$D$2:$D$150,"Accelerator",Investments_Clean!$F$2:$F$150,"Accepted"))>0,1,0)) -> 1 | BP60: =IF(BL60=0,"",IF((COUNTIFS(Investments_Clean!$A$2:$A$150,A60,Investments_Clean!$D$2:$D$150,"Corporate",Investments_Clean!$F$2:$F$150,"Accepted"))>0,1,0)) -> 0 | BQ60: =IF(BL60=0,"",IF((COUNTIFS(Investments_Clean!$A$2:$A$150,A60,Investments_Clean!$D$2:$D$150,"Government",Investments_Clean!$F$2:$F$150,"Accepted"))>0,1,0)) -> 0 | BR60: =IF(BL60=0,"",IF((COUNTIFS(Investments_Clean!$A$2:$A$150,A60,Investments_Clean!$D$2:$D$150,"Grant/Philanthropic",Investments_Clean!$F$2:$F$150,"Accepted")+COUNTIFS(Investments_Clean!$A$2:$A$150,A60,Investments_Clean!$D$2:$D$150,"DFI/Impact",Investments_Clean!$F$2:$F$150,"Accepted"))>0,1,0)) -> 0 | CA60: 0 | CC60: =IF(I60="","",IFERROR(IF(INDEX(Macro_Lookup!$B$2:$B$31,MATCH(I60,Macro_Lookup!$A$2:$A$31,0))="","",INDEX(Macro_Lookup!$B$2:$B$31,MATCH(I60,Macro_Lookup!$A$2:$A$31,0))),"")) | CD60: =IF(I60="","",IFERROR(IF(INDEX(Macro_Lookup!$C$2:$C$31,MATCH(I60,Macro_Lookup!$A$2:$A$31,0))="","",INDEX(Macro_Lookup!$C$2:$C$31,MATCH(I60,Macro_Lookup!$A$2:$A$31,0))),"")) | CE60: =IF(BJ60="","",IFERROR(IF(INDEX(Macro_Lookup!$B$2:$B$31,MATCH(BJ60,Macro_Lookup!$A$2:$A$31,0))="","",INDEX(Macro_Lookup!$B$2:$B$31,MATCH(BJ60,Macro_Lookup!$A$2:$A$31,0))),"")) | CF60: =IF(BJ60="","",IFERROR(IF(INDEX(Macro_Lookup!$C$2:$C$31,MATCH(BJ60,Macro_Lookup!$A$2:$A$31,0))="","",INDEX(Macro_Lookup!$C$2:$C$31,MATCH(BJ60,Macro_Lookup!$A$2:$A$31,0))),"")) | CG60: 7 | CH60: Original 100 (BD-ST-001..100); see Version_Log v1 (2026-10-06) | CI60: 2026-10-06
